Workbook

Sheet README
A1: DATRE CORPORATION LIMITED - MIS FINALISATION TEMPLATE (HO ACCOUNTS)
A2: Financial year 2026-27 | Rs. in Lacs
A4: FLOW
A5: 1. Factory feeds monthly P&L data -> sheet IN_PLF (column for the month).
A6: 2. Factory / Costing feeds product-wise contribution rows -> sheet IN_Contrib (append rows; FY and Month text must match, e.g. 2026-27 / October).
A7: 3. HO Accounts enters ledger items and adjustments -> sheet IN_HO (admin, salary, adjustments, MT statistics, collections).
A8: 4. Sheet MIS recalculates automatically (same layout as the published 'P&L for the year 2026-27 (Based on Sales)').
A9: 5. Sheet CONTRIB_SUM summarises contribution data by month / customer and cross-checks against MIS.
A10: 6. Sheet CHECK compares MIS output with the published Sept'26 MIS (Apr-Sep) - use as proof of the formula logic. Clear/ignore from Oct'26 onward.
A11: 7. Sheet PY_COMPARE holds the prior-year statistics from the published MIS; FY26-27 rows link live to MIS.
A13: COLOUR CODE
A14: Blue font = hard-coded input. Black = formula. Yellow fill = item to confirm/explain (see notes).
... A36: Paste factory PL figures into the month column of IN_PLF > append contribution rows in IN_Contrib > fill IN_HO for the month > review MIS and CONTRIB_SUM > clear yellow flags.

Sheet MIS
A1: DATRE CORPORATION LIMITED
A2: PROFIT AND LOSS ACCOUNT for the year 2026-27 (Based on Sales)
A3: Rs. In Lacs | R3: Average/Month
A5: PARTICULARS | B5: APR'26 | C5: MAY'26 | D5: JUN'26 | E5: 1st Qtr | F5: JUL'26 | G5: AUG'26 | H5: SEP'26 | I5: 2nd Qtr | J5: OCT'26 | K5: NOV'26 | L5: DEC'26 | M5: 3rd Qtr | N5: JAN'27 | O5: FEB'27 | P5: MAR'27 | Q5: 4th Qtr | R5: Total
A6: Turnover :
A7: Sales Domestic (incl GST) | B7: =B9+B8 -> 150.43 | C7: =C9+C8 -> 183.09 | D7: =D9+D8 -> 252.08 | E7: =SUM(B7:D7) -> 585.6 | F7: =F9+F8 -> 326.82 | G7: =G9+G8 -> 271.68 | H7: =H9+H8 -> 257.64 | I7: =SUM(F7:H7) -> 856.14 | J7: =J9+J8 -> 0 | K7: =K9+K8 -> 0 | L7: =L9+L8 -> 0 | M7: =SUM(J7:L7) -> 0 | N7: =N9+N8 -> 0 | O7: =O9+O8 -> 0 | P7: =P9+P8 -> 0 | Q7: =SUM(N7:P7) -> 0 | R7: =E7+I7+M7+Q7 -> 1441.74
A8: Less GST | B8: =ROUND(B9*IN_HO!C5,2) -> 22.95 | C8: =ROUND(C9*IN_HO!D5,2) -> 27.93 | D8: =ROUND(D9*IN_HO!E5,2) -> 38.45 | E8: =SUM(B8:D8) -> 89.33 | F8: =ROUND(F9*IN_HO!F5,2) -> 49.85 | G8: =ROUND(G9*IN_HO!G5,2) -> 41.44 | H8: =ROUND(H9*IN_HO!H5,2) -> 39.3 | I8: =SUM(F8:H8) -> 130.59 | J8: =ROUND(J9*IN_HO!I5,2) -> 0 | K8: =ROUND(K9*IN_HO!J5,2) -> 0 | L8: =ROUND(L9*IN_HO!K5,2) -> 0 | M8: =SUM(J8:L8) -> 0 | N8: =ROUND(N9*IN_HO!L5,2) -> 0 | O8: =ROUND(O9*IN_HO!M5,2) -> 0 | P8: =ROUND(P9*IN_HO!N5,2) -> 0 | Q8: =SUM(N8:P8) -> 0 | R8: =E8+I8+M8+Q8 -> 219.92
A9: Sales Domestic (ex GST) | B9: =IN_PLF!C38 -> 127.48 | C9: =IN_PLF!D38 -> 155.16 | D9: =IN_PLF!E38 -> 213.63 | E9: =SUM(B9:D9) -> 496.27 | F9: =IN_PLF!F38 -> 276.97 | G9: =IN_PLF!G38 -> 230.24 | H9: =IN_PLF!H38 -> 218.34 | I9: =SUM(F9:H9) -> 725.55 | J9: =IN_PLF!I38 -> 0 | K9: =IN_PLF!J38 -> 0 | L9: =IN_PLF!K38 -> 0 | M9: =SUM(J9:L9) -> 0 | N9: =IN_PLF!L38 -> 0 | O9: =IN_PLF!M38 -> 0 | P9: =IN_PLF!N38 -> 0 | Q9: =SUM(N9:P9) -> 0 | R9: =E9+I9+M9+Q9 -> 1221.82
A10: Less: Sales Return | B10: =IN_PLF!C49 -> 0 | C10: =IN_PLF!D49 -> 4.86 | D10: =IN_PLF!E49 -> 7.15 | E10: =SUM(B10:D10) -> 12.01 | F10: =IN_PLF!F49 -> 1.35 | G10: =IN_PLF!G49 -> 1 | H10: =IN_PLF!H49 -> 0.56 | I10: =SUM(F10:H10) -> 2.91 | J10: =IN_PLF!I49 -> 0 | K10: =IN_PLF!J49 -> 0 | L10: =IN_PLF!K49 -> 0 | M10: =SUM(J10:L10) -> 0 | N10: =IN_PLF!L49 -> 0 | O10: =IN_PLF!M49 -> 0 | P10: =IN_PLF!N49 -> 0 | Q10: =SUM(N10:P10) -> 0 | R10: =E10+I10+M10+Q10 -> 14.92
A11: Net Sales | B11: =B9-B10 -> 127.48 | C11: =C9-C10 -> 150.3 | D11: =D9-D10 -> 206.48 | E11: =SUM(B11:D11) -> 484.26 | F11: =F9-F10 -> 275.62 | G11: =G9-G10 -> 229.24 | H11: =H9-H10 -> 217.78 | I11: =SUM(F11:H11) -> 722.64 | J11: =J9-J10 -> 0 | K11: =K9-K10 -> 0 | L11: =L9-L10 -> 0 | M11: =SUM(J11:L11) -> 0 | N11: =N9-N10 -> 0 | O11: =O9-O10 -> 0 | P11: =P9-P10 -> 0 | Q11: =SUM(N11:P11) -> 0 | R11: =E11+I11+M11+Q11 -> 1206.9
A12: Other Business Income/Sales | B12: =IN_PLF!C43-IN_HO!C13 -> 0 | C12: =IN_PLF!D43-IN_HO!D13 -> 1.5 | D12: =IN_PLF!E43-IN_HO!E13 -> 0 | E12: =SUM(B12:D12) -> 1.5 | F12: =IN_PLF!F43-IN_HO!F13 -> 0 | G12: =IN_PLF!G43-IN_HO!G13 -> 2.5 | H12: =IN_PLF!H43-IN_HO!H13 -> 4.8 | I12: =SUM(F12:H12) -> 7.3 | J12: =IN_PLF!I43-IN_HO!I13 -> 0 | K12: =IN_PLF!J43-IN_HO!J13 -> 0 | L12: =IN_PLF!K43-IN_HO!K13 -> 0 | M12: =SUM(J12:L12) -> 0 | N12: =IN_PLF!L43-IN_HO!L13 -> 0 | O12: =IN_PLF!M43-IN_HO!M13 -> 0 | P12: =IN_PLF!N43-IN_HO!N13 -> 0 | Q12: =SUM(N12:P12) -> 0 | R12: =E12+I12+M12+Q12 -> 8.8
A13: Stock of Return Goods (Valued at Sales Price) | B13: =IN_PLF!C35 -> -15.08 | C13: =IN_PLF!D35 -> -3.56 | D13: =IN_PLF!E35 -> -4.02 | E13: =SUM(B13:D13) -> -22.66 | F13: =IN_PLF!F35 -> -3.79 | G13: =IN_PLF!G35 -> 1 | H13: =IN_PLF!H35 -> 0.56 | I13: =SUM(F13:H13) -> -2.23 | J13: =IN_PLF!I35 -> 0 | K13: =IN_PLF!J35 -> 0 | L13: =IN_PLF!K35 -> 0 | M13: =SUM(J13:L13) -> 0 | N13: =IN_PLF!L35 -> 0 | O13: =IN_PLF!M35 -> 0 | P13: =IN_PLF!N35 -> 0 | Q13: =SUM(N13:P13) -> 0 | R13: =E13+I13+M13+Q13 -> -24.89
A14: Net turnover for contribution | B14: =B11+B12+B13 -> 112.4 | C14: =C11+C12+C13 -> 148.24 | D14: =D11+D12+D13 -> 202.46 | E14: =SUM(B14:D14) -> 463.1 | F14: =F11+F12+F13 -> 271.83 | G14: =G11+G12+G13 -> 232.74 | H14: =H11+H12+H13 -> 223.14 | I14: =SUM(F14:H14) -> 727.71 | J14: =J11+J12+J13 -> 0 | K14: =K11+K12+K13 -> 0 | L14: =L11+L12+L13 -> 0 | M14: =SUM(J14:L14) -> 0 | N14: =N11+N12+N13 -> 0 | O14: =O11+O12+O13 -> 0 | P14: =P11+P12+P13 -> 0 | Q14: =SUM(N14:P14) -> 0 | R14: =E14+I14+M14+Q14 -> 1190.81
A15: Direct Expenditure (Variable Costs):
A16: Material Consumed-Direct & Indirect | B16: =IN_PLF!C5+IN_HO!C8 -> 47.91 | C16: =IN_PLF!D5+IN_HO!D8 -> 159.27 | D16: =IN_PLF!E5+IN_HO!E8 -> 153.67 | E16: =SUM(B16:D16) -> 360.85 | F16: =IN_PLF!F5+IN_HO!F8 -> 160.21 | G16: =IN_PLF!G5+IN_HO!G8 -> 109.64 | H16: =IN_PLF!H5+IN_HO!H8 -> 174.02 | I16: =SUM(F16:H16) -> 443.87 | J16: =IN_PLF!I5+IN_HO!I8 -> 0 | K16: =IN_PLF!J5+IN_HO!J8 -> 0 | L16: =IN_PLF!K5+IN_HO!K8 -> 0 | M16: =SUM(J16:L16) -> 0 | N16: =IN_PLF!L5+IN_HO!L8 -> 0 | O16: =IN_PLF!M5+IN_HO!M8 -> 0 | P16: =IN_PLF!N5+IN_HO!N8 -> 0 | Q16: =SUM(N16:P16) -> 0 | R16: =E16+I16+M16+Q16 -> 804.72
A17: (Increase)/Decrease in Stock | B17: =-IN_PLF!C32+IN_HO!C9 -> 31.72 | C17: =-IN_PLF!D32+IN_HO!D9 -> -71.63 | D17: =-IN_PLF!E32+IN_HO!E9 -> -32.47 | E17: =SUM(B17:D17) -> -72.38 | F17: =-IN_PLF!F32+IN_HO!F9 -> 22.62 | G17: =-IN_PLF!G32+IN_HO!G9 -> 43.89 | H17: =-IN_PLF!H32+IN_HO!H9 -> -48.76 | I17: =SUM(F17:H17) -> 17.75 | J17: =-IN_PLF!I32+IN_HO!I9 -> 0 | K17: =-IN_PLF!J32+IN_HO!J9 -> 0 | L17: =-IN_PLF!K32+IN_HO!K9 -> 0 | M17: =SUM(J17:L17) -> 0 | N17: =-IN_PLF!L32+IN_HO!L9 -> 0 | O17: =-IN_PLF!M32+IN_HO!M9 -> 0 | P17: =-IN_PLF!N32+IN_HO!N9 -> 0 | Q17: =SUM(N17:P17) -> 0 | R17: =E17+I17+M17+Q17 -> -54.63
A18: Manufacturing Overheads:
A19: - Power & Fuel (Variable part) | B19: =IN_PLF!C19+IN_PLF!C20+IN_HO!C10 -> 10.61 | C19: =IN_PLF!D19+IN_PLF!D20+IN_HO!D10 -> 15.14 | D19: =IN_PLF!E19+IN_PLF!E20+IN_HO!E10 -> 17.79 | E19: =SUM(B19:D19) -> 43.54 | F19: =IN_PLF!F19+IN_PLF!F20+IN_HO!F10 -> 18.01 | G19: =IN_PLF!G19+IN_PLF!G20+IN_HO!G10 -> 17.14 | H19: =IN_PLF!H19+IN_PLF!H20+IN_HO!H10 -> 18.37 | I19: =SUM(F19:H19) -> 53.52 | J19: =IN_PLF!I19+IN_PLF!I20+IN_HO!I10 -> 0 | K19: =IN_PLF!J19+IN_PLF!J20+IN_HO!J10 -> 0 | L19: =IN_PLF!K19+IN_PLF!K20+IN_HO!K10 -> 0 | M19: =SUM(J19:L19) -> 0 | N19: =IN_PLF!L19+IN_PLF!L20+IN_HO!L10 -> 0 | O19: =IN_PLF!M19+IN_PLF!M20+IN_HO!M10 -> 0 | P19: =IN_PLF!N19+IN_PLF!N20+IN_HO!N10 -> 0 | Q19: =SUM(N19:P19) -> 0 | R19: =E19+I19+M19+Q19 -> 97.06
A20: - Job-work Charges | B20: =IN_PLF!C9+IN_HO!C11 -> 9.1 | C20: =IN_PLF!D9+IN_HO!D11 -> 9.61 | D20: =IN_PLF!E9+IN_HO!E11 -> 12.19 | E20: =SUM(B20:D20) -> 30.9 | F20: =IN_PLF!F9+IN_HO!F11 -> 12.73 | G20: =IN_PLF!G9+IN_HO!G11 -> 11.56 | H20: =IN_PLF!H9+IN_HO!H11 -> 12.67 | I20: =SUM(F20:H20) -> 36.96 | J20: =IN_PLF!I9+IN_HO!I11 -> 0 | K20: =IN_PLF!J9+IN_HO!J11 -> 0 | L20: =IN_PLF!K9+IN_HO!K11 -> 0 | M20: =SUM(J20:L20) -> 0 | N20: =IN_PLF!L9+IN_HO!L11 -> 0 | O20: =IN_PLF!M9+IN_HO!M11 -> 0 | P20: =IN_PLF!N9+IN_HO!N11 -> 0 | Q20: =SUM(N20:P20) -> 0 | R20: =E20+I20+M20+Q20 -> 67.86
A21: Total Net Variable Costs | B21: =B16+B17+B19+B20 -> 99.34 | C21: =C16+C17+C19+C20 -> 112.39 | D21: =D16+D17+D19+D20 -> 151.18 | E21: =SUM(B21:D21) -> 362.91 | F21: =F16+F17+F19+F20 -> 213.57 | G21: =G16+G17+G19+G20 -> 182.23 | H21: =H16+H17+H19+H20 -> 156.3 | I21: =SUM(F21:H21) -> 552.1 | J21: =J16+J17+J19+J20 -> 0 | K21: =K16+K17+K19+K20 -> 0 | L21: =L16+L17+L19+L20 -> 0 | M21: =SUM(J21:L21) -> 0 | N21: =N16+N17+N19+N20 -> 0 | O21: =O16+O17+O19+O20 -> 0 | P21: =P16+P17+P19+P20 -> 0 | Q21: =SUM(N21:P21) -> 0 | R21: =E21+I21+M21+Q21 -> 915.01
A22: Contributions | B22: =B14-B21 -> 13.06 | C22: =C14-C21 -> 35.85 | D22: =D14-D21 -> 51.28 | E22: =SUM(B22:D22) -> 100.19 | F22: =F14-F21 -> 58.26 | G22: =G14-G21 -> 50.51 | H22: =H14-H21 -> 66.84 | I22: =SUM(F22:H22) -> 175.61 | J22: =J14-J21 -> 0 | K22: =K14-K21 -> 0 | L22: =L14-L21 -> 0 | M22: =SUM(J22:L22) -> 0 | N22: =N14-N21 -> 0 | O22: =O14-O21 -> 0 | P22: =P14-P21 -> 0 | Q22: =SUM(N22:P22) -> 0 | R22: =E22+I22+M22+Q22 -> 275.8
A24: Indirect Expenses (Fixed):
A25: Administrative Expenses | B25: =IN_HO!C16 -> 3.21 | C25: =IN_HO!D16 -> 4.13 | D25: =IN_HO!E16 -> 4.5 | E25: =SUM(B25:D25) -> 11.84 | F25: =IN_HO!F16 -> 7.52 | G25: =IN_HO!G16 -> 6.07 | H25: =IN_HO!H16 -> 7.13 | I25: =SUM(F25:H25) -> 20.72 | J25: =IN_HO!I16 -> 0 | K25: =IN_HO!J16 -> 0 | L25: =IN_HO!K16 -> 0 | M25: =SUM(J25:L25) -> 0 | N25: =IN_HO!L16 -> 0 | O25: =IN_HO!M16 -> 0 | P25: =IN_HO!N16 -> 0 | Q25: =SUM(N25:P25) -> 0 | R25: =E25+I25+M25+Q25 -> 32.56
A26: Material Consumed - Repair & maintt. | B26: =IN_PLF!C21 -> 1.38 | C26: =IN_PLF!D21 -> 2.28 | D26: =IN_PLF!E21 -> 2.31 | E26: =SUM(B26:D26) -> 5.97 | F26: =IN_PLF!F21 -> 3.41 | G26: =IN_PLF!G21 -> 2.28 | H26: =IN_PLF!H21 -> 1.97 | I26: =SUM(F26:H26) -> 7.66 | J26: =IN_PLF!I21 -> 0 | K26: =IN_PLF!J21 -> 0 | L26: =IN_PLF!K21 -> 0 | M26: =SUM(J26:L26) -> 0 | N26: =IN_PLF!L21 -> 0 | O26: =IN_PLF!M21 -> 0 | P26: =IN_PLF!N21 -> 0 | Q26: =SUM(N26:P26) -> 0 | R26: =E26+I26+M26+Q26 -> 13.63
A27: Other Manufacturing Overhead (Fixed) | B27: =IN_PLF!C22-IN_HO!C12 -> 4.62 | C27: =IN_PLF!D22-IN_HO!D12 -> 5.7 | D27: =IN_PLF!E22-IN_HO!E12 -> 5.93 | E27: =SUM(B27:D27) -> 16.25 | F27: =IN_PLF!F22-IN_HO!F12 -> 5.44 | G27: =IN_PLF!G22-IN_HO!G12 -> 4.71 | H27: =IN_PLF!H22-IN_HO!H12 -> 6.92 | I27: =SUM(F27:H27) -> 17.07 | J27: =IN_PLF!I22-IN_HO!I12 -> 0 | K27: =IN_PLF!J22-IN_HO!J12 -> 0 | L27: =IN_PLF!K22-IN_HO!K12 -> 0 | M27: =SUM(J27:L27) -> 0 | N27: =IN_PLF!L22-IN_HO!L12 -> 0 | O27: =IN_PLF!M22-IN_HO!M12 -> 0 | P27: =IN_PLF!N22-IN_HO!N12 -> 0 | Q27: =SUM(N27:P27) -> 0 | R27: =E27+I27+M27+Q27 -> 33.32
A28: Salary & Wages | B28: =IN_HO!C17 -> 15.91 | C28: =IN_HO!D17 -> 12.37 | D28: =IN_HO!E17 -> 14.85 | E28: =SUM(B28:D28) -> 43.13 | F28: =IN_HO!F17 -> 16.85 | G28: =IN_HO!G17 -> 15.87 | H28: =IN_HO!H17 -> 16.61 | I28: =SUM(F28:H28) -> 49.33 | J28: =IN_HO!I17 -> 0 | K28: =IN_HO!J17 -> 0 | L28: =IN_HO!K17 -> 0 | M28: =SUM(J28:L28) -> 0 | N28: =IN_HO!L17 -> 0 | O28: =IN_HO!M17 -> 0 | P28: =IN_HO!N17 -> 0 | Q28: =SUM(N28:P28) -> 0 | R28: =E28+I28+M28+Q28 -> 92.46
A29: - Power & Fuel (Fixed Part - Max Demand Charges) | B29: =IN_PLF!C18 -> 5.58 | C29: =IN_PLF!D18 -> 5.88 | D29: =IN_PLF!E18 -> 5.56 | E29: =SUM(B29:D29) -> 17.02 | F29: =IN_PLF!F18 -> 5.53 | G29: =IN_PLF!G18 -> 7.21 | H29: =IN_PLF!H18 -> 7.25 | I29: =SUM(F29:H29) -> 19.99 | J29: =IN_PLF!I18 -> 0 | K29: =IN_PLF!J18 -> 0 | L29: =IN_PLF!K18 -> 0 | M29: =SUM(J29:L29) -> 0 | N29: =IN_PLF!L18 -> 0 | O29: =IN_PLF!M18 -> 0 | P29: =IN_PLF!N18 -> 0 | Q29: =SUM(N29:P29) -> 0 | R29: =E29+I29+M29+Q29 -> 37.01
A30: Selling Expenses | B30: =IN_HO!C12 -> 0 | C30: =IN_HO!D12 -> 0 | D30: =IN_HO!E12 -> 0 | E30: =SUM(B30:D30) -> 0 | F30: =IN_HO!F12 -> 0 | G30: =IN_HO!G12 -> 0 | H30: =IN_HO!H12 -> 3.22 | I30: =SUM(F30:H30) -> 3.22 | J30: =IN_HO!I12 -> 0 | K30: =IN_HO!J12 -> 0 | L30: =IN_HO!K12 -> 0 | M30: =SUM(J30:L30) -> 0 | N30: =IN_HO!L12 -> 0 | O30: =IN_HO!M12 -> 0 | P30: =IN_HO!N12 -> 0 | Q30: =SUM(N30:P30) -> 0 | R30: =E30+I30+M30+Q30 -> 3.22
A31: Total Fixed Costs | B31: =SUM(B25:B30) -> 30.7 | C31: =SUM(C25:C30) -> 30.36 | D31: =SUM(D25:D30) -> 33.15 | E31: =SUM(B31:D31) -> 94.21 | F31: =SUM(F25:F30) -> 38.75 | G31: =SUM(G25:G30) -> 36.14 | H31: =SUM(H25:H30) -> 43.1 | I31: =SUM(F31:H31) -> 117.99 | J31: =SUM(J25:J30) -> 0 | K31: =SUM(K25:K30) -> 0 | L31: =SUM(L25:L30) -> 0 | M31: =SUM(J31:L31) -> 0 | N31: =SUM(N25:N30) -> 0 | O31: =SUM(O25:O30) -> 0 | P31: =SUM(P25:P30) -> 0 | Q31: =SUM(N31:P31) -> 0 | R31: =E31+I31+M31+Q31 -> 212.2
A32: NET PROFIT FROM OPERATIONS | B32: =B22-B31 -> -17.64 | C32: =C22-C31 -> 5.49 | D32: =D22-D31 -> 18.13 | E32: =SUM(B32:D32) -> 5.98 | F32: =F22-F31 -> 19.51 | G32: =G22-G31 -> 14.37 | H32: =H22-H31 -> 23.74 | I32: =SUM(F32:H32) -> 57.62 | J32: =J22-J31 -> 0 | K32: =K22-K31 -> 0 | L32: =L22-L31 -> 0 | M32: =SUM(J32:L32) -> 0 | N32: =N22-N31 -> 0 | O32: =O22-O31 -> 0 | P32: =P22-P31 -> 0 | Q32: =SUM(N32:P32) -> 0 | R32: =E32+I32+M32+Q32 -> 63.6
A33: Less: Deferred Revenue Expenses | B33: =IN_HO!C18 -> 0 | C33: =IN_HO!D18 -> 0 | D33: =IN_HO!E18 -> 0 | E33: =SUM(B33:D33) -> 0 | F33: =IN_HO!F18 -> 0 | G33: =IN_HO!G18 -> 0 | H33: =IN_HO!H18 -> 0 | I33: =SUM(F33:H33) -> 0 | J33: =IN_HO!I18 -> 0 | K33: =IN_HO!J18 -> 0 | L33: =IN_HO!K18 -> 0 | M33: =SUM(J33:L33) -> 0 | N33: =IN_HO!L18 -> 0 | O33: =IN_HO!M18 -> 0 | P33: =IN_HO!N18 -> 0 | Q33: =SUM(N33:P33) -> 0 | R33: =E33+I33+M33+Q33 -> 0
A34: Less: Other Non-Operating Expenses | B34: =IN_HO!C19 -> 0 | C34: =IN_HO!D19 -> 0 | D34: =IN_HO!E19 -> 0 | E34: =SUM(B34:D34) -> 0 | F34: =IN_HO!F19 -> 0 | G34: =IN_HO!G19 -> 0 | H34: =IN_HO!H19 -> 0 | I34: =SUM(F34:H34) -> 0 | J34: =IN_HO!I19 -> 0 | K34: =IN_HO!J19 -> 0 | L34: =IN_HO!K19 -> 0 | M34: =SUM(J34:L34) -> 0 | N34: =IN_HO!L19 -> 0 | O34: =IN_HO!M19 -> 0 | P34: =IN_HO!N19 -> 0 | Q34: =SUM(N34:P34) -> 0 | R34: =E34+I34+M34+Q34 -> 0
A35: Profit after Deferred Revenue Expenditure | B35: =B32-B33-B34 -> -17.64 | C35: =C32-C33-C34 -> 5.49 | D35: =D32-D33-D34 -> 18.13 | E35: =SUM(B35:D35) -> 5.98 | F35: =F32-F33-F34 -> 19.51 | G35: =G32-G33-G34 -> 14.37 | H35: =H32-H33-H34 -> 23.74 | I35: =SUM(F35:H35) -> 57.62 | J35: =J32-J33-J34 -> 0 | K35: =K32-K33-K34 -> 0 | L35: =L32-L33-L34 -> 0 | M35: =SUM(J35:L35) -> 0 | N35: =N32-N33-N34 -> 0 | O35: =O32-O33-O34 -> 0 | P35: =P32-P33-P34 -> 0 | Q35: =SUM(N35:P35) -> 0 | R35: =E35+I35+M35+Q35 -> 63.6
A36: Net Income from Storage Facility Service Charges | B36: =IN_PLF!C45+IN_HO!C13 -> 6.89 | C36: =IN_PLF!D45+IN_HO!D13 -> 6.89 | D36: =IN_PLF!E45+IN_HO!E13 -> 6.89 | E36: =SUM(B36:D36) -> 20.67 | F36: =IN_PLF!F45+IN_HO!F13 -> 6.95 | G36: =IN_PLF!G45+IN_HO!G13 -> 7.91 | H36: =IN_PLF!H45+IN_HO!H13 -> 7.39 | I36: =SUM(F36:H36) -> 22.25 | J36: =IN_PLF!I45+IN_HO!I13 -> 0 | K36: =IN_PLF!J45+IN_HO!J13 -> 0 | L36: =IN_PLF!K45+IN_HO!K13 -> 0 | M36: =SUM(J36:L36) -> 0 | N36: =IN_PLF!L45+IN_HO!L13 -> 0 | O36: =IN_PLF!M45+IN_HO!M13 -> 0 | P36: =IN_PLF!N45+IN_HO!N13 -> 0 | Q36: =SUM(N36:P36) -> 0 | R36: =E36+I36+M36+Q36 -> 42.92
A37: EBITDA | B37: =B35+B36 -> -10.75 | C37: =C35+C36 -> 12.38 | D37: =D35+D36 -> 25.02 | E37: =SUM(B37:D37) -> 26.65 | F37: =F35+F36 -> 26.46 | G37: =G35+G36 -> 22.28 | H37: =H35+H36 -> 31.13 | I37: =SUM(F37:H37) -> 79.87 | J37: =J35+J36 -> 0 | K37: =K35+K36 -> 0 | L37: =L35+L36 -> 0 | M37: =SUM(J37:L37) -> 0 | N37: =N35+N36 -> 0 | O37: =O35+O36 -> 0 | P37: =P35+P36 -> 0 | Q37: =SUM(N37:P37) -> 0 | R37: =E37+I37+M37+Q37 -> 106.52
A38: Depreciation | B38: =IN_HO!C20 -> 0 | C38: =IN_HO!D20 -> 0 | D38: =IN_HO!E20 -> 0 | E38: =SUM(B38:D38) -> 0 | F38: =IN_HO!F20 -> 0 | G38: =IN_HO!G20 -> 0 | H38: =IN_HO!H20 -> 0 | I38: =SUM(F38:H38) -> 0 | J38: =IN_HO!I20 -> 0 | K38: =IN_HO!J20 -> 0 | L38: =IN_HO!K20 -> 0 | M38: =SUM(J38:L38) -> 0 | N38: =IN_HO!L20 -> 0 | O38: =IN_HO!M20 -> 0 | P38: =IN_HO!N20 -> 0 | Q38: =SUM(N38:P38) -> 0 | R38: =E38+I38+M38+Q38 -> 0
A39: Interest | B39: =IN_HO!C21 -> 0 | C39: =IN_HO!D21 -> 0 | D39: =IN_HO!E21 -> 0 | E39: =SUM(B39:D39) -> 0 | F39: =IN_HO!F21 -> 0 | G39: =IN_HO!G21 -> 0 | H39: =IN_HO!H21 -> 0 | I39: =SUM(F39:H39) -> 0 | J39: =IN_HO!I21 -> 0 | K39: =IN_HO!J21 -> 0 | L39: =IN_HO!K21 -> 0 | M39: =SUM(J39:L39) -> 0 | N39: =IN_HO!L21 -> 0 | O39: =IN_HO!M21 -> 0 | P39: =IN_HO!N21 -> 0 | Q39: =SUM(N39:P39) -> 0 | R39: =E39+I39+M39+Q39 -> 0
A40: PBT 2026-27 | B40: =B37-B38-B39 -> -10.75 | C40: =C37-C38-C39 -> 12.38 | D40: =D37-D38-D39 -> 25.02 | E40: =SUM(B40:D40) -> 26.65 | F40: =F37-F38-F39 -> 26.46 | G40: =G37-G38-G39 -> 22.28 | H40: =H37-H38-H39 -> 31.13 | I40: =SUM(F40:H40) -> 79.87 | J40: =J37-J38-J39 -> 0 | K40: =K37-K38-K39 -> 0 | L40: =L37-L38-L39 -> 0 | M40: =SUM(J40:L40) -> 0 | N40: =N37-N38-N39 -> 0 | O40: =O37-O38-O39 -> 0 | P40: =P37-P38-P39 -> 0 | Q40: =SUM(N40:P40) -> 0 | R40: =E40+I40+M40+Q40 -> 106.52
A43: STATISTICS - 2026-27
A44: PARTICULARS | B44: APR'26 | C44: MAY'26 | D44: JUN'26 | E44: 1st Qtr | F44: JUL'26 | G44: AUG'26 | H44: SEP'26 | I44: 2nd Qtr | J44: OCT'26 | K44: NOV'26 | L44: DEC'26 | M44: 3rd Qtr | N44: JAN'27 | O44: FEB'27 | P44: MAR'27 | Q44: 4th Qtr | R44: Total | S44: Average/Month
A45: Production (MT) | B45: =IN_HO!C24 -> 33.56 | C45: =IN_HO!D24 -> 84.62 | D45: =IN_HO!E24 -> 83 | E45: =SUM(B45:D45) -> 201.18 | F45: =IN_HO!F24 -> 84.62 | G45: =IN_HO!G24 -> 77.44 | H45: =IN_HO!H24 -> 105.48 | I45: =SUM(F45:H45) -> 267.54 | J45: =IN_HO!I24 -> 0 | K45: =IN_HO!J24 -> 0 | L45: =IN_HO!K24 -> 0 | M45: =SUM(J45:L45) -> 0 | N45: =IN_HO!L24 -> 0 | O45: =IN_HO!M24 -> 0 | P45: =IN_HO!N24 -> 0 | Q45: =SUM(N45:P45) -> 0 | R45: =E45+I45+M45+Q45 -> 468.72 | S45: =R45/12 -> 39.06
A46: Despatch (MT) | B46: =IN_HO!C25 -> 50.44 | C46: =IN_HO!D25 -> 36.67 | D46: =IN_HO!E25 -> 106.07 | E46: =SUM(B46:D46) -> 193.18 | F46: =IN_HO!F25 -> 36.67 | G46: =IN_HO!G25 -> 94.58 | H46: =IN_HO!H25 -> 89.34 | I46: =SUM(F46:H46) -> 220.59 | J46: =IN_HO!I25 -> 0 | K46: =IN_HO!J25 -> 0 | L46: =IN_HO!K25 -> 0 | M46: =SUM(J46:L46) -> 0 | N46: =IN_HO!L25 -> 0 | O46: =IN_HO!M25 -> 0 | P46: =IN_HO!N25 -> 0 | Q46: =SUM(N46:P46) -> 0 | R46: =E46+I46+M46+Q46 -> 413.77 | S46: =R46/12 -> 34.480833
A47: In-house Rejections (MT) | B47: =IN_HO!C26 -> 5.73 | C47: =IN_HO!D26 -> 6.9 | D47: =IN_HO!E26 -> 9.39 | E47: =SUM(B47:D47) -> 22.02 | F47: =IN_HO!F26 -> 6.9 | G47: =IN_HO!G26 -> 9.16 | H47: =IN_HO!H26 -> 9.04 | I47: =SUM(F47:H47) -> 25.1 | J47: =IN_HO!I26 -> 0 | K47: =IN_HO!J26 -> 0 | L47: =IN_HO!K26 -> 0 | M47: =SUM(J47:L47) -> 0 | N47: =IN_HO!L26 -> 0 | O47: =IN_HO!M26 -> 0 | P47: =IN_HO!N26 -> 0 | Q47: =SUM(N47:P47) -> 0 | R47: =E47+I47+M47+Q47 -> 47.12 | S47: =R47/12 -> 3.9266667
A48: Realisation/MT (Rs. in lac) = actual despatch value / despatch MT | B48: =IF(B46=0,0,IN_PLF!C39/B46) -> 2.5273592 | C48: =IF(C46=0,0,IN_PLF!D39/C46) -> 2.4548677 | D48: =IF(D46=0,0,IN_PLF!E39/D46) -> 2.6281701 | F48: =IF(F46=0,0,IN_PLF!F39/F46) -> 7.5530406 | G48: =IF(G46=0,0,IN_PLF!G39/G46) -> 2.4343413 | H48: =IF(H46=0,0,IN_PLF!H39/H46) -> 2.4439221 | J48: =IF(J46=0,0,IN_PLF!I39/J46) -> 0 | K48: =IF(K46=0,0,IN_PLF!J39/K46) -> 0 | L48: =IF(L46=0,0,IN_PLF!K39/L46) -> 0 | N48: =IF(N46=0,0,IN_PLF!L39/N46) -> 0 | O48: =IF(O46=0,0,IN_PLF!M39/O46) -> 0 | P48: =IF(P46=0,0,IN_PLF!N39/P46) -> 0
A49: Sales net of Return (without GST, O/Income) | B49: =B11 -> 127.48 | C49: =C11 -> 150.3 | D49: =D11 -> 206.48 | E49: =SUM(B49:D49) -> 484.26 | F49: =F11 -> 275.62 | G49: =G11 -> 229.24 | H49: =H11 -> 217.78 | I49: =SUM(F49:H49) -> 722.64 | J49: =J11 -> 0 | K49: =K11 -> 0 | L49: =L11 -> 0 | M49: =SUM(J49:L49) -> 0 | N49: =N11 -> 0 | O49: =O11 -> 0 | P49: =P11 -> 0 | Q49: =SUM(N49:P49) -> 0 | R49: =E49+I49+M49+Q49 -> 1206.9 | S49: =R49/12 -> 100.575
A50: Collections (including GST) | B50: =IN_HO!C27 -> 149.75 | C50: =IN_HO!D27 -> 126.8 | D50: =IN_HO!E27 -> 238.95 | E50: =SUM(B50:D50) -> 515.5 | F50: =IN_HO!F27 -> 269.64 | G50: =IN_HO!G27 -> 302.91 | H50: =IN_HO!H27 -> 284.24 | I50: =SUM(F50:H50) -> 856.79 | J50: =IN_HO!I27 -> 0 | K50: =IN_HO!J27 -> 0 | L50: =IN_HO!K27 -> 0 | M50: =SUM(J50:L50) -> 0 | N50: =IN_HO!L27 -> 0 | O50: =IN_HO!M27 -> 0 | P50: =IN_HO!N27 -> 0 | Q50: =SUM(N50:P50) -> 0 | R50: =E50+I50+M50+Q50 -> 1372.29 | S50: =R50/12 -> 114.3575
A51: PBT | B51: =B40 -> -10.75 | C51: =C40 -> 12.38 | D51: =D40 -> 25.02 | E51: =SUM(B51:D51) -> 26.65 | F51: =F40 -> 26.46 | G51: =G40 -> 22.28 | H51: =H40 -> 31.13 | I51: =SUM(F51:H51) -> 79.87 | J51: =J40 -> 0 | K51: =K40 -> 0 | L51: =L40 -> 0 | M51: =SUM(J51:L51) -> 0 | N51: =N40 -> 0 | O51: =O40 -> 0 | P51: =P40 -> 0 | Q51: =SUM(N51:P51) -> 0 | R51: =E51+I51+M51+Q51 -> 106.52 | S51: =R51/12 -> 8.8766667
A52: - NET PROFIT FROM OPERATIONS | B52: =B32 -> -17.64 | C52: =C32 -> 5.49 | D52: =D32 -> 18.13 | E52: =SUM(B52:D52) -> 5.98 | F52: =F32 -> 19.51 | G52: =G32 -> 14.37 | H52: =H32 -> 23.74 | I52: =SUM(F52:H52) -> 57.62 | J52: =J32 -> 0 | K52: =K32 -> 0 | L52: =L32 -> 0 | M52: =SUM(J52:L52) -> 0 | N52: =N32 -> 0 | O52: =O32 -> 0 | P52: =P32 -> 0 | Q52: =SUM(N52:P52) -> 0 | R52: =E52+I52+M52+Q52 -> 63.6 | S52: =R52/12 -> 5.3
A53: - Income from Storage Facility Service Ch | B53: =B36 -> 6.89 | C53: =C36 -> 6.89 | D53: =D36 -> 6.89 | E53: =SUM(B53:D53) -> 20.67 | F53: =F36 -> 6.95 | G53: =G36 -> 7.91 | H53: =H36 -> 7.39 | I53: =SUM(F53:H53) -> 22.25 | J53: =J36 -> 0 | K53: =K36 -> 0 | L53: =L36 -> 0 | M53: =SUM(J53:L53) -> 0 | N53: =N36 -> 0 | O53: =O36 -> 0 | P53: =P36 -> 0 | Q53: =SUM(N53:P53) -> 0 | R53: =E53+I53+M53+Q53 -> 42.92 | S53: =R53/12 -> 3.5766667
A56: CROSS-CHECK FROM CONTRIBUTION DATA (IN_Contrib) - not part of published MIS
A57: PARTICULARS | B57: APR'26 | C57: MAY'26 | D57: JUN'26 | E57: 1st Qtr | F57: JUL'26 | G57: AUG'26 | H57: SEP'26 | I57: 2nd Qtr | J57: OCT'26 | K57: NOV'26 | L57: DEC'26 | M57: 3rd Qtr | N57: JAN'27 | O57: FEB'27 | P57: MAR'27 | Q57: 4th Qtr | R57: Total
A58: Pouring MT per Contribution sheet | B58: =SUMIFS(IN_Contrib!$G$4:$G$2000,IN_Contrib!$B$4:$B$2000,IN_HO!$C$2,IN_Contrib!$C$4:$C$2000,"April") -> 39.086 | C58: =SUMIFS(IN_Contrib!$G$4:$G$2000,IN_Contrib!$B$4:$B$2000,IN_HO!$C$2,IN_Contrib!$C$4:$C$2000,"May") -> 91.311 | D58: =SUMIFS(IN_Contrib!$G$4:$G$2000,IN_Contrib!$B$4:$B$2000,IN_HO!$C$2,IN_Contrib!$C$4:$C$2000,"June") -> 92.135 | E58: =SUM(B58:D58) -> 222.532 | F58: =SUMIFS(IN_Contrib!$G$4:$G$2000,IN_Contrib!$B$4:$B$2000,IN_HO!$C$2,IN_Contrib!$C$4:$C$2000,"July") -> 106.77 | G58: =SUMIFS(IN_Contrib!$G$4:$G$2000,IN_Contrib!$B$4:$B$2000,IN_HO!$C$2,IN_Contrib!$C$4:$C$2000,"August") -> 85.14 | H58: =SUMIFS(IN_Contrib!$G$4:$G$2000,IN_Contrib!$B$4:$B$2000,IN_HO!$C$2,IN_Contrib!$C$4:$C$2000,"September") -> 113.84 | I58: =SUM(F58:H58) -> 305.75 | J58: =SUMIFS(IN_Contrib!$G$4:$G$2000,IN_Contrib!$B$4:$B$2000,IN_HO!$C$2,IN_Contrib!$C$4:$C$2000,"October") -> 0 | K58: =SUMIFS(IN_Contrib!$G$4:$G$2000,IN_Contrib!$B$4:$B$2000,IN_HO!$C$2,IN_Contrib!$C$4:$C$2000,"November") -> 0 | L58: =SUMIFS(IN_Contrib!$G$4:$G$2000,IN_Contrib!$B$4:$B$2000,IN_HO!$C$2,IN_Contrib!$C$4:$C$2000,"December") -> 0 | M58: =SUM(J58:L58) -> 0 | N58: =SUMIFS(IN_Contrib!$G$4:$G$2000,IN_Contrib!$B$4:$B$2000,IN_HO!$C$2,IN_Contrib!$C$4:$C$2000,"January") -> 0 | O58: =SUMIFS(IN_Contrib!$G$4:$G$2000,IN_Contrib!$B$4:$B$2000,IN_HO!$C$2,IN_Contrib!$C$4:$C$2000,"February") -> 0 | P58: =SUMIFS(IN_Contrib!$G$4:$G$2000,IN_Contrib!$B$4:$B$2000,IN_HO!$C$2,IN_Contrib!$C$4:$C$2000,"March") -> 0 | Q58: =SUM(N58:P58) -> 0 | R58: =E58+I58+M58+Q58 -> 528.282
A59: Rejection MT per Contribution sheet (Nos x wt) | B59: =SUMIFS(IN_Contrib!$AD$4:$AD$2000,IN_Contrib!$B$4:$B$2000,IN_HO!$C$2,IN_Contrib!$C$4:$C$2000,"April") -> 5.478 | C59: =SUMIFS(IN_Contrib!$AD$4:$AD$2000,IN_Contrib!$B$4:$B$2000,IN_HO!$C$2,IN_Contrib!$C$4:$C$2000,"May") -> 4.942 | D59: =SUMIFS(IN_Contrib!$AD$4:$AD$2000,IN_Contrib!$B$4:$B$2000,IN_HO!$C$2,IN_Contrib!$C$4:$C$2000,"June") -> 1.0485 | E59: =SUM(B59:D59) -> 11.4685 | F59: =SUMIFS(IN_Contrib!$AD$4:$AD$2000,IN_Contrib!$B$4:$B$2000,IN_HO!$C$2,IN_Contrib!$C$4:$C$2000,"July") -> 6.4248 | G59: =SUMIFS(IN_Contrib!$AD$4:$AD$2000,IN_Contrib!$B$4:$B$2000,IN_HO!$C$2,IN_Contrib!$C$4:$C$2000,"August") -> 7.782 | H59: =SUMIFS(IN_Contrib!$AD$4:$AD$2000,IN_Contrib!$B$4:$B$2000,IN_HO!$C$2,IN_Contrib!$C$4:$C$2000,"September") -> 8.51899 | I59: =SUM(F59:H59) -> 22.72579 | J59: =SUMIFS(IN_Contrib!$AD$4:$AD$2000,IN_Contrib!$B$4:$B$2000,IN_HO!$C$2,IN_Contrib!$C$4:$C$2000,"October") -> 0 | K59: =SUMIFS(IN_Contrib!$AD$4:$AD$2000,IN_Contrib!$B$4:$B$2000,IN_HO!$C$2,IN_Contrib!$C$4:$C$2000,"November") -> 0 | L59: =SUMIFS(IN_Contrib!$AD$4:$AD$2000,IN_Contrib!$B$4:$B$2000,IN_HO!$C$2,IN_Contrib!$C$4:$C$2000,"December") -> 0 | M59: =SUM(J59:L59) -> 0 | N59: =SUMIFS(IN_Contrib!$AD$4:$AD$2000,IN_Contrib!$B$4:$B$2000,IN_HO!$C$2,IN_Contrib!$C$4:$C$2000,"January") -> 0 | O59: =SUMIFS(IN_Contrib!$AD$4:$AD$2000,IN_Contrib!$B$4:$B$2000,IN_HO!$C$2,IN_Contrib!$C$4:$C$2000,"February") -> 0 | P59: =SUMIFS(IN_Contrib!$AD$4:$AD$2000,IN_Contrib!$B$4:$B$2000,IN_HO!$C$2,IN_Contrib!$C$4:$C$2000,"March") -> 0 | Q59: =SUM(N59:P59) -> 0 | R59: =E59+I59+M59+Q59 -> 34.19429
A60: Customer-wise contribution (Pouring & rejn.) Rs L | B60: =SUMIFS(IN_Contrib!$Z$4:$Z$2000,IN_Contrib!$B$4:$B$2000,IN_HO!$C$2,IN_Contrib!$C$4:$C$2000,"April") -> 20.96 | C60: =SUMIFS(IN_Contrib!$Z$4:$Z$2000,IN_Contrib!$B$4:$B$2000,IN_HO!$C$2,IN_Contrib!$C$4:$C$2000,"May") -> 47.26 | D60: =SUMIFS(IN_Contrib!$Z$4:$Z$2000,IN_Contrib!$B$4:$B$2000,IN_HO!$C$2,IN_Contrib!$C$4:$C$2000,"June") -> 55.89 | E60: =SUM(B60:D60) -> 124.11 | F60: =SUMIFS(IN_Contrib!$Z$4:$Z$2000,IN_Contrib!$B$4:$B$2000,IN_HO!$C$2,IN_Contrib!$C$4:$C$2000,"July") -> 57.05 | G60: =SUMIFS(IN_Contrib!$Z$4:$Z$2000,IN_Contrib!$B$4:$B$2000,IN_HO!$C$2,IN_Contrib!$C$4:$C$2000,"August") -> 47.98 | H60: =SUMIFS(IN_Contrib!$Z$4:$Z$2000,IN_Contrib!$B$4:$B$2000,IN_HO!$C$2,IN_Contrib!$C$4:$C$2000,"September") -> 72.02 | I60: =SUM(F60:H60) -> 177.05 | J60: =SUMIFS(IN_Contrib!$Z$4:$Z$2000,IN_Contrib!$B$4:$B$2000,IN_HO!$C$2,IN_Contrib!$C$4:$C$2000,"October") -> 0 | K60: =SUMIFS(IN_Contrib!$Z$4:$Z$2000,IN_Contrib!$B$4:$B$2000,IN_HO!$C$2,IN_Contrib!$C$4:$C$2000,"November") -> 0 | L60: =SUMIFS(IN_Contrib!$Z$4:$Z$2000,IN_Contrib!$B$4:$B$2000,IN_HO!$C$2,IN_Contrib!$C$4:$C$2000,"December") -> 0 | M60: =SUM(J60:L60) -> 0 | N60: =SUMIFS(IN_Contrib!$Z$4:$Z$2000,IN_Contrib!$B$4:$B$2000,IN_HO!$C$2,IN_Contrib!$C$4:$C$2000,"January") -> 0 | O60: =SUMIFS(IN_Contrib!$Z$4:$Z$2000,IN_Contrib!$B$4:$B$2000,IN_HO!$C$2,IN_Contrib!$C$4:$C$2000,"February") -> 0 | P60: =SUMIFS(IN_Contrib!$Z$4:$Z$2000,IN_Contrib!$B$4:$B$2000,IN_HO!$C$2,IN_Contrib!$C$4:$C$2000,"March") -> 0 | Q60: =SUM(N60:P60) -> 0 | R60: =E60+I60+M60+Q60 -> 301.16
A61: Loss of contribution - rejn & destruct test Rs L | B61: =SUMIFS(IN_Contrib!$AC$4:$AC$2000,IN_Contrib!$B$4:$B$2000,IN_HO!$C$2,IN_Contrib!$C$4:$C$2000,"April") -> 3.57 | C61: =SUMIFS(IN_Contrib!$AC$4:$AC$2000,IN_Contrib!$B$4:$B$2000,IN_HO!$C$2,IN_Contrib!$C$4:$C$2000,"May") -> 3.89 | D61: =SUMIFS(IN_Contrib!$AC$4:$AC$2000,IN_Contrib!$B$4:$B$2000,IN_HO!$C$2,IN_Contrib!$C$4:$C$2000,"June") -> 5.1 | E61: =SUM(B61:D61) -> 12.56 | F61: =SUMIFS(IN_Contrib!$AC$4:$AC$2000,IN_Contrib!$B$4:$B$2000,IN_HO!$C$2,IN_Contrib!$C$4:$C$2000,"July") -> 6.16 | G61: =SUMIFS(IN_Contrib!$AC$4:$AC$2000,IN_Contrib!$B$4:$B$2000,IN_HO!$C$2,IN_Contrib!$C$4:$C$2000,"August") -> 6.32 | H61: =SUMIFS(IN_Contrib!$AC$4:$AC$2000,IN_Contrib!$B$4:$B$2000,IN_HO!$C$2,IN_Contrib!$C$4:$C$2000,"September") -> 6.14 | I61: =SUM(F61:H61) -> 18.62 | J61: =SUMIFS(IN_Contrib!$AC$4:$AC$2000,IN_Contrib!$B$4:$B$2000,IN_HO!$C$2,IN_Contrib!$C$4:$C$2000,"October") -> 0 | K61: =SUMIFS(IN_Contrib!$AC$4:$AC$2000,IN_Contrib!$B$4:$B$2000,IN_HO!$C$2,IN_Contrib!$C$4:$C$2000,"November") -> 0 | L61: =SUMIFS(IN_Contrib!$AC$4:$AC$2000,IN_Contrib!$B$4:$B$2000,IN_HO!$C$2,IN_Contrib!$C$4:$C$2000,"December") -> 0 | M61: =SUM(J61:L61) -> 0 | N61: =SUMIFS(IN_Contrib!$AC$4:$AC$2000,IN_Contrib!$B$4:$B$2000,IN_HO!$C$2,IN_Contrib!$C$4:$C$2000,"January") -> 0 | O61: =SUMIFS(IN_Contrib!$AC$4:$AC$2000,IN_Contrib!$B$4:$B$2000,IN_HO!$C$2,IN_Contrib!$C$4:$C$2000,"February") -> 0 | P61: =SUMIFS(IN_Contrib!$AC$4:$AC$2000,IN_Contrib!$B$4:$B$2000,IN_HO!$C$2,IN_Contrib!$C$4:$C$2000,"March") -> 0 | Q61: =SUM(N61:P61) -> 0 | R61: =E61+I61+M61+Q61 -> 31.18
A62: Variance: MIS Production MT - Pouring MT | B62: =B45-B58 -> -5.526 | C62: =C45-C58 -> -6.691 | D62: =D45-D58 -> -9.135 | E62: =E45-E58 -> -21.352 | F62: =F45-F58 -> -22.15 | G62: =G45-G58 -> -7.7 | H62: =H45-H58 -> -8.36 | I62: =I45-I58 -> -38.21 | ... R62: =R45-R58 -> -59.562
A63: Variance: MIS Rejection MT - Contribution-sheet Rejection MT | B63: =B47-B59 -> 0.252 | C63: =C47-C59 -> 1.958 | D63: =D47-D59 -> 8.3415 | E63: =E47-E59 -> 10.5515 | F63: =F47-F59 -> 0.4752 | G63: =G47-G59 -> 1.378 | H63: =H47-H59 -> 0.52101 | I63: =I47-I59 -> 2.37421 | ... R63: =R47-R59 -> 12.92571
A64: Ledger Contribution (MIS) - Customer-wise contribution (Contribution sheet) | B64: =B22-B60 -> -7.9 | C64: =C22-C60 -> -11.41 | D64: =D22-D60 -> -4.61 | E64: =E22-E60 -> -23.92 | F64: =F22-F60 -> 1.21 | G64: =G22-G60 -> 2.53 | H64: =H22-H60 -> -5.18 | I64: =I22-I60 -> -1.44 | ... R64: =R22-R60 -> -25.36

Sheet IN_PLF
A1: PL FACTORY DATA - monthly feed from factory (Rs. Lacs)
A3: Sl | B3: Particulars | C3: Apr'26 | D3: May'26 | E3: Jun'26 | F3: Jul'26 | G3: Aug'26 | H3: Sep'26 | I3: Oct'26 | J3: Nov'26 | K3: Dec'26 | L3: Jan'27 | M3: Feb'27 | N3: Mar'27
A5: 1 | B5: Material Consumption: | C5: =SUM(C6:C8) -> 49.71 | D5: =SUM(D6:D8) -> 159.27 | E5: =SUM(E6:E8) -> 151.43 | F5: =SUM(F6:F8) -> 157.21 | G5: =SUM(G6:G8) -> 107.64 | H5: =SUM(H6:H8) -> 171.02 | I5: =SUM(I6:I8) -> 0 | J5: =SUM(J6:J8) -> 0 | ... N5: =SUM(N6:N8) -> 0
B6: Basic RM | C6: 37.43 | D6: 144.29 | E6: 135.24 | F6: 134.88 | G6: 84.93 | H6: 148.59
B7: Consumables | C7: 11.75 | D7: 14.9 | E7: 15.86 | F7: 21.66 | G7: 22.1 | H7: 21.92
B8: Addln. Exp on Purchase | C8: 0.53 | D8: 0.08 | E8: 0.33 | F8: 0.67 | G8: 0.61 | H8: 0.51
A9: 2 | B9: Contractual Prodn Expenses (Job): | C9: =SUM(C10:C16) -> 9.1 | D9: =SUM(D10:D16) -> 9.48 | E9: =SUM(E10:E16) -> 10.12 | F9: =SUM(F10:F16) -> 10.73 | G9: =SUM(G10:G16) -> 9.55 | H9: =SUM(H10:H16) -> 10.67 | I9: =SUM(I10:I16) -> 0 | J9: =SUM(J10:J16) -> 0 | ... N9: =SUM(N10:N16) -> 0
B10: Krishna Enterprise - MLT MLD Etc | C10: 3.76 | D10: 3.95 | E10: 3.87 | F10: 4.5 | G10: 3.54 | H10: 4.43
B11: Rahaman Enterprise QC | C11: 0 | D11: 0 | E11: 0 | F11: 0 | G11: 0 | H11: 0
B12: Krishna Enterprise / Rahaman - FLT | C12: 3.99 | D12: 3.97 | E12: 4.18 | F12: 4.35 | G12: 4.37 | H12: 4.7
B13: Sree Engineering | C13: 0.55 | D13: 0.76 | E13: 0.7 | F13: 0.9 | G13: 0.89 | H13: 0.79
B14: Tapas Samanta & Outside-Inside Machining | C14: 0 | D14: 0 | E14: 0 | F14: 0 | G14: 0 | H14: 0
B15: Outside H/T | C15: 0 | D15: 0 | E15: 0.22 | F15: 0 | G15: 0 | H15: 0
B16: Radiography Charges | C16: 0.8 | D16: 0.8 | E16: 1.15 | F16: 0.98 | G16: 0.75 | H16: 0.75
A17: 3 | B17: Power | C17: =SUM(C18:C20) -> 16.05 | D17: =SUM(D18:D20) -> 21.02 | E17: =SUM(E18:E20) -> 23.34 | F17: =SUM(F18:F20) -> 23.55 | G17: =SUM(G18:G20) -> 24.35 | H17: =SUM(H18:H20) -> 25.62 | I17: =SUM(I18:I20) -> 0 | J17: =SUM(J18:J20) -> 0 | ... N17: =SUM(N18:N20) -> 0
B18: Demand Charges | C18: 5.58 | D18: 5.88 | E18: 5.56 | F18: 5.53 | G18: 7.21 | H18: 7.25
B19: Power Cost - Excl. Demand Charge | C19: 10.47 | D19: 15.14 | E19: 17.78 | F19: 18.02 | G19: 17.14 | H19: 18.37
B20: DG fuel | C20: 0 | D20: 0 | E20: 0 | F20: 0 | G20: 0 | H20: 0
A21: 4 | B21: Consumption for Plant & Mach. Maintenance: | C21: 1.38 | D21: 2.28 | E21: 2.31 | F21: 3.41 | G21: 2.28 | H21: 1.97
A22: 5 | B22: Other Expenses as per trial (Factory): | C22: =SUM(C23:C31) -> 4.62 | D22: =SUM(D23:D31) -> 5.7 | E22: =SUM(E23:E31) -> 5.93 | F22: =SUM(F23:F31) -> 5.44 | G22: =SUM(G23:G31) -> 4.71 | H22: =SUM(H23:H31) -> 10.14 | I22: =SUM(I23:I31) -> 0 | J22: =SUM(J23:J31) -> 0 | ... N22: =SUM(N23:N31) -> 0
B23: Machinery Maintenance - Service | C23: 0.03 | D23: 1.34 | E23: 1.38 | F23: 0.46 | G23: 0.22 | H23: 0.51
B24: Maintenance - Building | C24: 0 | D24: 0 | E24: 0 | F24: 1.38 | G24: 0 | H24: 2.13
B25: Security Exp | C25: 1.46 | D25: 1.5 | E25: 1.45 | F25: 1.55 | G25: 1.46 | H25: 1.46
B26: Manufacturing OH | C26: 3.06 | D26: 2.51 | E26: 2.48 | F26: 2 | G26: 2.98 | H26: 2.77
B27: Selling & Distribution Exp | C27: 0 | D27: 0 | E27: 0 | F27: 0 | G27: 0 | H27: 0
B28: Business Promotion | C28: 0.07 | D28: 0.35 | E28: 0.33 | F28: 0.05 | G28: 0.05 | H28: 0.05
B29: Transport agst Sale | C29: 0 | D29: 0 | E29: 0 | F29: 0 | G29: 0 | H29: 0
B30: Transport sale return | C30: 0 | D30: 0 | E30: 0.29 | F30: 0 | G30: 0 | H30: 3.22
B31: Liquidity damages | C31: 0 | D31: 0 | E31: 0 | F31: 0 | G31: 0 | H31: 0
A32: 6 | B32: Increase(+)/Decrease(-) in Stock (WIP) [as reported by factory] | C32: -31.72 | D32: 71.63 | E32: 32.47 | F32: -22.62 | G32: -40.89 | H32: 48.76
B33: OP WIP | C33: 152.29 | D33: =C34 -> 120.57 | E33: =D34 -> 192.2 | F33: =E34 -> 224.67 | G33: =F34 -> 202.05 | H33: =G34 -> 161.16 | I33: =H34 -> 209.92 | J33: =I34 -> 0 | K33: =J34 -> 0 | ... N33: =M34 -> 0
B34: CL WIP | C34: 120.57 | D34: 192.2 | E34: 224.67 | F34: 202.05 | G34: 161.16 | H34: 209.92
A35: 7 | B35: Increase(+)/Decrease(-) of Stock of Returned Goods [as reported] | C35: -15.08 | D35: -3.56 | E35: -4.02 | F35: -3.79 | G35: 1 | H35: 0.56
B36: OP Stock | C36: 58.66 | D36: =C37 -> 43.58 | E36: =D37 -> 40.03 | F36: =E37 -> 36.01 | G36: =F37 -> 32.22 | H36: =G37 -> 33.22 | I36: =H37 -> 33.78 | J36: =I37 -> 0 | K36: =J37 -> 0 | ... N36: =M37 -> 0
B37: CL Stock | C37: 43.58 | D37: 40.03 | E37: 36.01 | F37: 32.22 | G37: 33.22 | H37: 33.78
A38: 8 | B38: Sale (Fresh & Cus Ret. Goods) for the month: | C38: =SUM(C39:C40) -> 127.48 | D38: =SUM(D39:D40) -> 155.16 | E38: =SUM(E39:E40) -> 213.63 | F38: =SUM(F39:F40) -> 276.97 | G38: =SUM(G39:G40) -> 230.24 | H38: =SUM(H39:H40) -> 218.34 | I38: =SUM(I39:I40) -> 0 | J38: =SUM(J39:J40) -> 0 | ... N38: =SUM(N39:N40) -> 0
B39: a. Actual despatch Made | C39: 127.48 | D39: 90.02 | E39: 278.77 | F39: 276.97 | G39: 230.24 | H39: 218.34
B40: b. Ready to despatch _ Adjustment | C40: 0 | D40: 65.14 | E40: -65.14 | F40: 0 | G40: 0 | H40: 0
A41: 9 | B41: Other Sale / Income | C41: =SUM(C42:C48) -> 6.89 | D41: =SUM(D42:D48) -> 8.39 | E41: =SUM(E42:E48) -> 6.89 | F41: =SUM(F42:F48) -> 6.95 | G41: =SUM(G42:G48) -> 10.41 | H41: =SUM(H42:H48) -> 12.19 | I41: =SUM(I42:I48) -> 0 | J41: =SUM(J42:J48) -> 0 | ... N41: =SUM(N42:N48) -> 0
B42: Foundry return (Unusable) | C42: 0 | D42: 0 | E42: 0 | F42: 0 | G42: 0 | H42: 0
B43: Pattern | C43: 0 | D43: 1.5 | E43: 0 | F43: 0.06 | G43: 2.5 | H43: 4.8
B44: Transport ch | C44: 0 | D44: 0 | E44: 0 | F44: 0 | G44: 0 | H44: 0
B45: Storage Facility Service Ch | C45: 6.89 | D45: 6.89 | E45: 6.89 | F45: 6.89 | G45: 7.91 | H45: 7.39
B46: Electricity Facility To almatis | C46: 0 | D46: 0 | E46: 0 | F46: 0 | G46: 0 | H46: 0
B47: Suppl. Bill of Earlier Months | C47: 0 | D47: 0 | E47: 0 | F47: 0 | G47: 0 | H47: 0
B48: Suppl. Bill of Earlier Year | C48: 0 | D48: 0 | E48: 0 | F48: 0 | G48: 0 | H48: 0
A49: 10 | B49: Sales Return for the month (repairable goods included in Stock - returned goods): | C49: 0 | D49: 4.86 | E49: 7.15 | F49: 1.35 | G49: 1 | H49: 0.56
A50: 11 | B50: Raw material recovery from rejection of customers' returned goods (memo - not in PAT): | C50: =SUM(C51:C53) -> 0 | D50: =SUM(D51:D53) -> 0 | E50: =SUM(E51:E53) -> 0 | F50: =SUM(F51:F53) -> 0 | G50: =SUM(G51:G53) -> 0 | H50: =SUM(H51:H53) -> 0 | I50: =SUM(I51:I53) -> 0 | J50: =SUM(J51:J53) -> 0 | ... N50: =SUM(N51:N53) -> 0
B51: Value of Rejection at Sale Price | C51: 0 | D51: 0 | E51: 0 | F51: 0 | G51: 0 | H51: 0
B52: Raw Material Realisation | C52: 0 | D52: 0 | E52: 0 | F52: 0 | G52: 0 | H52: 0
B53: Loss on Returned Customer Goods Rejection | C53: 0 | D53: 0 | E53: 0 | F53: 0 | G53: 0 | H53: 0
B55: CHECKS
B56: WIP: CL - OP - reported change (should be ~0) | C56: =ROUND(C34-C33-C32,2) -> 0 | D56: =ROUND(D34-D33-D32,2) -> 0 | E56: =ROUND(E34-E33-E32,2) -> 0 | F56: =ROUND(F34-F33-F32,2) -> 0 | G56: =ROUND(G34-G33-G32,2) -> 0 | H56: =ROUND(H34-H33-H32,2) -> 0 | I56: =ROUND(I34-I33-I32,2) -> -209.92 | J56: =ROUND(J34-J33-J32,2) -> 0 | ... N56: =ROUND(N34-N33-N32,2) -> 0
B57: Returned goods: CL - OP - reported change (should be ~0) | C57: =ROUND(C37-C36-C35,2) -> 0 | D57: =ROUND(D37-D36-D35,2) -> 0.01 | E57: =ROUND(E37-E36-E35,2) -> 0 | F57: =ROUND(F37-F36-F35,2) -> 0 | G57: =ROUND(G37-G36-G35,2) -> 0 | H57: =ROUND(H37-H36-H35,2) -> 0 | I57: =ROUND(I37-I36-I35,2) -> -33.78 | J57: =ROUND(J37-J36-J35,2) -> 0 | ... N57: =ROUND(N37-N36-N35,2) -> 0

Sheet IN_Contrib
A1: CONTRIBUTION DATA - product-wise monthly cost sheet (append new month rows below; keep Year/Month text exact)
A3: Customer | B3: Year | C3: Month | D3: Product | E3: Weight per Casting (Kg) | F3: Pouring (Nos) | G3: Prodn-Pouring (MT) | H3: Rejn In House (Nos) | I3: Destruct. Test (Nos) | J3: Effective Yield % | K3: Melting Raw Mat Cost Rs/kg | L3: Melting Refractories etc Rs/kg | M3: MLD Mat Cost Rs/kg | N3: FTL Mat Cost Rs/kg | O3: Component Rs/kg | P3: Inspn Mat Rs/kg | Q3: Spl Material per Kg | R3: Packg & Painting Rs/kg | S3: Total Material Cost Rs/kg | T3: Other Direct Exp per Kg | U3: Labour Charges Rs/kg | V3: Power Cost (Var) Rs/kg | W3: Total Var Cost Rs/kg | X3: Effective Sale Price Rs/kg | Y3: Contribution Rs/kg | Z3: Customer-wise Contribution Rs L | AA3: Rejn Loss (Exc OH) Rs L | AB3: Loss on Destruct Test Rs L | AC3: Loss of Contribution Rejn & Destr. Rs L | AD3: Rejection MT (calc) | AE3: Destruct Test MT (calc) | AF3: Var Cost check (Mat+Oth+Lab+Pow-Total) | AG3: Contrib/kg check (Sale-Var-Contr)
A4: Tega | B4: 2022-23 | C4: April | D4: RM-22-00587E000-T1 | E4: 18.75 | F4: 6 | G4: 0.11 | J4: 59.61 | K4: 108.92 | L4: 2.21 | M4: 19.55 | N4: 3.9 | O4: 0.45 | P4: 1.5 | R4: 1.1 | S4: 137.63 | T4: 0.9 | U4: 10 | V4: 20.68 | W4: 169.2 | X4: 223.53 | Y4: 54.33 | Z4: 0.06 | AA4: 0 | AB4: 0 | AC4: 0 | AD4: =H4*E4/1000 -> 0 | AE4: =I4*E4/1000 -> 0 | AF4: =ROUND(S4+T4+U4+V4-W4,2) -> 0.01 | AG4: =ROUND(X4-W4-Y4,2) -> 0
A5: Tega | B5: 2022-23 | C5: April | D5: RM-22-00589E000-T1 | E5: 25 | F5: 24 | G5: 0.6 | J5: 63.85 | K5: 108.46 | L5: 2.07 | M5: 19.54 | N5: 3.9 | O5: 0.45 | P5: 1.5 | R5: 1.1 | S5: 137.02 | T5: 0.9 | U5: 10 | V5: 19.89 | W5: 167.81 | X5: 223.53 | Y5: 55.72 | Z5: 0.33 | AA5: 0 | AB5: 0 | AC5: 0 | AD5: =H5*E5/1000 -> 0 | AE5: =I5*E5/1000 -> 0 | AF5: =ROUND(S5+T5+U5+V5-W5,2) -> 0 | AG5: =ROUND(X5-W5-Y5,2) -> 0
A6: Tega | B6: 2022-23 | C6: April | D6: RM-22-01952AN00-T1 | E6: 20.7 | F6: 8 | G6: 0.17 | J6: 59.04 | K6: 108.99 | L6: 2.24 | M6: 18.01 | N6: 3.9 | O6: 0.45 | P6: 1.5 | R6: 1.1 | S6: 136.18 | T6: 0.9 | U6: 10 | V6: 20.79 | W6: 167.87 | X6: 223.53 | Y6: 55.66 | Z6: 0.09 | AA6: 0 | AB6: 0 | AC6: 0 | AD6: =H6*E6/1000 -> 0 | AE6: =I6*E6/1000 -> 0 | AF6: =ROUND(S6+T6+U6+V6-W6,2) -> 0 | AG6: =ROUND(X6-W6-Y6,2) -> 0
A7: Tega | B7: 2022-23 | C7: April | D7: RM-22-01879ON00-T1 | E7: 29.7 | F7: 18 | G7: 0.53 | J7: 60.87 | K7: 108.78 | L7: 2.17 | M7: 15.94 | N7: 3.9 | O7: 0.45 | P7: 1.5 | R7: 1.1 | S7: 133.84 | T7: 0.9 | U7: 10 | V7: 20.43 | W7: 165.17 | X7: 223.53 | Y7: 58.36 | Z7: 0.31 | AA7: 0 | AB7: 0 | AC7: 0 | AD7: =H7*E7/1000 -> 0 | AE7: =I7*E7/1000 -> 0 | AF7: =ROUND(S7+T7+U7+V7-W7,2) -> 0 | AG7: =ROUND(X7-W7-Y7,2) -> 0
A8: Tega | B8: 2022-23 | C8: April | D8: RM-22-02783ON00-T1 | E8: 39.26 | F8: 8 | G8: 0.31 | J8: 64.15 | K8: 108.43 | L8: 2.06 | M8: 13.65 | N8: 3.9 | O8: 0.54 | P8: 1.5 | R8: 1.1 | S8: 131.18 | T8: 0.9 | U8: 10 | V8: 19.84 | W8: 161.92 | X8: 223.53 | Y8: 61.61 | Z8: 0.19 | AA8: 0 | AB8: 0 | AC8: 0 | AD8: =H8*E8/1000 -> 0 | AE8: =I8*E8/1000 -> 0 | AF8: =ROUND(S8+T8+U8+V8-W8,2) -> 0 | AG8: =ROUND(X8-W8-Y8,2) -> 0
A9: Tega | B9: 2022-23 | C9: April | D9: RM-22-07245ON00-T1 | E9: 28.92 | F9: 4 | G9: 0.12 | J9: 63.01 | K9: 108.55 | L9: 2.09 | M9: 16.53 | N9: 3.9 | O9: 0.45 | P9: 1.5 | R9: 1.1 | S9: 134.12 | T9: 0.9 | U9: 10 | V9: 20.04 | W9: 165.06 | X9: 223.53 | Y9: 58.47 | Z9: 0.07 | AA9: 0 | AB9: 0 | AC9: 0 | AD9: =H9*E9/1000 -> 0 | AE9: =I9*E9/1000 -> 0 | AF9: =ROUND(S9+T9+U9+V9-W9,2) -> 0 | AG9: =ROUND(X9-W9-Y9,2) -> 0
A10: Tega | B10: 2022-23 | C10: May | D10: RM-22-00589E000-T1 | E10: 25 | F10: 96 | G10: 2.4 | J10: 63.85 | K10: 123.74 | L10: 2.07 | M10: 19.25 | N10: 3.9 | O10: 0.45 | P10: 1.5 | R10: 1.1 | S10: 152.02 | T10: 0.9 | U10: 10.2 | V10: 18.52 | W10: 181.64 | X10: 223.53 | Y10: 41.89 | Z10: 1.01 | AA10: 0 | AB10: 0 | AC10: 0 | AD10: =H10*E10/1000 -> 0 | AE10: =I10*E10/1000 -> 0 | AF10: =ROUND(S10+T10+U10+V10-W10,2) -> 0 | AG10: =ROUND(X10-W10-Y10,2) -> 0
A11: Tega | B11: 2022-23 | C11: May | D11: RM-22-01952AN00-T1 | E11: 20.7 | F11: 52 | G11: 1.08 | I11: 1 | J11: 59.04 | K11: 124.34 | L11: 2.24 | M11: 17.77 | N11: 3.9 | O11: 0.45 | P11: 1.5 | R11: 1.1 | S11: 151.3 | T11: 0.9 | U11: 10.2 | V11: 19.39 | W11: 181.79 | X11: 223.53 | Y11: 41.74 | Z11: 0.43 | AA11: 0 | AB11: 0.01 | AC11: 0.01 | AD11: =H11*E11/1000 -> 0 | AE11: =I11*E11/1000 -> 0.0207 | AF11: =ROUND(S11+T11+U11+V11-W11,2) -> 0 | AG11: =ROUND(X11-W11-Y11,2) -> 0
A12: Tega | B12: 2022-23 | C12: May | D12: RM-22-06182ON00-T1 | E12: 18 | F12: 1 | G12: 0.02 | J12: 64.17 | K12: 123.71 | L12: 2.06 | M12: 15.6 | N12: 3.9 | O12: 0.45 | P12: 1.5 | R12: 1.1 | S12: 148.31 | T12: 0.9 | U12: 10.2 | V12: 18.47 | W12: 177.88 | X12: 223.53 | Y12: 45.65 | Z12: 0.01 | AA12: 0 | AB12: 0 | AC12: 0 | AD12: =H12*E12/1000 -> 0 | AE12: =I12*E12/1000 -> 0 | AF12: =ROUND(S12+T12+U12+V12-W12,2) -> 0 | AG12: =ROUND(X12-W12-Y12,2) -> 0
A13: Tega | B13: 2022-23 | C13: May | D13: RM-22-01879ON00-T1 | E13: 29.7 | F13: 24 | G13: 0.71 | J13: 60.87 | K13: 124.1 | L13: 2.17 | M13: 15.72 | N13: 3.9 | O13: 0.45 | P13: 1.5 | R13: 1.1 | S13: 148.94 | T13: 0.9 | U13: 10.2 | V13: 19.05 | W13: 179.08 | X13: 223.53 | Y13: 44.45 | Z13: 0.32 | AA13: 0 | AB13: 0 | AC13: 0 | AD13: =H13*E13/1000 -> 0 | AE13: =I13*E13/1000 -> 0 | AF13: =ROUND(S13+T13+U13+V13-W13,2) -> 0.01 | AG13: =ROUND(X13-W13-Y13,2) -> 0
A14: Tega | B14: 2022-23 | C14: May | D14: RM-22-02782ON00-T1 | E14: 28 | F14: 1 | G14: 0.03 | J14: 68 | K14: 123.3 | L14: 1.94 | M14: 16.59 | N14: 3.9 | O14: 0.45 | P14: 1.5 | R14: 1.1 | S14: 148.78 | T14: 0.9 | U14: 10.2 | V14: 17.87 | W14: 177.75 | X14: 223.53 | Y14: 45.78 | Z14: 0.01 | AA14: 0 | AB14: 0 | AC14: 0 | AD14: =H14*E14/1000 -> 0 | AE14: =I14*E14/1000 -> 0 | AF14: =ROUND(S14+T14+U14+V14-W14,2) -> 0 | AG14: =ROUND(X14-W14-Y14,2) -> 0
A15: Tega | B15: 2022-23 | C15: May | D15: RM-22-02783ON00-T1 | E15: 39.26 | F15: 224 | G15: 8.79 | H15: 21 | I15: 2 | J15: 64.15 | K15: 123.71 | L15: 2.06 | M15: 13.45 | N15: 3.9 | O15: 0.54 | P15: 1.5 | R15: 1.1 | S15: 146.26 | T15: 0.9 | U15: 10.2 | V15: 18.47 | W15: 175.83 | X15: 223.53 | Y15: 47.7 | Z15: 3.33 | AA15: 0.39 | AB15: 0.04 | AC15: 0.43 | AD15: =H15*E15/1000 -> 0.82446 | AE15: =I15*E15/1000 -> 0.07852 | AF15: =ROUND(S15+T15+U15+V15-W15,2) -> 0 | AG15: =ROUND(X15-W15-Y15,2) -> 0
A16: Tega | B16: 2022-23 | C16: May | D16: RM-22-07245ON00-T1 | E16: 28.92 | F16: 32 | G16: 0.93 | H16: 2 | J16: 63.01 | K16: 123.84 | L16: 2.09 | M16: 16.29 | N16: 3.9 | O16: 0.45 | P16: 1.5 | R16: 1.1 | S16: 149.18 | T16: 0.9 | U16: 10.2 | V16: 18.66 | W16: 178.94 | X16: 223.53 | Y16: 44.59 | Z16: 0.36 | AA16: 0.03 | AB16: 0 | AC16: 0.03 | AD16: =H16*E16/1000 -> 0.05784 | AE16: =I16*E16/1000 -> 0 | AF16: =ROUND(S16+T16+U16+V16-W16,2) -> 0 | AG16: =ROUND(X16-W16-Y16,2) -> 0
A17: Tega | B17: 2022-23 | C17: August | D17: RM-22-00593C000-T1 | E17: 34.5 | F17: 142 | G17: 4.9 | J17: 69.03 | K17: 122.74 | L17: 1.91 | M17: 13.2 | N17: 3.9 | O17: 0.54 | P17: 1.5 | R17: 1.1 | S17: 144.89 | T17: 0.9 | U17: 10.74 | V17: 17.74 | W17: 174.28 | X17: 223.53 | Y17: 49.25 | Z17: 2.41 | AA17: 0 | AB17: 0 | AC17: 0 | AD17: =H17*E17/1000 -> 0 | AE17: =I17*E17/1000 -> 0 | AF17: =ROUND(S17+T17+U17+V17-W17,2) -> -0.01 | AG17: =ROUND(X17-W17-Y17,2) -> 0
A18: Tega | B18: 2022-23 | C18: August | D18: RM-22-00591C000-T1 | E18: 26.17 | F18: 42 | G18: 1.1 | H18: 1 | J18: 65.78 | K18: 123.07 | L18: 2.01 | M18: 15.46 | N18: 3.9 | O18: 0.45 | P18: 1.5 | R18: 1.1 | S18: 147.49 | T18: 0.9 | U18: 10.74 | V18: 18.22 | W18: 177.36 | X18: 223.53 | Y18: 46.17 | Z18: 0.48 | AA18: 0.01 | AB18: 0 | AC18: 0.01 | AD18: =H18*E18/1000 -> 0.02617 | AE18: =I18*E18/1000 -> 0 | AF18: =ROUND(S18+T18+U18+V18-W18,2) -> -0.01 | AG18: =ROUND(X18-W18-Y18,2) -> 0
A19: Tega | B19: 2022-23 | C19: August | D19: RM-22-01972AN00-T1 | E19: 50.5 | F19: 60 | G19: 3.03 | H19: 1 | J19: 70.44 | K19: 122.61 | L19: 1.87 | M19: 13.67 | N19: 3.9 | O19: 0.45 | P19: 1.5 | R19: 1.1 | S19: 145.1 | T19: 0.9 | U19: 10.74 | V19: 17.55 | W19: 174.28 | X19: 223.53 | Y19: 49.25 | Z19: 1.44 | AA19: 0.02 | AB19: 0 | AC19: 0.02 | AD19: =H19*E19/1000 -> 0.0505 | AE19: =I19*E19/1000 -> 0 | AF19: =ROUND(S19+T19+U19+V19-W19,2) -> 0.01 | AG19: =ROUND(X19-W19-Y19,2) -> 0
A20: Tega | B20: 2022-23 | C20: August | D20: RM-22-00919AN00-T1 | E20: 22.5 | F20: 70 | G20: 1.58 | J20: 63.96 | K20: 123.27 | L20: 2.06 | M20: 15.66 | N20: 3.9 | O20: 0.45 | P20: 1.5 | R20: 1.1 | S20: 147.95 | T20: 0.9 | U20: 10.74 | V20: 18.52 | W20: 178.1 | X20: 223.53 | Y20: 45.43 | Z20: 0.72 | AA20: 0 | AB20: 0 | AC20: 0 | AD20: =H20*E20/1000 -> 0 | AE20: =I20*E20/1000 -> 0 | AF20: =ROUND(S20+T20+U20+V20-W20,2) -> 0.01 | AG20: =ROUND(X20-W20-Y20,2) -> 0
A21: Tega | B21: 2022-23 | C21: September | D21: RM-22-00593C000-T1 | E21: 34.5 | F21: 4 | G21: 0.14 | H21: 1 | J21: 69.03 | K21: 107.83 | L21: 1.91 | M21: 11.08 | N21: 3.9 | O21: 0.54 | P21: 1.5 | R21: 1.1 | S21: 127.86 | T21: 0.9 | U21: 10.74 | V21: 16.7 | W21: 156.2 | X21: 223.53 | Y21: 67.33 | Z21: 0.06 | AA21: 0.01 | AB21: 0 | AC21: 0.02 | AD21: =H21*E21/1000 -> 0.0345 | AE21: =I21*E21/1000 -> 0 | AF21: =ROUND(S21+T21+U21+V21-W21,2) -> 0 | AG21: =ROUND(X21-W21-Y21,2) -> 0
A22: Tega | B22: 2022-23 | C22: September | D22: RM-22-00591C000-T1 | E22: 26.17 | F22: 4 | G22: 0.1 | H22: 1 | J22: 65.78 | K22: 108.12 | L22: 2.01 | M22: 13.06 | N22: 3.9 | O22: 0.45 | P22: 1.5 | R22: 1.1 | S22: 130.13 | T22: 0.9 | U22: 10.74 | V22: 17.15 | W22: 158.92 | X22: 223.53 | Y22: 64.61 | Z22: 0.04 | AA22: 0.01 | AB22: 0 | AC22: 0.02 | AD22: =H22*E22/1000 -> 0.02617 | AE22: =I22*E22/1000 -> 0 | AF22: =ROUND(S22+T22+U22+V22-W22,2) -> 0 | AG22: =ROUND(X22-W22-Y22,2) -> 0
A23: Tega | B23: 2022-23 | C23: September | D23: RM-22-01972AN00-T1 | E23: 50.5 | F23: 66 | G23: 3.33 | H23: 5 | J23: 70.44 | K23: 107.71 | L23: 1.87 | M23: 11.35 | N23: 3.9 | O23: 0.45 | P23: 1.5 | R23: 1.1 | S23: 127.88 | T23: 0.9 | U23: 10.74 | V23: 16.51 | W23: 156.04 | X23: 223.53 | Y23: 67.49 | Z23: 1.98 | AA23: 0.1 | AB23: 0 | AC23: 0.17 | AD23: =H23*E23/1000 -> 0.2525 | AE23: =I23*E23/1000 -> 0 | AF23: =ROUND(S23+T23+U23+V23-W23,2) -> -0.01 | AG23: =ROUND(X23-W23-Y23,2) -> 0
A24: Tega | B24: 2022-23 | C24: September | D24: RM-22-00919AN00-T1 | E24: 22.5 | F24: 6 | G24: 0.14 | J24: 63.96 | K24: 108.29 | L24: 2.06 | M24: 12.99 | N24: 3.9 | O24: 0.45 | P24: 1.5 | R24: 1.1 | S24: 130.29 | T24: 0.9 | U24: 10.74 | V24: 17.43 | W24: 159.36 | X24: 223.53 | Y24: 64.17 | Z24: 0.09 | AA24: 0 | AB24: 0 | AC24: 0 | AD24: =H24*E24/1000 -> 0 | AE24: =I24*E24/1000 -> 0 | AF24: =ROUND(S24+T24+U24+V24-W24,2) -> 0 | AG24: =ROUND(X24-W24-Y24,2) -> 0
A25: Tega | B25: 2022-23 | C25: December | D25: RM-22-00587E000-T1 | E25: 18.75 | F25: 8 | G25: 0.15 | J25: 59.61 | K25: 147 | L25: 2.21 | M25: 20.46 | N25: 3.9 | O25: 0.45 | P25: 1.5 | R25: 1.1 | S25: 176.63 | T25: 0.9 | U25: 10.74 | V25: 17.17 | W25: 205.44 | X25: 229.13 | Y25: 23.69 | Z25: 0.04 | AA25: 0 | AB25: 0 | AC25: 0 | AD25: =H25*E25/1000 -> 0 | AE25: =I25*E25/1000 -> 0 | AF25: =ROUND(S25+T25+U25+V25-W25,2) -> 0 | AG25: =ROUND(X25-W25-Y25,2) -> 0
A26: Tega | B26: 2022-23 | C26: December | D26: RM-22-00589E000-T1 | E26: 25 | F26: 126 | G26: 3.15 | H26: 6 | J26: 63.85 | K26: 146.39 | L26: 2.07 | M26: 20.53 | N26: 3.9 | O26: 0.45 | P26: 1.5 | R26: 1.1 | S26: 175.94 | T26: 0.9 | U26: 10.74 | V26: 16.5 | W26: 204.08 | X26: 229.13 | Y26: 25.05 | Z26: 0.67 | AA26: 0.08 | AB26: 0 | AC26: 0.04 | AD26: =H26*E26/1000 -> 0.15 | AE26: =I26*E26/1000 -> 0 | AF26: =ROUND(S26+T26+U26+V26-W26,2) -> 0 | AG26: =ROUND(X26-W26-Y26,2) -> 0
A27: Tega | B27: 2022-23 | C27: December | D27: RM-22-01952AN00-T1 | E27: 20.7 | F27: 64 | G27: 1.3248 | J27: 59.04 | K27: 147.09 | L27: 2.24 | M27: 18.87 | N27: 3.9 | O27: 0.45 | P27: 1.5 | R27: 1.1 | S27: 175.14 | T27: 0.9 | U27: 10.74 | V27: 17.27 | W27: 204.05 | X27: 229.13 | Y27: 25.08 | Z27: 0.33 | AA27: 0 | AB27: 0 | AC27: 0 | AD27: =H27*E27/1000 -> 0 | AE27: =I27*E27/1000 -> 0 | AF27: =ROUND(S27+T27+U27+V27-W27,2) -> 0 | AG27: =ROUND(X27-W27-Y27,2) -> 0
A28: Tega | B28: 2022-23 | C28: December | D28: RM-22-00595G000-T1 | E28: 31.66 | F28: 8 | G28: 0.2533 | J28: 61.09 | K28: 146.78 | L28: 2.16 | M28: 15.57 | N28: 3.9 | O28: 0.45 | P28: 1.5 | R28: 1.1 | S28: 171.46 | T28: 0.9 | U28: 10.74 | V28: 16.93 | W28: 200.03 | X28: 244 | Y28: 43.97 | Z28: 0.11 | AA28: 0 | AB28: 0 | AC28: 0 | AD28: =H28*E28/1000 -> 0 | AE28: =I28*E28/1000 -> 0 | AF28: =ROUND(S28+T28+U28+V28-W28,2) -> 0 | AG28: =ROUND(X28-W28-Y28,2) -> 0
A29: Tega | B29: 2022-23 | C29: December | D29: RM-22-03070CN00-T1 | E29: 25 | F29: 6 | G29: 0.15 | J29: 58.82 | K29: 147.13 | L29: 2.24 | M29: 15.28 | N29: 3.9 | O29: 0.45 | P29: 1.5 | R29: 1.1 | S29: 171.6 | T29: 0.9 | U29: 10.74 | V29: 17.3 | W29: 200.54 | X29: 244 | Y29: 43.46 | Z29: 0.07 | AA29: 0 | AB29: 0 | AC29: 0 | AD29: =H29*E29/1000 -> 0 | AE29: =I29*E29/1000 -> 0 | AF29: =ROUND(S29+T29+U29+V29-W29,2) -> 0 | AG29: =ROUND(X29-W29-Y29,2) -> 0
A30: Tega | B30: 2022-23 | C30: December | D30: RM-22-03070CN01-T1 | E30: 34 | F30: 4 | G30: 0.136 | J30: 66.4 | K30: 146.06 | L30: 1.99 | M30: 14.64 | N30: 3.9 | O30: 0.45 | P30: 1.5 | R30: 1.1 | S30: 169.64 | T30: 0.9 | U30: 10.74 | V30: 16.14 | W30: 197.42 | X30: 244 | Y30: 46.58 | Z30: 0.06 | AA30: 0 | AB30: 0 | AC30: 0 | AD30: =H30*E30/1000 -> 0 | AE30: =I30*E30/1000 -> 0 | AF30: =ROUND(S30+T30+U30+V30-W30,2) -> 0 | AG30: =ROUND(X30-W30-Y30,2) -> 0
A31: Tega | B31: 2022-23 | C31: December | D31: RM-22-03070CN02-T1 | E31: 23 | F31: 6 | G31: 0.138 | J31: 61.5 | K31: 146.72 | L31: 2.15 | M31: 15.9 | N31: 3.9 | O31: 0.45 | P31: 1.5 | R31: 1.1 | S31: 171.71 | T31: 0.9 | U31: 10.74 | V31: 16.86 | W31: 200.21 | X31: 244 | Y31: 43.79 | Z31: 0.06 | AA31: 0 | AB31: 0 | AC31: 0 | AD31: =H31*E31/1000 -> 0 | AE31: =I31*E31/1000 -> 0 | AF31: =ROUND(S31+T31+U31+V31-W31,2) -> 0 | AG31: =ROUND(X31-W31-Y31,2) -> 0
A32: Tega | B32: 2022-23 | C32: December | D32: RM-22-06182ON00-T1 | E32: 18 | F32: 1 | G32: 0.018 | J32: 64.17 | K32: 146.35 | L32: 2.06 | M32: 16.68 | N32: 3.9 | O32: 0.45 | P32: 1.5 | R32: 1.1 | S32: 172.04 | T32: 0.9 | U32: 10.74 | V32: 16.46 | W32: 200.13 | X32: 229.13 | Y32: 29 | Z32: 0.01 | AA32: 0 | AB32: 0 | AC32: 0 | AD32: =H32*E32/1000 -> 0 | AE32: =I32*E32/1000 -> 0 | AF32: =ROUND(S32+T32+U32+V32-W32,2) -> 0.01 | AG32: =ROUND(X32-W32-Y32,2) -> 0
A33: Tega | B33: 2022-23 | C33: December | D33: RM-22-01879ON00-T1 | E33: 29.7 | F33: 42 | G33: 1.2474 | J33: 60.87 | K33: 146.81 | L33: 2.17 | M33: 16.73 | N33: 3.9 | O33: 0.45 | P33: 1.5 | R33: 1.1 | S33: 172.66 | T33: 0.9 | U33: 10.74 | V33: 16.96 | W33: 201.26 | X33: 229.13 | Y33: 27.87 | Z33: 0.35 | AA33: 0 | AB33: 0 | AC33: 0 | AD33: =H33*E33/1000 -> 0 | AE33: =I33*E33/1000 -> 0 | AF33: =ROUND(S33+T33+U33+V33-W33,2) -> 0 | AG33: =ROUND(X33-W33-Y33,2) -> 0
A34: Tega | B34: 2022-23 | C34: December | D34: RM-22-02782ON00-T1 | E34: 28 | F34: 3 | G34: 0.084 | H34: 2 | J34: 68 | K34: 145.86 | L34: 1.94 | M34: 17.75 | N34: 3.9 | O34: 0.45 | P34: 1.5 | R34: 1.1 | S34: 172.5 | T34: 0.9 | U34: 10.74 | V34: 15.93 | W34: 200.08 | X34: 229.13 | Y34: 29.05 | Z34: -0.02 | AA34: 0.03 | AB34: 0 | AC34: 0.02 | AD34: =H34*E34/1000 -> 0.056 | AE34: =I34*E34/1000 -> 0 | AF34: =ROUND(S34+T34+U34+V34-W34,2) -> -0.01 | AG34: =ROUND(X34-W34-Y34,2) -> 0
A35: Tega | B35: 2022-23 | C35: December | D35: RM-22-02783ON00-T1 | E35: 39.26 | F35: 216 | G35: 8.4802 | H35: 1 | J35: 64.15 | K35: 146.35 | L35: 2.06 | M35: 14.34 | N35: 3.9 | O35: 0.54 | P35: 1.5 | R35: 1.1 | S35: 169.79 | T35: 0.9 | U35: 10.74 | V35: 16.46 | W35: 197.89 | X35: 229.13 | Y35: 31.24 | Z35: 2.62 | AA35: 0.02 | AB35: 0 | AC35: 0.01 | AD35: =H35*E35/1000 -> 0.03926 | AE35: =I35*E35/1000 -> 0 | AF35: =ROUND(S35+T35+U35+V35-W35,2) -> 0 | AG35: =ROUND(X35-W35-Y35,2) -> 0
A36: Tega | B36: 2022-23 | C36: December | D36: RM-22-07245ON00-T1 | E36: 28.92 | F36: 32 | G36: 0.9254 | J36: 63.01 | K36: 146.51 | L36: 2.09 | M36: 17.36 | N36: 3.9 | O36: 0.45 | P36: 1.5 | R36: 1.1 | S36: 172.91 | T36: 0.9 | U36: 10.74 | V36: 16.63 | W36: 201.18 | X36: 229.13 | Y36: 27.95 | Z36: 0.26 | AA36: 0 | AB36: 0 | AC36: 0 | AD36: =H36*E36/1000 -> 0 | AE36: =I36*E36/1000 -> 0 | AF36: =ROUND(S36+T36+U36+V36-W36,2) -> 0 | AG36: =ROUND(X36-W36-Y36,2) -> 0
A37: Tega | B37: 2022-23 | C37: January | D37: RM-22-00595G000-T1 | E37: 31.66 | F37: 104 | G37: 3.2926 | H37: 10 | J37: 61.09 | K37: 148.44 | L37: 2.16 | M37: 15.57 | N37: 3.9 | O37: 0.45 | P37: 1.5 | R37: 1.1 | S37: 173.12 | T37: 0.9 | U37: 10.74 | V37: 16.93 | W37: 201.69 | X37: 244 | Y37: 42.31 | Z37: 1.1 | AA37: 0.16 | AB37: 0 | AC37: 0.13 | AD37: =H37*E37/1000 -> 0.3166 | AE37: =I37*E37/1000 -> 0 | AF37: =ROUND(S37+T37+U37+V37-W37,2) -> 0 | AG37: =ROUND(X37-W37-Y37,2) -> 0
A38: Tega | B38: 2022-23 | C38: January | D38: RM-22-03070CN00-T1 | E38: 25 | F38: 276 | G38: 6.9 | H38: 37 | J38: 58.82 | K38: 148.79 | L38: 2.24 | M38: 15.28 | N38: 3.9 | O38: 0.45 | P38: 1.5 | R38: 1.1 | S38: 173.26 | T38: 0.9 | U38: 10.74 | V38: 17.3 | W38: 202.21 | X38: 244 | Y38: 41.79 | Z38: 2.04 | AA38: 0.46 | AB38: 0 | AC38: 0.39 | AD38: =H38*E38/1000 -> 0.925 | AE38: =I38*E38/1000 -> 0 | AF38: =ROUND(S38+T38+U38+V38-W38,2) -> -0.01 | AG38: =ROUND(X38-W38-Y38,2) -> 0
A39: Tega | B39: 2022-23 | C39: January | D39: RM-22-03070CN01-T1 | E39: 34 | F39: 52 | G39: 1.768 | H39: 3 | J39: 66.4 | K39: 147.71 | L39: 1.99 | M39: 14.64 | N39: 3.9 | O39: 0.45 | P39: 1.5 | R39: 1.1 | S39: 171.29 | T39: 0.9 | U39: 10.74 | V39: 16.14 | W39: 199.07 | X39: 244 | Y39: 44.93 | Z39: 0.7 | AA39: 0.05 | AB39: 0 | AC39: 0.05 | AD39: =H39*E39/1000 -> 0.102 | AE39: =I39*E39/1000 -> 0 | AF39: =ROUND(S39+T39+U39+V39-W39,2) -> 0 | AG39: =ROUND(X39-W39-Y39,2) -> 0
A40: Tega | B40: 2022-23 | C40: January | D40: RM-22-03070CN02-T1 | E40: 23 | F40: 52 | G40: 1.196 | H40: 5 | J40: 61.5 | K40: 148.38 | L40: 2.15 | M40: 15.9 | N40: 3.9 | O40: 0.45 | P40: 1.5 | R40: 1.1 | S40: 173.37 | T40: 0.9 | U40: 10.74 | V40: 16.86 | W40: 201.87 | X40: 244 | Y40: 42.13 | Z40: 0.4 | AA40: 0.06 | AB40: 0 | AC40: 0.05 | AD40: =H40*E40/1000 -> 0.115 | AE40: =I40*E40/1000 -> 0 | AF40: =ROUND(S40+T40+U40+V40-W40,2) -> 0 | AG40: =ROUND(X40-W40-Y40,2) -> 0
A41: Tega | B41: 2022-23 | C41: February | D41: RM-22-01945AN00-T1 | E41: 28.96 | F41: 8 | G41: 0.2317 | J41: 60.78 | K41: 156 | L41: 2.17 | M41: 13.04 | N41: 3.9 | O41: 0.54 | P41: 1.5 | R41: 1.1 | S41: 178.25 | T41: 0.9 | U41: 10.74 | V41: 16.45 | W41: 206.34 | X41: 283.11 | Y41: 76.77 | Z41: 0.18 | AA41: 0 | AB41: 0 | AC41: 0 | AD41: =H41*E41/1000 -> 0 | AE41: =I41*E41/1000 -> 0 | AF41: =ROUND(S41+T41+U41+V41-W41,2) -> 0 | AG41: =ROUND(X41-W41-Y41,2) -> 0
A42: Tega | B42: 2022-23 | C42: February | D42: RM-22-01944AN00-T1 | E42: 38.05 | F42: 12 | G42: 0.4566 | J42: 64.1 | K42: 155.51 | L42: 2.06 | M42: 16.58 | N42: 3.9 | O42: 0.54 | P42: 1.5 | R42: 1.1 | S42: 181.19 | T42: 0.9 | U42: 10.74 | V42: 15.96 | W42: 208.79 | X42: 283.11 | Y42: 74.32 | Z42: 0.34 | AA42: 0 | AB42: 0 | AC42: 0 | AD42: =H42*E42/1000 -> 0 | AE42: =I42*E42/1000 -> 0 | AF42: =ROUND(S42+T42+U42+V42-W42,2) -> 0 | AG42: =ROUND(X42-W42-Y42,2) -> 0
A43: Tega | B43: 2022-23 | C43: February | D43: RM-22-01972AN00-T1 | E43: 50.5 | F43: 12 | G43: 1 | J43: 70.44 | K43: 154.68 | L43: 1.87 | M43: 14.01 | N43: 3.9 | O43: 0.45 | P43: 1.5 | R43: 1.1 | S43: 177.52 | T43: 0.9 | U43: 10.74 | V43: 15.15 | W43: 204.31 | X43: 283.11 | Y43: 78.8 | Z43: 0.48 | AA43: 0 | AB43: 0 | AC43: 0 | AD43: =H43*E43/1000 -> 0 | AE43: =I43*E43/1000 -> 0 | AF43: =ROUND(S43+T43+U43+V43-W43,2) -> 0 | AG43: =ROUND(X43-W43-Y43,2) -> 0
A44: Tega | B44: 2022-23 | C44: February | D44: RM-22-01973AN00-T1 | E44: 37.5 | F44: 8 | G44: 0.3 | J44: 63.73 | K44: 155.56 | L44: 2.07 | M44: 12.44 | N44: 3.9 | O44: 0.45 | P44: 1.5 | R44: 1.1 | S44: 177.02 | T44: 0.9 | U44: 10.74 | V44: 16.01 | W44: 204.67 | X44: 283.11 | Y44: 78.44 | Z44: 0.24 | AA44: 0 | AB44: 0 | AC44: 0 | AD44: =H44*E44/1000 -> 0 | AE44: =I44*E44/1000 -> 0 | AF44: =ROUND(S44+T44+U44+V44-W44,2) -> 0 | AG44: =ROUND(X44-W44-Y44,2) -> 0
A45: Tega | B45: 2022-23 | C45: February | D45: RM-22-01974AN00-T1 | E45: 35.75 | F45: 8 | G45: 0.286 | J45: 70.98 | K45: 154.62 | L45: 1.86 | M45: 12.26 | N45: 3.9 | O45: 0.45 | P45: 1.5 | R45: 1.1 | S45: 175.69 | T45: 0.9 | U45: 10.74 | V45: 15.09 | W45: 202.42 | X45: 283.11 | Y45: 80.69 | Z45: 0.23 | AA45: 0 | AB45: 0 | AC45: 0 | AD45: =H45*E45/1000 -> 0 | AE45: =I45*E45/1000 -> 0 | AF45: =ROUND(S45+T45+U45+V45-W45,2) -> 0 | AG45: =ROUND(X45-W45-Y45,2) -> 0
A46: Tega | B46: 2022-23 | C46: March | D46: RM-22-01945AN00-T1 | E46: 28.96 | F46: 1079 | G46: 31.248 | H46: 43 | J46: 60.78 | K46: 163.33 | L46: 2.17 | M46: 13.04 | N46: 3.9 | O46: 0.54 | P46: 1.5 | R46: 1.1 | S46: 185.57 | T46: 0.9 | U46: 7.74 | V46: 16.45 | W46: 210.67 | X46: 283.11 | Y46: 72.44 | Z46: 21.18 | AA46: 0.56 | AB46: 0 | AC46: 0.9 | AD46: =H46*E46/1000 -> 1.24528 | AE46: =I46*E46/1000 -> 0 | AF46: =ROUND(S46+T46+U46+V46-W46,2) -> -0.01 | AG46: =ROUND(X46-W46-Y46,2) -> 0
A47: Tega | B47: 2022-23 | C47: March | D47: RM-22-01976AN00-T1 | E47: 28 | F47: 552 | G47: 15.456 | H47: 12 | J47: 61 | K47: 163.29 | L47: 2.16 | M47: 13.6 | N47: 3.9 | O47: 0.45 | P47: 1.5 | R47: 1.1 | S47: 186 | T47: 0.9 | U47: 7.74 | V47: 16.42 | W47: 211.06 | X47: 283.11 | Y47: 72.05 | Z47: 10.74 | AA47: 0.15 | AB47: 0 | AC47: 0.24 | AD47: =H47*E47/1000 -> 0.336 | AE47: =I47*E47/1000 -> 0 | AF47: =ROUND(S47+T47+U47+V47-W47,2) -> 0 | AG47: =ROUND(X47-W47-Y47,2) -> 0
A48: Tega | B48: 2022-23 | C48: March | D48: RM-22-01944AN00-T1 | E48: 37.78 | F48: 132 | G48: 4.987 | J48: 64.1 | K48: 162.81 | L48: 2.06 | M48: 16.68 | N48: 3.9 | O48: 0.54 | P48: 1.5 | R48: 1.1 | S48: 188.59 | T48: 0.9 | U48: 7.74 | V48: 15.96 | W48: 213.19 | X48: 283.11 | Y48: 69.92 | Z48: 3.49 | AA48: 0 | AB48: 0 | AC48: 0 | AD48: =H48*E48/1000 -> 0 | AE48: =I48*E48/1000 -> 0 | AF48: =ROUND(S48+T48+U48+V48-W48,2) -> 0 | AG48: =ROUND(X48-W48-Y48,2) -> 0
A49: Tega | B49: 2022-23 | C49: March | D49: RM-22-01972AN00-T1 | E49: 50.15 | F49: 252 | G49: 13 | H49: 2 | J49: 70.44 | K49: 161.94 | L49: 1.87 | M49: 14.1 | N49: 3.9 | O49: 0.45 | P49: 1.5 | R49: 1.1 | S49: 184.86 | T49: 0.9 | U49: 7.74 | V49: 15.15 | W49: 208.65 | X49: 283.11 | Y49: 74.46 | Z49: 9.29 | AA49: 0.04 | AB49: 0 | AC49: 0.07 | AD49: =H49*E49/1000 -> 0.1003 | AE49: =I49*E49/1000 -> 0 | AF49: =ROUND(S49+T49+U49+V49-W49,2) -> 0 | AG49: =ROUND(X49-W49-Y49,2) -> 0
A50: Tega | B50: 2022-23 | C50: March | D50: RM-22-01973AN00-T1 | E50: 37.5 | F50: 488 | G50: 18.3 | J50: 63.73 | K50: 162.86 | L50: 2.07 | M50: 12.44 | N50: 3.9 | O50: 0.45 | P50: 1.5 | R50: 1.1 | S50: 184.32 | T50: 0.9 | U50: 7.74 | V50: 16.01 | W50: 208.97 | X50: 283.11 | Y50: 74.14 | Z50: 13.57 | AA50: 0 | AB50: 0 | AC50: 0 | AD50: =H50*E50/1000 -> 0 | AE50: =I50*E50/1000 -> 0 | AF50: =ROUND(S50+T50+U50+V50-W50,2) -> 0 | AG50: =ROUND(X50-W50-Y50,2) -> 0
A51: Tega | B51: 2022-23 | C51: March | D51: RM-22-01974AN00-T1 | E51: 35.75 | F51: 116 | G51: 4.147 | J51: 70.98 | K51: 161.88 | L51: 1.86 | M51: 12.26 | N51: 3.9 | O51: 0.45 | P51: 1.5 | R51: 1.1 | S51: 182.95 | T51: 0.9 | U51: 7.74 | V51: 15.09 | W51: 206.68 | X51: 283.11 | Y51: 76.43 | Z51: 3.17 | AA51: 0 | AB51: 0 | AC51: 0 | AD51: =H51*E51/1000 -> 0 | AE51: =I51*E51/1000 -> 0 | AF51: =ROUND(S51+T51+U51+V51-W51,2) -> 0 | AG51: =ROUND(X51-W51-Y51,2) -> 0
A52: Tega | B52: 2022-23 | C52: March | D52: RM-22-05785AN00-T1 | E52: 66.3 | F52: 3 | G52: 0.1989 | J52: 72.22 | K52: 161.73 | L52: 1.83 | M52: 11.47 | N52: 3.9 | O52: 0.45 | P52: 1.5 | R52: 1.1 | S52: 181.97 | T52: 0.9 | U52: 7.74 | V52: 14.95 | W52: 205.56 | X52: 282.19 | Y52: 76.63 | Z52: 0.15 | AA52: 0 | AB52: 0 | AC52: 0 | AD52: =H52*E52/1000 -> 0 | AE52: =I52*E52/1000 -> 0 | AF52: =ROUND(S52+T52+U52+V52-W52,2) -> 0 | AG52: =ROUND(X52-W52-Y52,2) -> 0
A53: Tega | B53: 2022-23 | C53: March | D53: RM-22-05786AN00-T1 | E53: 62 | F53: 3 | G53: 0.186 | J53: 71.79 | K53: 161.78 | L53: 1.84 | M53: 11.67 | N53: 3.9 | O53: 0.45 | P53: 1.5 | R53: 1.1 | S53: 182.24 | T53: 0.9 | U53: 7.74 | V53: 14.99 | W53: 205.87 | X53: 282.19 | Y53: 76.32 | Z53: 0.14 | AA53: 0 | AB53: 0 | AC53: 0 | AD53: =H53*E53/1000 -> 0 | AE53: =I53*E53/1000 -> 0 | AF53: =ROUND(S53+T53+U53+V53-W53,2) -> 0 | AG53: =ROUND(X53-W53-Y53,2) -> 0
A54: Tega | B54: 2022-23 | C54: March | D54: RM-22-05788AN00-T1 | E54: 44.15 | F54: 4 | G54: 0.1766 | J54: 67.89 | K54: 162.27 | L54: 1.94 | M54: 11.52 | N54: 3.9 | O54: 0.45 | P54: 1.5 | R54: 1.1 | S54: 182.68 | T54: 0.9 | U54: 7.74 | V54: 15.46 | W54: 206.78 | X54: 282.19 | Y54: 75.41 | Z54: 0.13 | AA54: 0 | AB54: 0 | AC54: 0 | AD54: =H54*E54/1000 -> 0 | AE54: =I54*E54/1000 -> 0 | AF54: =ROUND(S54+T54+U54+V54-W54,2) -> 0 | AG54: =ROUND(X54-W54-Y54,2) -> 0
A55: Tega | B55: 2022-23 | C55: March | D55: RM-22-05735ON00-T1 | E55: 63 | F55: 3 | G55: 0.189 | J55: 66.67 | K55: 162.44 | L55: 1.98 | M55: 12.26 | N55: 3.9 | O55: 0.45 | P55: 1.5 | R55: 1.1 | S55: 183.63 | T55: 0.9 | U55: 7.74 | V55: 15.61 | W55: 207.88 | X55: 282.19 | Y55: 74.31 | Z55: 0.14 | AA55: 0 | AB55: 0 | AC55: 0 | AD55: =H55*E55/1000 -> 0 | AE55: =I55*E55/1000 -> 0 | AF55: =ROUND(S55+T55+U55+V55-W55,2) -> 0 | AG55: =ROUND(X55-W55-Y55,2) -> 0
A56: Tega | B56: 2022-23 | C56: March | D56: RM-22-05735ON01-T1 | E56: 47 | F56: 4 | G56: 0.188 | J56: 68.2 | K56: 162.23 | L56: 1.94 | M56: 11.42 | N56: 3.9 | O56: 0.45 | P56: 1.5 | R56: 1.1 | S56: 182.54 | T56: 0.9 | U56: 7.74 | V56: 15.42 | W56: 206.6 | X56: 282.19 | Y56: 75.59 | Z56: 0.14 | AA56: 0 | AB56: 0 | AC56: 0 | AD56: =H56*E56/1000 -> 0 | AE56: =I56*E56/1000 -> 0 | AF56: =ROUND(S56+T56+U56+V56-W56,2) -> 0 | AG56: =ROUND(X56-W56-Y56,2) -> 0
A57: Tega | B57: 2022-23 | C57: March | D57: RM-22-06573ON00-T1 | E57: 32.7 | F57: 124 | G57: 4.0548 | J57: 62.55 | K57: 163.04 | L57: 2.11 | M57: 13.49 | N57: 3.9 | O57: 0.45 | P57: 1.5 | R57: 1.1 | S57: 185.59 | T57: 0.9 | U57: 7.74 | V57: 16.19 | W57: 210.41 | X57: 282.19 | Y57: 71.78 | Z57: 2.91 | AA57: 0 | AB57: 0 | AC57: 0 | AD57: =H57*E57/1000 -> 0 | AE57: =I57*E57/1000 -> 0 | AF57: =ROUND(S57+T57+U57+V57-W57,2) -> 0.01 | AG57: =ROUND(X57-W57-Y57,2) -> 0
A58: Tega | B58: 2022-23 | C58: March | D58: RM-22-07980N00-T1 | E58: 29 | F58: 8 | G58: 0.232 | J58: 63.01 | K58: 162.97 | L58: 2.09 | M58: 16.62 | N58: 3.9 | O58: 0.45 | P58: 1.5 | R58: 1.1 | S58: 188.64 | T58: 0.9 | U58: 7.74 | V58: 16.12 | W58: 213.39 | X58: 282.19 | Y58: 68.8 | Z58: 0.16 | AA58: 0 | AB58: 0 | AC58: 0 | AD58: =H58*E58/1000 -> 0 | AE58: =I58*E58/1000 -> 0 | AF58: =ROUND(S58+T58+U58+V58-W58,2) -> 0.01 | AG58: =ROUND(X58-W58-Y58,2) -> 0
A59: Tega | B59: 2022-23 | C59: March | D59: RM-22-09303ON00-M2 | E59: 95 | F59: 3 | G59: 0.285 | J59: 73.53 | K59: 50.9 | L59: 1.8 | M59: 14.86 | N59: 3.9 | O59: 0.45 | P59: 1.5 | R59: 1.1 | S59: 74.5 | T59: 0.9 | U59: 7.74 | V59: 14.8 | W59: 97.94 | X59: 155 | Y59: 57.06 | Z59: 0.16 | AA59: 0 | AB59: 0 | AC59: 0 | AD59: =H59*E59/1000 -> 0 | AE59: =I59*E59/1000 -> 0 | AF59: =ROUND(S59+T59+U59+V59-W59,2) -> 0 | AG59: =ROUND(X59-W59-Y59,2) -> 0
A60: Tega | B60: 2023-24 | C60: April | D60: RM-22-01972AN00-T1 | E60: 50.15 | F60: 449 | G60: 22.52 | H60: 30 | I60: 4 | J60: 70.44 | K60: 149.88 | L60: 1.87 | M60: 14.1 | N60: 3.9 | O60: 0.45 | P60: 1.5 | R60: 1.1 | S60: 172.8 | T60: 0.9 | U60: 7.74 | V60: 15.15 | W60: 196.59 | X60: 282.19 | Y60: 85.6 | Z60: 17.07 | AA60: 0.64 | AB60: 0.1 | AC60: 1.46 | AD60: =H60*E60/1000 -> 1.5045 | AE60: =I60*E60/1000 -> 0.2006 | AF60: =ROUND(S60+T60+U60+V60-W60,2) -> 0 | AG60: =ROUND(X60-W60-Y60,2) -> 0
A61: Tega | B61: 2023-24 | C61: April | D61: RM-22-01973AN00-T1 | E61: 37.5 | F61: 8 | G61: 0.3 | H61: 16 | J61: 63.73 | K61: 150.73 | L61: 2.07 | M61: 12.44 | N61: 3.9 | O61: 0.45 | P61: 1.5 | R61: 1.1 | S61: 172.19 | T61: 0.9 | U61: 7.74 | V61: 16.01 | W61: 196.84 | X61: 282.19 | Y61: 85.35 | Z61: -0.51 | AA61: 0.26 | AB61: 0 | AC61: 0.51 | AD61: =H61*E61/1000 -> 0.6 | AE61: =I61*E61/1000 -> 0 | AF61: =ROUND(S61+T61+U61+V61-W61,2) -> 0 | AG61: =ROUND(X61-W61-Y61,2) -> 0
A62: Tega | B62: 2023-24 | C62: April | D62: RM-22-01974AN00-T1 | E62: 35.75 | F62: 8 | G62: 0.29 | H62: 16 | I62: 1 | J62: 70.98 | K62: 149.82 | L62: 1.86 | M62: 12.26 | N62: 3.9 | O62: 0.45 | P62: 1.5 | R62: 1.1 | S62: 170.9 | T62: 0.9 | U62: 7.74 | V62: 15.09 | W62: 194.62 | X62: 282.19 | Y62: 87.57 | Z62: -0.53 | AA62: 0.23 | AB62: 0.02 | AC62: 0.53 | AD62: =H62*E62/1000 -> 0.572 | AE62: =I62*E62/1000 -> 0.03575 | AF62: =ROUND(S62+T62+U62+V62-W62,2) -> 0.01 | AG62: =ROUND(X62-W62-Y62,2) -> 0
A63: Tega | B63: 2023-24 | C63: April | D63: RM-22-05785AN00-T1 | E63: 66.3 | F63: 398 | G63: 26.39 | H63: 5 | J63: 72.22 | K63: 149.69 | L63: 1.83 | M63: 11.47 | N63: 3.9 | O63: 0.45 | P63: 1.5 | R63: 1.1 | S63: 169.93 | T63: 0.9 | U63: 7.74 | V63: 14.95 | W63: 193.52 | X63: 282.19 | Y63: 88.67 | Z63: 22.97 | AA63: 0.13 | AB63: 0 | AC63: 0.29 | AD63: =H63*E63/1000 -> 0.3315 | AE63: =I63*E63/1000 -> 0 | AF63: =ROUND(S63+T63+U63+V63-W63,2) -> 0 | AG63: =ROUND(X63-W63-Y63,2) -> 0
A64: Tega | B64: 2023-24 | C64: April | D64: RM-22-05786AN00-T1 | E64: 62 | F64: 42 | G64: 2.6 | H64: 4 | I64: 1 | J64: 71.79 | K64: 149.73 | L64: 1.84 | M64: 11.67 | N64: 3.9 | O64: 0.45 | P64: 1.5 | R64: 1.1 | S64: 170.19 | T64: 0.9 | U64: 7.74 | V64: 14.99 | W64: 193.83 | X64: 282.19 | Y64: 88.36 | Z64: 1.9 | AA64: 0.1 | AB64: 0.03 | AC64: 0.27 | AD64: =H64*E64/1000 -> 0.248 | AE64: =I64*E64/1000 -> 0.062 | AF64: =ROUND(S64+T64+U64+V64-W64,2) -> -0.01 | AG64: =ROUND(X64-W64-Y64,2) -> 0
A65: Tega | B65: 2023-24 | C65: April | D65: RM-22-05788AN00-T1 | E65: 44.15 | F65: 39 | G65: 1.72 | H65: 6 | J65: 67.89 | K65: 150.19 | L65: 1.94 | M65: 11.52 | N65: 3.9 | O65: 0.45 | P65: 1.5 | R65: 1.1 | S65: 170.6 | T65: 0.9 | U65: 7.74 | V65: 15.46 | W65: 194.69 | X65: 282.19 | Y65: 87.5 | Z65: 1.17 | AA65: 0.11 | AB65: 0 | AC65: 0.23 | AD65: =H65*E65/1000 -> 0.2649 | AE65: =I65*E65/1000 -> 0 | AF65: =ROUND(S65+T65+U65+V65-W65,2) -> 0.01 | AG65: =ROUND(X65-W65-Y65,2) -> 0
A66: Tega | B66: 2023-24 | C66: April | D66: RM-22-05735ON00-T1 | E66: 63 | F66: 27 | G66: 1.7 | J66: 66.67 | K66: 150.34 | L66: 1.98 | M66: 12.26 | N66: 3.9 | O66: 0.45 | P66: 1.5 | R66: 1.1 | S66: 171.53 | T66: 0.9 | U66: 7.74 | V66: 15.61 | W66: 195.79 | X66: 282.19 | Y66: 86.4 | Z66: 1.47 | AA66: 0 | AB66: 0 | AC66: 0 | AD66: =H66*E66/1000 -> 0 | AE66: =I66*E66/1000 -> 0 | AF66: =ROUND(S66+T66+U66+V66-W66,2) -> -0.01 | AG66: =ROUND(X66-W66-Y66,2) -> 0
A67: Tega | B67: 2023-24 | C67: April | D67: RM-22-05735ON01-T1 | E67: 47 | F67: 16 | G67: 0.75 | H67: 1 | J67: 68.2 | K67: 150.15 | L67: 1.94 | M67: 11.42 | N67: 3.9 | O67: 0.45 | P67: 1.5 | R67: 1.1 | S67: 170.46 | T67: 0.9 | U67: 7.74 | V67: 15.42 | W67: 194.52 | X67: 282.19 | Y67: 87.67 | Z67: 0.6 | AA67: 0.02 | AB67: 0 | AC67: 0.04 | AD67: =H67*E67/1000 -> 0.047 | AE67: =I67*E67/1000 -> 0 | AF67: =ROUND(S67+T67+U67+V67-W67,2) -> 0 | AG67: =ROUND(X67-W67-Y67,2) -> 0
A68: Tega | B68: 2023-24 | C68: April | D68: RM-22-05946AN00-T1 | E68: 46.8 | F68: 16 | G68: 0.75 | J68: 67.23 | K68: 150.27 | L68: 1.96 | M68: 12.69 | N68: 3.9 | O68: 0.45 | P68: 1.5 | R68: 1.1 | S68: 171.88 | T68: 0.9 | U68: 7.74 | V68: 15.54 | W68: 196.06 | X68: 282.19 | Y68: 86.13 | Z68: 0.64 | AA68: 0 | AB68: 0 | AC68: 0 | AD68: =H68*E68/1000 -> 0 | AE68: =I68*E68/1000 -> 0 | AF68: =ROUND(S68+T68+U68+V68-W68,2) -> 0 | AG68: =ROUND(X68-W68-Y68,2) -> 0
A69: Tega | B69: 2023-24 | C69: April | D69: RM-22-05947AN00-T1 | E69: 46.8 | F69: 52 | G69: 2.43 | J69: 67.23 | K69: 150.27 | L69: 1.96 | M69: 12.69 | N69: 3.9 | O69: 0.45 | P69: 1.5 | R69: 1.1 | S69: 171.88 | T69: 0.9 | U69: 7.74 | V69: 15.54 | W69: 196.06 | X69: 282.19 | Y69: 86.13 | Z69: 2.1 | AA69: 0 | AB69: 0 | AC69: 0 | AD69: =H69*E69/1000 -> 0 | AE69: =I69*E69/1000 -> 0 | AF69: =ROUND(S69+T69+U69+V69-W69,2) -> 0 | AG69: =ROUND(X69-W69-Y69,2) -> 0
A70: Tega | B70: 2023-24 | C70: April | D70: RM-22-06573ON00-T1 | E70: 32.7 | F70: 171 | G70: 5.59 | H70: 8 | J70: 62.55 | K70: 150.9 | L70: 2.11 | M70: 13.49 | N70: 3.9 | O70: 0.45 | P70: 1.5 | R70: 1.1 | S70: 173.45 | T70: 0.9 | U70: 7.74 | V70: 16.19 | W70: 198.27 | X70: 282.19 | Y70: 83.92 | Z70: 4.36 | AA70: 0.11 | AB70: 0 | AC70: 0.22 | AD70: =H70*E70/1000 -> 0.2616 | AE70: =I70*E70/1000 -> 0 | AF70: =ROUND(S70+T70+U70+V70-W70,2) -> 0.01 | AG70: =ROUND(X70-W70-Y70,2) -> 0
A71: Tega | B71: 2023-24 | C71: April | D71: RM-22-07980N00-T1 | E71: 29 | F71: 64 | G71: 1.86 | H71: 1 | J71: 63.01 | K71: 150.83 | L71: 2.09 | M71: 16.62 | N71: 3.9 | O71: 0.45 | P71: 1.5 | R71: 1.1 | S71: 176.5 | T71: 0.9 | U71: 7.74 | V71: 16.12 | W71: 201.26 | X71: 282.19 | Y71: 80.93 | Z71: 1.47 | AA71: 0.01 | AB71: 0 | AC71: 0.02 | AD71: =H71*E71/1000 -> 0.029 | AE71: =I71*E71/1000 -> 0 | AF71: =ROUND(S71+T71+U71+V71-W71,2) -> 0 | AG71: =ROUND(X71-W71-Y71,2) -> 0
A72: Tega | B72: 2023-24 | C72: May | D72: RM-22-05785AN00-T1 | E72: 66 | F72: 30 | G72: 1.98 | H72: 32 | J72: 72.22 | K72: 152.48 | L72: 1.83 | M72: 11.51 | N72: 3.9 | O72: 0.45 | P72: 1.5 | R72: 1.1 | S72: 172.77 | T72: 0.9 | U72: 8.65 | V72: 15.52 | W72: 197.84 | X72: 282.19 | Y72: 84.35 | Z72: -0.95 | AA72: 0.84 | AB72: 0 | AC72: 1.78 | AD72: =H72*E72/1000 -> 2.112 | AE72: =I72*E72/1000 -> 0 | AF72: =ROUND(S72+T72+U72+V72-W72,2) -> 0 | AG72: =ROUND(X72-W72-Y72,2) -> 0
A73: Tega | B73: 2023-24 | C73: May | D73: RM-22-05946AN00-T1 | E73: 46.5 | F73: 88 | G73: 4.09 | J73: 67.23 | K73: 153.08 | L73: 1.96 | M73: 12.76 | N73: 3.9 | O73: 0.45 | P73: 1.5 | R73: 1.1 | S73: 174.75 | T73: 0.9 | U73: 8.65 | V73: 16.13 | W73: 200.43 | X73: 251.83 | Y73: 51.4 | Z73: 2.1 | AA73: 0 | AB73: 0 | AC73: 0 | AD73: =H73*E73/1000 -> 0 | AE73: =I73*E73/1000 -> 0 | AF73: =ROUND(S73+T73+U73+V73-W73,2) -> 0 | AG73: =ROUND(X73-W73-Y73,2) -> 0
A74: Tega | B74: 2023-24 | C74: May | D74: RM-22-05947AN00-T1 | E74: 46.5 | F74: 4 | G74: 0.19 | J74: 67.23 | K74: 153.08 | L74: 1.96 | M74: 12.76 | N74: 3.9 | O74: 0.45 | P74: 1.5 | R74: 1.1 | S74: 174.75 | T74: 0.9 | U74: 8.65 | V74: 16.13 | W74: 200.43 | X74: 251.83 | Y74: 51.4 | Z74: 0.1 | AA74: 0 | AB74: 0 | AC74: 0 | AD74: =H74*E74/1000 -> 0 | AE74: =I74*E74/1000 -> 0 | AF74: =ROUND(S74+T74+U74+V74-W74,2) -> 0 | AG74: =ROUND(X74-W74-Y74,2) -> 0
A75: Tega | B75: 2023-24 | C75: June | D75: RM-22-00593C000-T1 | E75: 34.5 | F75: 132 | G75: 4.55 | J75: 69.03 | K75: 147.22 | L75: 1.91 | M75: 15.64 | N75: 3.9 | O75: 0.54 | P75: 1.5 | R75: 1.1 | S75: 171.82 | T75: 0.9 | U75: 8.65 | V75: 16.4 | W75: 197.77 | X75: 240.4 | Y75: 42.63 | Z75: 1.94 | AA75: 0 | AB75: 0 | AC75: 0 | AD75: =H75*E75/1000 -> 0 | AE75: =I75*E75/1000 -> 0 | AF75: =ROUND(S75+T75+U75+V75-W75,2) -> 0 | AG75: =ROUND(X75-W75-Y75,2) -> 0
A76: Tega | B76: 2023-24 | C76: June | D76: RM-22-00773B000-T1 | E76: 22.8 | F76: 6 | G76: 0.14 | J76: 64.48 | K76: 147.79 | L76: 2.05 | M76: 18.16 | N76: 3.9 | O76: 0.45 | P76: 1.5 | R76: 1.1 | S76: 174.95 | T76: 0.9 | U76: 8.65 | V76: 17.03 | W76: 201.54 | X76: 240.4 | Y76: 38.86 | Z76: 0.05 | AA76: 0 | AB76: 0 | AC76: 0 | AD76: =H76*E76/1000 -> 0 | AE76: =I76*E76/1000 -> 0 | AF76: =ROUND(S76+T76+U76+V76-W76,2) -> -0.01 | AG76: =ROUND(X76-W76-Y76,2) -> 0
A77: Tega | B77: 2023-24 | C77: June | D77: RM-22-00591C000-T1 | E77: 26.17 | F77: 18 | G77: 0.47 | J77: 65.78 | K77: 147.62 | L77: 2.01 | M77: 18.24 | N77: 3.9 | O77: 0.45 | P77: 1.5 | R77: 1.1 | S77: 174.81 | T77: 0.9 | U77: 8.65 | V77: 16.84 | W77: 201.21 | X77: 240.4 | Y77: 39.19 | Z77: 0.18 | AA77: 0 | AB77: 0 | AC77: 0 | AD77: =H77*E77/1000 -> 0 | AE77: =I77*E77/1000 -> 0 | AF77: =ROUND(S77+T77+U77+V77-W77,2) -> -0.01 | AG77: =ROUND(X77-W77-Y77,2) -> 0
A78: Tega | B78: 2023-24 | C78: June | D78: RM-22-01972AN00-T1 | E78: 50.15 | F78: 47 | G78: 2.36 | I78: 1 | J78: 70.44 | K78: 147.06 | L78: 1.87 | M78: 16.43 | N78: 3.9 | O78: 0.45 | P78: 1.5 | R78: 1.1 | S78: 172.32 | T78: 0.9 | U78: 8.65 | V78: 16.23 | W78: 198.09 | X78: 240.4 | Y78: 42.31 | Z78: 0.95 | AA78: 0 | AB78: 0.03 | AC78: 0.02 | AD78: =H78*E78/1000 -> 0 | AE78: =I78*E78/1000 -> 0.05015 | AF78: =ROUND(S78+T78+U78+V78-W78,2) -> 0.01 | AG78: =ROUND(X78-W78-Y78,2) -> 0
A79: Tega | B79: 2023-24 | C79: June | D79: RM-22-01973AN00-T1 | E79: 37.5 | F79: 103 | G79: 3.86 | H79: 12 | J79: 63.73 | K79: 147.89 | L79: 2.07 | M79: 14.34 | N79: 3.9 | O79: 0.45 | P79: 1.5 | R79: 1.1 | S79: 171.25 | T79: 0.9 | U79: 8.65 | V79: 17.15 | W79: 197.95 | X79: 240.4 | Y79: 42.45 | Z79: 1.25 | AA79: 0.2 | AB79: 0 | AC79: 0.19 | AD79: =H79*E79/1000 -> 0.45 | AE79: =I79*E79/1000 -> 0 | AF79: =ROUND(S79+T79+U79+V79-W79,2) -> 0 | AG79: =ROUND(X79-W79-Y79,2) -> 0
A80: Tega | B80: 2023-24 | C80: June | D80: RM-22-00595G000-T1 | E80: 31.66 | F80: 134 | G80: 4.24 | H80: 3 | J80: 61.09 | K80: 148.27 | L80: 2.16 | M80: 18 | N80: 3.9 | O80: 0.45 | P80: 1.5 | R80: 1.1 | S80: 175.38 | T80: 0.9 | U80: 8.65 | V80: 17.57 | W80: 202.5 | X80: 240.53 | Y80: 38.03 | Z80: 1.53 | AA80: 0.05 | AB80: 0 | AC80: 0.04 | AD80: =H80*E80/1000 -> 0.09498 | AE80: =I80*E80/1000 -> 0 | AF80: =ROUND(S80+T80+U80+V80-W80,2) -> 0 | AG80: =ROUND(X80-W80-Y80,2) -> 0
A81: Tega | B81: 2023-24 | C81: June | D81: RM-22-01893AN00-T1 | E81: 21.6 | F81: 30 | G81: 0.65 | J81: 61.98 | K81: 148.14 | L81: 2.13 | M81: 19.49 | N81: 3.9 | O81: 0.45 | P81: 1.5 | R81: 1.1 | S81: 176.71 | T81: 0.9 | U81: 8.65 | V81: 17.42 | W81: 203.68 | X81: 240.4 | Y81: 36.72 | Z81: 0.24 | AA81: 0 | AB81: 0 | AC81: 0 | AD81: =H81*E81/1000 -> 0 | AE81: =I81*E81/1000 -> 0 | AF81: =ROUND(S81+T81+U81+V81-W81,2) -> 0 | AG81: =ROUND(X81-W81-Y81,2) -> 0
A82: Tega | B82: 2023-24 | C82: June | D82: RM-22-03334ON00-T1 | E82: 47.33 | F82: 3 | G82: 0.14 | J82: 67.25 | K82: 147.44 | L82: 1.96 | M82: 15.76 | N82: 3.9 | O82: 0.45 | P82: 1.5 | R82: 1.1 | S82: 172.11 | T82: 0.9 | U82: 8.65 | V82: 16.64 | W82: 198.3 | X82: 240.4 | Y82: 42.1 | Z82: 0.06 | AA82: 0 | AB82: 0 | AC82: 0 | AD82: =H82*E82/1000 -> 0 | AE82: =I82*E82/1000 -> 0 | AF82: =ROUND(S82+T82+U82+V82-W82,2) -> 0 | AG82: =ROUND(X82-W82-Y82,2) -> 0
A83: Tega | B83: 2023-24 | C83: June | D83: RM-22-09303ON00-M2 | E83: 95 | F83: 3 | G83: 0.29 | J83: 73.53 | K83: 66.7 | L83: 1.8 | M83: 17.63 | N83: 3.9 | O83: 0.45 | P83: 1.5 | R83: 1.1 | S83: 93.07 | T83: 0.9 | U83: 8.65 | V83: 15.86 | W83: 118.48 | X83: 155 | Y83: 36.52 | Z83: 0.1 | AA83: 0 | AB83: 0 | AC83: 0 | AD83: =H83*E83/1000 -> 0 | AE83: =I83*E83/1000 -> 0 | AF83: =ROUND(S83+T83+U83+V83-W83,2) -> 0 | AG83: =ROUND(X83-W83-Y83,2) -> 0
A84: Tega | B84: 2023-24 | C84: July | D84: RM-22-00593C000-T1 | E84: 34.5 | F84: 692 | G84: 23.87 | H84: 14 | I84: 1 | J84: 69.03 | K84: 134.91 | L84: 1.91 | M84: 14.04 | N84: 3.9 | O84: 0.54 | P84: 1.5 | R84: 1.1 | S84: 157.9 | T84: 0.9 | U84: 8.65 | V84: 16.4 | W84: 183.86 | X84: 240.4 | Y84: 56.54 | Z84: 12.98 | AA84: 0.21 | AB84: 0.02 | AC84: 0.29 | AD84: =H84*E84/1000 -> 0.483 | AE84: =I84*E84/1000 -> 0.0345 | AF84: =ROUND(S84+T84+U84+V84-W84,2) -> -0.01 | AG84: =ROUND(X84-W84-Y84,2) -> 0
A85: Tega | B85: 2023-24 | C85: July | D85: RM-22-00773B000-T1 | E85: 22.8 | F85: 174 | G85: 3.97 | H85: 2 | J85: 64.48 | K85: 135.43 | L85: 2.05 | M85: 16.22 | N85: 3.9 | O85: 0.54 | P85: 1.5 | R85: 1.1 | S85: 160.74 | T85: 0.9 | U85: 8.65 | V85: 17.03 | W85: 187.32 | X85: 240.4 | Y85: 53.08 | Z85: 2.06 | AA85: 0.02 | AB85: 0 | AC85: 0.02 | AD85: =H85*E85/1000 -> 0.0456 | AE85: =I85*E85/1000 -> 0 | AF85: =ROUND(S85+T85+U85+V85-W85,2) -> 0 | AG85: =ROUND(X85-W85-Y85,2) -> 0
A86: Tega | B86: 2023-24 | C86: July | D86: RM-22-00591C000-T1 | E86: 26.17 | F86: 722 | G86: 18.89 | H86: 24 | I86: 2 | J86: 65.78 | K86: 135.27 | L86: 2.01 | M86: 16.42 | N86: 3.9 | O86: 0.54 | P86: 1.5 | R86: 1.1 | S86: 160.74 | T86: 0.9 | U86: 8.65 | V86: 16.84 | W86: 187.13 | X86: 240.4 | Y86: 53.27 | Z86: 9.38 | AA86: 0.29 | AB86: 0.03 | AC86: 0.36 | AD86: =H86*E86/1000 -> 0.62808 | AE86: =I86*E86/1000 -> 0.05234 | AF86: =ROUND(S86+T86+U86+V86-W86,2) -> 0 | AG86: =ROUND(X86-W86-Y86,2) -> 0
A87: Tega | B87: 2023-24 | C87: July | D87: RM-22-01973AN00-T1 | E87: 37.5 | F87: 56 | G87: 2.1 | H87: 2 | I87: 1 | J87: 63.73 | K87: 135.52 | L87: 2.07 | M87: 12.91 | N87: 3.9 | O87: 0.54 | P87: 1.5 | R87: 1.1 | S87: 157.54 | T87: 0.9 | U87: 8.65 | V87: 17.15 | W87: 184.24 | X87: 240.4 | Y87: 56.16 | Z87: 1.06 | AA87: 0.03 | AB87: 0.02 | AC87: 0.06 | AD87: =H87*E87/1000 -> 0.075 | AE87: =I87*E87/1000 -> 0.0375 | AF87: =ROUND(S87+T87+U87+V87-W87,2) -> 0 | AG87: =ROUND(X87-W87-Y87,2) -> 0
A88: Tega | B88: 2023-24 | C88: July | D88: RM-22-00595G000-T1 | E88: 31.66 | F88: 160 | G88: 5.07 | H88: 4 | I88: 2 | J88: 61.09 | K88: 135.87 | L88: 2.16 | M88: 16.17 | N88: 3.9 | O88: 0.54 | P88: 1.5 | R88: 1.1 | S88: 161.24 | T88: 0.9 | U88: 8.65 | V88: 17.57 | W88: 188.36 | X88: 240.4 | Y88: 52.04 | Z88: 2.44 | AA88: 0.06 | AB88: 0.04 | AC88: 0.1 | AD88: =H88*E88/1000 -> 0.12664 | AE88: =I88*E88/1000 -> 0.06332 | AF88: =ROUND(S88+T88+U88+V88-W88,2) -> 0 | AG88: =ROUND(X88-W88-Y88,2) -> 0
A89: Tega | B89: 2023-24 | C89: July | D89: RM-22-00803A000-T1 | E89: 15.4 | F89: 272 | G89: 4.19 | H89: 1 | J89: 67.5 | K89: 135.08 | L89: 1.96 | M89: 23.36 | N89: 3.9 | O89: 0.54 | P89: 1.5 | R89: 1.1 | S89: 167.43 | T89: 0.9 | U89: 8.65 | V89: 16.61 | W89: 193.58 | X89: 240.4 | Y89: 46.82 | Z89: 1.95 | AA89: 0.01 | AB89: 0 | AC89: 0.01 | AD89: =H89*E89/1000 -> 0.0154 | AE89: =I89*E89/1000 -> 0 | AF89: =ROUND(S89+T89+U89+V89-W89,2) -> 0.01 | AG89: =ROUND(X89-W89-Y89,2) -> 0
A90: Tega | B90: 2023-24 | C90: July | D90: RM-22-00583B000-T1 | E90: 17 | F90: 312 | G90: 5.3 | J90: 62.02 | K90: 135.74 | L90: 2.13 | M90: 20.47 | N90: 3.9 | O90: 0.54 | P90: 1.5 | R90: 1.1 | S90: 165.38 | T90: 0.9 | U90: 8.65 | V90: 17.41 | W90: 192.34 | X90: 240.4 | Y90: 48.06 | Z90: 2.55 | AA90: 0 | AB90: 0 | AC90: 0 | AD90: =H90*E90/1000 -> 0 | AE90: =I90*E90/1000 -> 0 | AF90: =ROUND(S90+T90+U90+V90-W90,2) -> 0 | AG90: =ROUND(X90-W90-Y90,2) -> 0
A91: Tega | B91: 2023-24 | C91: July | D91: RM-22-01893AN00-T1 | E91: 21.6 | F91: 25 | G91: 0.54 | H91: 3 | J91: 61.98 | K91: 135.75 | L91: 2.13 | M91: 17.39 | N91: 3.9 | O91: 0.54 | P91: 1.5 | R91: 1.1 | S91: 162.3 | T91: 0.9 | U91: 8.65 | V91: 17.42 | W91: 189.27 | X91: 240.4 | Y91: 51.13 | Z91: 0.21 | AA91: 0.03 | AB91: 0 | AC91: 0.03 | AD91: =H91*E91/1000 -> 0.0648 | AE91: =I91*E91/1000 -> 0 | AF91: =ROUND(S91+T91+U91+V91-W91,2) -> 0 | AG91: =ROUND(X91-W91-Y91,2) -> 0
A92: Tega | B92: 2023-24 | C92: July | D92: RM-22-03334ON00-T1 | E92: 47.33 | F92: 24 | G92: 1.14 | J92: 67.25 | K92: 135.1 | L92: 1.96 | M92: 14.11 | N92: 3.9 | O92: 0.54 | P92: 1.5 | R92: 1.1 | S92: 158.22 | T92: 0.9 | U92: 8.65 | V92: 16.64 | W92: 184.41 | X92: 240.4 | Y92: 55.99 | Z92: 0.64 | AA92: 0 | AB92: 0 | AC92: 0 | AD92: =H92*E92/1000 -> 0 | AE92: =I92*E92/1000 -> 0 | AF92: =ROUND(S92+T92+U92+V92-W92,2) -> 0 | AG92: =ROUND(X92-W92-Y92,2) -> 0
A93: Tega | B93: 2023-24 | C93: July | D93: RM-22-00631E000-T1 | E93: 32.34 | F93: 60 | G93: 1.94 | H93: 1 | J93: 69.3 | K93: 134.88 | L93: 1.9 | M93: 16.76 | N93: 3.9 | O93: 0.54 | P93: 1.5 | R93: 1.1 | S93: 160.58 | T93: 0.9 | U93: 8.65 | V93: 16.37 | W93: 186.5 | X93: 240.4 | Y93: 53.9 | Z93: 1.01 | AA93: 0.01 | AB93: 0 | AC93: 0.02 | AD93: =H93*E93/1000 -> 0.03234 | AE93: =I93*E93/1000 -> 0 | AF93: =ROUND(S93+T93+U93+V93-W93,2) -> 0 | AG93: =ROUND(X93-W93-Y93,2) -> 0
A94: Tega | B94: 2023-24 | C94: July | D94: RM-22-00488E000-T1 | E94: 30.35 | F94: 96 | G94: 2.91 | J94: 68 | K94: 135.02 | L94: 1.94 | M94: 16.58 | N94: 3.9 | O94: 0.54 | P94: 1.5 | R94: 1.1 | S94: 160.59 | T94: 0.9 | U94: 8.65 | V94: 16.54 | W94: 186.68 | X94: 240.4 | Y94: 53.72 | Z94: 1.57 | AA94: 0 | AB94: 0 | AC94: 0 | AD94: =H94*E94/1000 -> 0 | AE94: =I94*E94/1000 -> 0 | AF94: =ROUND(S94+T94+U94+V94-W94,2) -> 0 | AG94: =ROUND(X94-W94-Y94,2) -> 0
A95: Tega | B95: 2023-24 | C95: August | D95: RM-22-00593C000-T1 | E95: 34.5 | F95: 594 | G95: 20.49 | H95: 54 | I95: 4 | J95: 69.03 | K95: 142.03 | L95: 2.44 | M95: 14.67 | N95: 3.9 | O95: 0.54 | P95: 1.5 | R95: 1.1 | S95: 166.18 | T95: 0.9 | U95: 8.65 | V95: 16.4 | W95: 192.14 | X95: 237.93 | Y95: 45.79 | Z95: 7.57 | AA95: 0.82 | AB95: 0.08 | AC95: 0.92 | AD95: =H95*E95/1000 -> 1.863 | AE95: =I95*E95/1000 -> 0.138 | AF95: =ROUND(S95+T95+U95+V95-W95,2) -> -0.01 | AG95: =ROUND(X95-W95-Y95,2) -> 0
A96: Tega | B96: 2023-24 | C96: August | D96: RM-22-00773B000-T1 | E96: 22.8 | F96: 6 | G96: 0.14 | H96: 5 | J96: 64.48 | K96: 142.58 | L96: 2.61 | M96: 16.99 | N96: 3.9 | O96: 0.54 | P96: 1.5 | R96: 1.1 | S96: 169.22 | T96: 0.9 | U96: 8.65 | V96: 17.03 | W96: 195.8 | X96: 237.93 | Y96: 42.13 | Z96: -0.04 | AA96: 0.05 | AB96: 0 | AC96: 0.05 | AD96: =H96*E96/1000 -> 0.114 | AE96: =I96*E96/1000 -> 0 | AF96: =ROUND(S96+T96+U96+V96-W96,2) -> 0 | AG96: =ROUND(X96-W96-Y96,2) -> 0
A97: Tega | B97: 2023-24 | C97: August | D97: RM-22-00591C000-T1 | E97: 26.17 | F97: 306 | G97: 8.01 | H97: 20 | J97: 65.78 | K97: 142.41 | L97: 2.56 | M97: 17.14 | N97: 3.9 | O97: 0.54 | P97: 1.5 | R97: 1.1 | S97: 169.15 | T97: 0.9 | U97: 8.65 | V97: 16.84 | W97: 195.54 | X97: 237.93 | Y97: 42.39 | Z97: 2.92 | AA97: 0.25 | AB97: 0 | AC97: 0.22 | AD97: =H97*E97/1000 -> 0.5234 | AE97: =I97*E97/1000 -> 0 | AF97: =ROUND(S97+T97+U97+V97-W97,2) -> 0 | AG97: =ROUND(X97-W97-Y97,2) -> 0
A98: Tega | B98: 2023-24 | C98: August | D98: RM-22-01972AN00-T1 | E98: 50.15 | F98: 12 | G98: 0.6 | H98: 1 | I98: 1 | J98: 70.44 | K98: 141.87 | L98: 2.39 | M98: 15.37 | N98: 3.9 | O98: 0.54 | P98: 1.5 | R98: 1.1 | S98: 166.67 | T98: 0.9 | U98: 8.65 | V98: 16.23 | W98: 192.45 | X98: 237.93 | Y98: 45.48 | Z98: 0.18 | AA98: 0.02 | AB98: 0.03 | AC98: 0.05 | AD98: =H98*E98/1000 -> 0.05015 | AE98: =I98*E98/1000 -> 0.05015 | AF98: =ROUND(S98+T98+U98+V98-W98,2) -> 0 | AG98: =ROUND(X98-W98-Y98,2) -> 0
A99: Tega | B99: 2023-24 | C99: August | D99: RM-22-01973AN00-T1 | E99: 37.5 | F99: 56 | G99: 2.1 | H99: 10 | I99: 1 | J99: 63.73 | K99: 142.68 | L99: 2.64 | M99: 13.47 | N99: 3.9 | O99: 0.54 | P99: 1.5 | R99: 1.1 | S99: 165.83 | T99: 0.9 | U99: 8.65 | V99: 17.15 | W99: 192.53 | X99: 237.93 | Y99: 45.4 | Z99: 0.58 | AA99: 0.17 | AB99: 0.02 | AC99: 0.19 | AD99: =H99*E99/1000 -> 0.375 | AE99: =I99*E99/1000 -> 0.0375 | AF99: =ROUND(S99+T99+U99+V99-W99,2) -> 0 | AG99: =ROUND(X99-W99-Y99,2) -> 0
A100: Tega | B100: 2023-24 | C100: August | D100: RM-22-00803A000-T1 | E100: 15.4 | F100: 280 | G100: 4.31 | H100: 22 | I100: 1 | J100: 67.5 | K100: 142.21 | L100: 2.49 | M100: 24.39 | N100: 3.9 | O100: 0.54 | P100: 1.5 | R100: 1.1 | S100: 176.13 | T100: 0.9 | U100: 8.65 | V100: 16.61 | W100: 202.28 | X100: 237.93 | Y100: 35.65 | Z100: 1.22 | AA100: 0.18 | AB100: 0.01 | AC100: 0.13 | AD100: =H100*E100/1000 -> 0.3388 | AE100: =I100*E100/1000 -> 0.0154 | AF100: =ROUND(S100+T100+U100+V100-W100,2) -> 0.01 | AG100: =ROUND(X100-W100-Y100,2) -> 0
A101: Tega | B101: 2023-24 | C101: August | D101: RM-22-00583B000-T1 | E101: 17 | F101: 328 | G101: 5.58 | H101: 20 | I101: 1 | J101: 62.02 | K101: 142.91 | L101: 2.71 | M101: 21.47 | N101: 3.9 | O101: 0.54 | P101: 1.5 | R101: 1.1 | S101: 174.13 | T101: 0.9 | U101: 8.65 | V101: 17.41 | W101: 201.1 | X101: 237.93 | Y101: 36.83 | Z101: 1.73 | AA101: 0.18 | AB101: 0.01 | AC101: 0.13 | AD101: =H101*E101/1000 -> 0.34 | AE101: =I101*E101/1000 -> 0.017 | AF101: =ROUND(S101+T101+U101+V101-W101,2) -> -0.01 | AG101: =ROUND(X101-W101-Y101,2) -> 0
...

Sheet IN_HO
A1: HO ACCOUNTS INPUTS - ledger items, adjustments and MT statistics (Rs. Lacs)
A2: Financial year label (must match IN_Contrib): | C2: 2026-27
A4: Ref | B4: Item | C4: Apr'26 | D4: May'26 | E4: Jun'26 | F4: Jul'26 | G4: Aug'26 | H4: Sep'26 | I4: Oct'26 | J4: Nov'26 | K4: Dec'26 | L4: Jan'27 | M4: Feb'27 | N4: Mar'27 | O4: Note
B5: GST rate on domestic sales | C5: 0.18 | D5: 0.18 | E5: 0.18 | F5: 0.18 | G5: 0.18 | H5: 0.18 | I5: =C5 -> 0.18 | J5: =C5 -> 0.18 | K5: =C5 -> 0.18 | L5: =C5 -> 0.18 | M5: =C5 -> 0.18 | N5: =C5 -> 0.18 | O5: 18% in all months of Sept'26 MIS
B7: HO ADJUSTMENTS (back-solved from published Sept'26 MIS - HO to document nature)
B8: Material consumed - adjustment (+ increases cost) | C8: -1.8 | D8: 0 | E8: 2.24 | F8: 3 | G8: 2 | H8: 3 | O8: Published less factory PL row 1
B9: (Inc)/Dec in stock - adjustment | C9: 0 | D9: 0 | E9: 0 | F9: 0 | G9: 3 | H9: 0 | O9: Published less (-PL row 6). Aug'26 3.00 to be explained
B10: Power variable - adjustment | C10: 0.14 | D10: 0 | E10: 0.01 | F10: -0.01 | G10: 0 | H10: 0 | O10: Rounding / unallocated
B11: Job-work charges - adjustment (e.g. QC job work not in PL feed) | C11: 0 | D11: 0.13 | E11: 2.07 | F11: 2 | G11: 2.01 | H11: 2 | O11: ~2.00 each month Jun-Sep; Rahaman QC row is blank in factory feed
B12: Selling expenses carved out of Other factory expenses | C12: 0 | D12: 0 | E12: 0 | F12: 0 | G12: 0 | H12: 3.22 | O12: Sep'26 3.22 = transport on sale return. Jun'26 0.29 NOT carved out in published MIS
B13: Pattern income shown under Storage income (reclass) | C13: 0 | D13: 0 | E13: 0 | F13: 0.06 | G13: 0 | H13: 0 | O13: Jul'26 0.06
B15: HO LEDGER ITEMS (not in factory feed)
B16: Administrative Expenses | C16: 3.21 | D16: 4.13 | E16: 4.5 | F16: 7.52 | G16: 6.07 | H16: 7.13
B17: Salary & Wages | C17: 15.91 | D17: 12.37 | E17: 14.85 | F17: 16.85 | G17: 15.87 | H17: 16.61
B18: Deferred Revenue Expenses | C18: 0 | D18: 0 | E18: 0 | F18: 0 | G18: 0 | H18: 0
B19: Other Non-Operating Expenses | C19: 0 | D19: 0 | E19: 0 | F19: 0 | G19: 0 | H19: 0
B20: Depreciation | C20: 0 | D20: 0 | E20: 0 | F20: 0 | G20: 0 | H20: 0
B21: Interest | C21: 0 | D21: 0 | E21: 0 | F21: 0 | G21: 0 | H21: 0
B23: STATISTICS (MT) AND COLLECTIONS
B24: Production (MT) | C24: 33.56 | D24: 84.62 | E24: 83 | F24: 84.62 | G24: 77.44 | H24: 105.48 | O24: Jul'26 identical to May'26 - verify
B25: Despatch (MT) | C25: 50.44 | D25: 36.67 | E25: 106.07 | F25: 36.67 | G25: 94.58 | H25: 89.34 | O25: Jul'26 identical to May'26 - verify
B26: In-house Rejections (MT) | C26: 5.73 | D26: 6.9 | E26: 9.39 | F26: 6.9 | G26: 9.16 | H26: 9.04 | O26: Jul'26 identical to May'26 - verify
B27: Collections (including GST) | C27: 149.75 | D27: 126.8 | E27: 238.95 | F27: 269.64 | G27: 302.91 | H27: 284.24

Sheet CONTRIB_SUM
A1: CONTRIBUTION SUMMARY (formula-driven from IN_Contrib)
A2: Financial year: | B2: =IN_HO!C2 -> 2026-27
A4: Customer-wise contribution (Pouring & rejn.) Rs. Lacs | B4: Apr | C4: May | D4: Jun | E4: Jul | F4: Aug | G4: Sep | H4: Oct | I4: Nov | J4: Dec | K4: Jan | L4: Feb | M4: Mar | N4: Total
A5: Tega | B5: =SUMIFS(IN_Contrib!$Z$4:$Z$2000,IN_Contrib!$A$4:$A$2000,$A5,IN_Contrib!$B$4:$B$2000,$B$2,IN_Contrib!$C$4:$C$2000,"April") -> 8.58 | C5: =SUMIFS(IN_Contrib!$Z$4:$Z$2000,IN_Contrib!$A$4:$A$2000,$A5,IN_Contrib!$B$4:$B$2000,$B$2,IN_Contrib!$C$4:$C$2000,"May") -> 45.44 | D5: =SUMIFS(IN_Contrib!$Z$4:$Z$2000,IN_Contrib!$A$4:$A$2000,$A5,IN_Contrib!$B$4:$B$2000,$B$2,IN_Contrib!$C$4:$C$2000,"June") -> 55.89 | E5: =SUMIFS(IN_Contrib!$Z$4:$Z$2000,IN_Contrib!$A$4:$A$2000,$A5,IN_Contrib!$B$4:$B$2000,$B$2,IN_Contrib!$C$4:$C$2000,"July") -> 33.82 | F5: =SUMIFS(IN_Contrib!$Z$4:$Z$2000,IN_Contrib!$A$4:$A$2000,$A5,IN_Contrib!$B$4:$B$2000,$B$2,IN_Contrib!$C$4:$C$2000,"August") -> 14.57 | G5: =SUMIFS(IN_Contrib!$Z$4:$Z$2000,IN_Contrib!$A$4:$A$2000,$A5,IN_Contrib!$B$4:$B$2000,$B$2,IN_Contrib!$C$4:$C$2000,"September") -> 49.48 | H5: =SUMIFS(IN_Contrib!$Z$4:$Z$2000,IN_Contrib!$A$4:$A$2000,$A5,IN_Contrib!$B$4:$B$2000,$B$2,IN_Contrib!$C$4:$C$2000,"October") -> 0 | I5: =SUMIFS(IN_Contrib!$Z$4:$Z$2000,IN_Contrib!$A$4:$A$2000,$A5,IN_Contrib!$B$4:$B$2000,$B$2,IN_Contrib!$C$4:$C$2000,"November") -> 0 | J5: =SUMIFS(IN_Contrib!$Z$4:$Z$2000,IN_Contrib!$A$4:$A$2000,$A5,IN_Contrib!$B$4:$B$2000,$B$2,IN_Contrib!$C$4:$C$2000,"December") -> 0 | K5: =SUMIFS(IN_Contrib!$Z$4:$Z$2000,IN_Contrib!$A$4:$A$2000,$A5,IN_Contrib!$B$4:$B$2000,$B$2,IN_Contrib!$C$4:$C$2000,"January") -> 0 | L5: =SUMIFS(IN_Contrib!$Z$4:$Z$2000,IN_Contrib!$A$4:$A$2000,$A5,IN_Contrib!$B$4:$B$2000,$B$2,IN_Contrib!$C$4:$C$2000,"February") -> 0 | M5: =SUMIFS(IN_Contrib!$Z$4:$Z$2000,IN_Contrib!$A$4:$A$2000,$A5,IN_Contrib!$B$4:$B$2000,$B$2,IN_Contrib!$C$4:$C$2000,"March") -> 0 | N5: =SUM(B5:M5) -> 207.78
A6: Thejo Engineering | B6: =SUMIFS(IN_Contrib!$Z$4:$Z$2000,IN_Contrib!$A$4:$A$2000,$A6,IN_Contrib!$B$4:$B$2000,$B$2,IN_Contrib!$C$4:$C$2000,"April") -> 12.38 | C6: =SUMIFS(IN_Contrib!$Z$4:$Z$2000,IN_Contrib!$A$4:$A$2000,$A6,IN_Contrib!$B$4:$B$2000,$B$2,IN_Contrib!$C$4:$C$2000,"May") -> 1.39 | D6: =SUMIFS(IN_Contrib!$Z$4:$Z$2000,IN_Contrib!$A$4:$A$2000,$A6,IN_Contrib!$B$4:$B$2000,$B$2,IN_Contrib!$C$4:$C$2000,"June") -> 0 | E6: =SUMIFS(IN_Contrib!$Z$4:$Z$2000,IN_Contrib!$A$4:$A$2000,$A6,IN_Contrib!$B$4:$B$2000,$B$2,IN_Contrib!$C$4:$C$2000,"July") -> 23.23 | F6: =SUMIFS(IN_Contrib!$Z$4:$Z$2000,IN_Contrib!$A$4:$A$2000,$A6,IN_Contrib!$B$4:$B$2000,$B$2,IN_Contrib!$C$4:$C$2000,"August") -> 33.41 | G6: =SUMIFS(IN_Contrib!$Z$4:$Z$2000,IN_Contrib!$A$4:$A$2000,$A6,IN_Contrib!$B$4:$B$2000,$B$2,IN_Contrib!$C$4:$C$2000,"September") -> 22.54 | H6: =SUMIFS(IN_Contrib!$Z$4:$Z$2000,IN_Contrib!$A$4:$A$2000,$A6,IN_Contrib!$B$4:$B$2000,$B$2,IN_Contrib!$C$4:$C$2000,"October") -> 0 | I6: =SUMIFS(IN_Contrib!$Z$4:$Z$2000,IN_Contrib!$A$4:$A$2000,$A6,IN_Contrib!$B$4:$B$2000,$B$2,IN_Contrib!$C$4:$C$2000,"November") -> 0 | J6: =SUMIFS(IN_Contrib!$Z$4:$Z$2000,IN_Contrib!$A$4:$A$2000,$A6,IN_Contrib!$B$4:$B$2000,$B$2,IN_Contrib!$C$4:$C$2000,"December") -> 0 | K6: =SUMIFS(IN_Contrib!$Z$4:$Z$2000,IN_Contrib!$A$4:$A$2000,$A6,IN_Contrib!$B$4:$B$2000,$B$2,IN_Contrib!$C$4:$C$2000,"January") -> 0 | L6: =SUMIFS(IN_Contrib!$Z$4:$Z$2000,IN_Contrib!$A$4:$A$2000,$A6,IN_Contrib!$B$4:$B$2000,$B$2,IN_Contrib!$C$4:$C$2000,"February") -> 0 | M6: =SUMIFS(IN_Contrib!$Z$4:$Z$2000,IN_Contrib!$A$4:$A$2000,$A6,IN_Contrib!$B$4:$B$2000,$B$2,IN_Contrib!$C$4:$C$2000,"March") -> 0 | N6: =SUM(B6:M6) -> 92.95
A7: ESCORT(Main Body) Rev.3 | B7: =SUMIFS(IN_Contrib!$Z$4:$Z$2000,IN_Contrib!$A$4:$A$2000,$A7,IN_Contrib!$B$4:$B$2000,$B$2,IN_Contrib!$C$4:$C$2000,"April") -> 0 | C7: =SUMIFS(IN_Contrib!$Z$4:$Z$2000,IN_Contrib!$A$4:$A$2000,$A7,IN_Contrib!$B$4:$B$2000,$B$2,IN_Contrib!$C$4:$C$2000,"May") -> 0 | D7: =SUMIFS(IN_Contrib!$Z$4:$Z$2000,IN_Contrib!$A$4:$A$2000,$A7,IN_Contrib!$B$4:$B$2000,$B$2,IN_Contrib!$C$4:$C$2000,"June") -> 0 | E7: =SUMIFS(IN_Contrib!$Z$4:$Z$2000,IN_Contrib!$A$4:$A$2000,$A7,IN_Contrib!$B$4:$B$2000,$B$2,IN_Contrib!$C$4:$C$2000,"July") -> 0 | F7: =SUMIFS(IN_Contrib!$Z$4:$Z$2000,IN_Contrib!$A$4:$A$2000,$A7,IN_Contrib!$B$4:$B$2000,$B$2,IN_Contrib!$C$4:$C$2000,"August") -> 0 | G7: =SUMIFS(IN_Contrib!$Z$4:$Z$2000,IN_Contrib!$A$4:$A$2000,$A7,IN_Contrib!$B$4:$B$2000,$B$2,IN_Contrib!$C$4:$C$2000,"September") -> 0 | H7: =SUMIFS(IN_Contrib!$Z$4:$Z$2000,IN_Contrib!$A$4:$A$2000,$A7,IN_Contrib!$B$4:$B$2000,$B$2,IN_Contrib!$C$4:$C$2000,"October") -> 0 | I7: =SUMIFS(IN_Contrib!$Z$4:$Z$2000,IN_Contrib!$A$4:$A$2000,$A7,IN_Contrib!$B$4:$B$2000,$B$2,IN_Contrib!$C$4:$C$2000,"November") -> 0 | J7: =SUMIFS(IN_Contrib!$Z$4:$Z$2000,IN_Contrib!$A$4:$A$2000,$A7,IN_Contrib!$B$4:$B$2000,$B$2,IN_Contrib!$C$4:$C$2000,"December") -> 0 | K7: =SUMIFS(IN_Contrib!$Z$4:$Z$2000,IN_Contrib!$A$4:$A$2000,$A7,IN_Contrib!$B$4:$B$2000,$B$2,IN_Contrib!$C$4:$C$2000,"January") -> 0 | L7: =SUMIFS(IN_Contrib!$Z$4:$Z$2000,IN_Contrib!$A$4:$A$2000,$A7,IN_Contrib!$B$4:$B$2000,$B$2,IN_Contrib!$C$4:$C$2000,"February") -> 0 | M7: =SUMIFS(IN_Contrib!$Z$4:$Z$2000,IN_Contrib!$A$4:$A$2000,$A7,IN_Contrib!$B$4:$B$2000,$B$2,IN_Contrib!$C$4:$C$2000,"March") -> 0 | N7: =SUM(B7:M7) -> 0
A8: ESCORT (Knuckle) | B8: =SUMIFS(IN_Contrib!$Z$4:$Z$2000,IN_Contrib!$A$4:$A$2000,$A8,IN_Contrib!$B$4:$B$2000,$B$2,IN_Contrib!$C$4:$C$2000,"April") -> 0 | C8: =SUMIFS(IN_Contrib!$Z$4:$Z$2000,IN_Contrib!$A$4:$A$2000,$A8,IN_Contrib!$B$4:$B$2000,$B$2,IN_Contrib!$C$4:$C$2000,"May") -> 0 | D8: =SUMIFS(IN_Contrib!$Z$4:$Z$2000,IN_Contrib!$A$4:$A$2000,$A8,IN_Contrib!$B$4:$B$2000,$B$2,IN_Contrib!$C$4:$C$2000,"June") -> 0 | E8: =SUMIFS(IN_Contrib!$Z$4:$Z$2000,IN_Contrib!$A$4:$A$2000,$A8,IN_Contrib!$B$4:$B$2000,$B$2,IN_Contrib!$C$4:$C$2000,"July") -> 0 | F8: =SUMIFS(IN_Contrib!$Z$4:$Z$2000,IN_Contrib!$A$4:$A$2000,$A8,IN_Contrib!$B$4:$B$2000,$B$2,IN_Contrib!$C$4:$C$2000,"August") -> 0 | G8: =SUMIFS(IN_Contrib!$Z$4:$Z$2000,IN_Contrib!$A$4:$A$2000,$A8,IN_Contrib!$B$4:$B$2000,$B$2,IN_Contrib!$C$4:$C$2000,"September") -> 0 | H8: =SUMIFS(IN_Contrib!$Z$4:$Z$2000,IN_Contrib!$A$4:$A$2000,$A8,IN_Contrib!$B$4:$B$2000,$B$2,IN_Contrib!$C$4:$C$2000,"October") -> 0 | I8: =SUMIFS(IN_Contrib!$Z$4:$Z$2000,IN_Contrib!$A$4:$A$2000,$A8,IN_Contrib!$B$4:$B$2000,$B$2,IN_Contrib!$C$4:$C$2000,"November") -> 0 | J8: =SUMIFS(IN_Contrib!$Z$4:$Z$2000,IN_Contrib!$A$4:$A$2000,$A8,IN_Contrib!$B$4:$B$2000,$B$2,IN_Contrib!$C$4:$C$2000,"December") -> 0 | K8: =SUMIFS(IN_Contrib!$Z$4:$Z$2000,IN_Contrib!$A$4:$A$2000,$A8,IN_Contrib!$B$4:$B$2000,$B$2,IN_Contrib!$C$4:$C$2000,"January") -> 0 | L8: =SUMIFS(IN_Contrib!$Z$4:$Z$2000,IN_Contrib!$A$4:$A$2000,$A8,IN_Contrib!$B$4:$B$2000,$B$2,IN_Contrib!$C$4:$C$2000,"February") -> 0 | M8: =SUMIFS(IN_Contrib!$Z$4:$Z$2000,IN_Contrib!$A$4:$A$2000,$A8,IN_Contrib!$B$4:$B$2000,$B$2,IN_Contrib!$C$4:$C$2000,"March") -> 0 | N8: =SUM(B8:M8) -> 0
A9: ESCORT (Lock Casting) | B9: =SUMIFS(IN_Contrib!$Z$4:$Z$2000,IN_Contrib!$A$4:$A$2000,$A9,IN_Contrib!$B$4:$B$2000,$B$2,IN_Contrib!$C$4:$C$2000,"April") -> 0 | C9: =SUMIFS(IN_Contrib!$Z$4:$Z$2000,IN_Contrib!$A$4:$A$2000,$A9,IN_Contrib!$B$4:$B$2000,$B$2,IN_Contrib!$C$4:$C$2000,"May") -> 0 | D9: =SUMIFS(IN_Contrib!$Z$4:$Z$2000,IN_Contrib!$A$4:$A$2000,$A9,IN_Contrib!$B$4:$B$2000,$B$2,IN_Contrib!$C$4:$C$2000,"June") -> 0 | E9: =SUMIFS(IN_Contrib!$Z$4:$Z$2000,IN_Contrib!$A$4:$A$2000,$A9,IN_Contrib!$B$4:$B$2000,$B$2,IN_Contrib!$C$4:$C$2000,"July") -> 0 | F9: =SUMIFS(IN_Contrib!$Z$4:$Z$2000,IN_Contrib!$A$4:$A$2000,$A9,IN_Contrib!$B$4:$B$2000,$B$2,IN_Contrib!$C$4:$C$2000,"August") -> 0 | G9: =SUMIFS(IN_Contrib!$Z$4:$Z$2000,IN_Contrib!$A$4:$A$2000,$A9,IN_Contrib!$B$4:$B$2000,$B$2,IN_Contrib!$C$4:$C$2000,"September") -> 0 | H9: =SUMIFS(IN_Contrib!$Z$4:$Z$2000,IN_Contrib!$A$4:$A$2000,$A9,IN_Contrib!$B$4:$B$2000,$B$2,IN_Contrib!$C$4:$C$2000,"October") -> 0 | I9: =SUMIFS(IN_Contrib!$Z$4:$Z$2000,IN_Contrib!$A$4:$A$2000,$A9,IN_Contrib!$B$4:$B$2000,$B$2,IN_Contrib!$C$4:$C$2000,"November") -> 0 | J9: =SUMIFS(IN_Contrib!$Z$4:$Z$2000,IN_Contrib!$A$4:$A$2000,$A9,IN_Contrib!$B$4:$B$2000,$B$2,IN_Contrib!$C$4:$C$2000,"December") -> 0 | K9: =SUMIFS(IN_Contrib!$Z$4:$Z$2000,IN_Contrib!$A$4:$A$2000,$A9,IN_Contrib!$B$4:$B$2000,$B$2,IN_Contrib!$C$4:$C$2000,"January") -> 0 | L9: =SUMIFS(IN_Contrib!$Z$4:$Z$2000,IN_Contrib!$A$4:$A$2000,$A9,IN_Contrib!$B$4:$B$2000,$B$2,IN_Contrib!$C$4:$C$2000,"February") -> 0 | M9: =SUMIFS(IN_Contrib!$Z$4:$Z$2000,IN_Contrib!$A$4:$A$2000,$A9,IN_Contrib!$B$4:$B$2000,$B$2,IN_Contrib!$C$4:$C$2000,"March") -> 0 | N9: =SUM(B9:M9) -> 0
A10: ESCORT (Autometic Coupler) | B10: =SUMIFS(IN_Contrib!$Z$4:$Z$2000,IN_Contrib!$A$4:$A$2000,$A10,IN_Contrib!$B$4:$B$2000,$B$2,IN_Contrib!$C$4:$C$2000,"April") -> 0 | C10: =SUMIFS(IN_Contrib!$Z$4:$Z$2000,IN_Contrib!$A$4:$A$2000,$A10,IN_Contrib!$B$4:$B$2000,$B$2,IN_Contrib!$C$4:$C$2000,"May") -> 0 | D10: =SUMIFS(IN_Contrib!$Z$4:$Z$2000,IN_Contrib!$A$4:$A$2000,$A10,IN_Contrib!$B$4:$B$2000,$B$2,IN_Contrib!$C$4:$C$2000,"June") -> 0 | E10: =SUMIFS(IN_Contrib!$Z$4:$Z$2000,IN_Contrib!$A$4:$A$2000,$A10,IN_Contrib!$B$4:$B$2000,$B$2,IN_Contrib!$C$4:$C$2000,"July") -> 0 | F10: =SUMIFS(IN_Contrib!$Z$4:$Z$2000,IN_Contrib!$A$4:$A$2000,$A10,IN_Contrib!$B$4:$B$2000,$B$2,IN_Contrib!$C$4:$C$2000,"August") -> 0 | G10: =SUMIFS(IN_Contrib!$Z$4:$Z$2000,IN_Contrib!$A$4:$A$2000,$A10,IN_Contrib!$B$4:$B$2000,$B$2,IN_Contrib!$C$4:$C$2000,"September") -> 0 | H10: =SUMIFS(IN_Contrib!$Z$4:$Z$2000,IN_Contrib!$A$4:$A$2000,$A10,IN_Contrib!$B$4:$B$2000,$B$2,IN_Contrib!$C$4:$C$2000,"October") -> 0 | I10: =SUMIFS(IN_Contrib!$Z$4:$Z$2000,IN_Contrib!$A$4:$A$2000,$A10,IN_Contrib!$B$4:$B$2000,$B$2,IN_Contrib!$C$4:$C$2000,"November") -> 0 | J10: =SUMIFS(IN_Contrib!$Z$4:$Z$2000,IN_Contrib!$A$4:$A$2000,$A10,IN_Contrib!$B$4:$B$2000,$B$2,IN_Contrib!$C$4:$C$2000,"December") -> 0 | K10: =SUMIFS(IN_Contrib!$Z$4:$Z$2000,IN_Contrib!$A$4:$A$2000,$A10,IN_Contrib!$B$4:$B$2000,$B$2,IN_Contrib!$C$4:$C$2000,"January") -> 0 | L10: =SUMIFS(IN_Contrib!$Z$4:$Z$2000,IN_Contrib!$A$4:$A$2000,$A10,IN_Contrib!$B$4:$B$2000,$B$2,IN_Contrib!$C$4:$C$2000,"February") -> 0 | M10: =SUMIFS(IN_Contrib!$Z$4:$Z$2000,IN_Contrib!$A$4:$A$2000,$A10,IN_Contrib!$B$4:$B$2000,$B$2,IN_Contrib!$C$4:$C$2000,"March") -> 0 | N10: =SUM(B10:M10) -> 0
A11: ESCORT (Fork Eye) | B11: =SUMIFS(IN_Contrib!$Z$4:$Z$2000,IN_Contrib!$A$4:$A$2000,$A11,IN_Contrib!$B$4:$B$2000,$B$2,IN_Contrib!$C$4:$C$2000,"April") -> 0 | C11: =SUMIFS(IN_Contrib!$Z$4:$Z$2000,IN_Contrib!$A$4:$A$2000,$A11,IN_Contrib!$B$4:$B$2000,$B$2,IN_Contrib!$C$4:$C$2000,"May") -> 0 | D11: =SUMIFS(IN_Contrib!$Z$4:$Z$2000,IN_Contrib!$A$4:$A$2000,$A11,IN_Contrib!$B$4:$B$2000,$B$2,IN_Contrib!$C$4:$C$2000,"June") -> 0 | E11: =SUMIFS(IN_Contrib!$Z$4:$Z$2000,IN_Contrib!$A$4:$A$2000,$A11,IN_Contrib!$B$4:$B$2000,$B$2,IN_Contrib!$C$4:$C$2000,"July") -> 0 | F11: =SUMIFS(IN_Contrib!$Z$4:$Z$2000,IN_Contrib!$A$4:$A$2000,$A11,IN_Contrib!$B$4:$B$2000,$B$2,IN_Contrib!$C$4:$C$2000,"August") -> 0 | G11: =SUMIFS(IN_Contrib!$Z$4:$Z$2000,IN_Contrib!$A$4:$A$2000,$A11,IN_Contrib!$B$4:$B$2000,$B$2,IN_Contrib!$C$4:$C$2000,"September") -> 0 | H11: =SUMIFS(IN_Contrib!$Z$4:$Z$2000,IN_Contrib!$A$4:$A$2000,$A11,IN_Contrib!$B$4:$B$2000,$B$2,IN_Contrib!$C$4:$C$2000,"October") -> 0 | I11: =SUMIFS(IN_Contrib!$Z$4:$Z$2000,IN_Contrib!$A$4:$A$2000,$A11,IN_Contrib!$B$4:$B$2000,$B$2,IN_Contrib!$C$4:$C$2000,"November") -> 0 | J11: =SUMIFS(IN_Contrib!$Z$4:$Z$2000,IN_Contrib!$A$4:$A$2000,$A11,IN_Contrib!$B$4:$B$2000,$B$2,IN_Contrib!$C$4:$C$2000,"December") -> 0 | K11: =SUMIFS(IN_Contrib!$Z$4:$Z$2000,IN_Contrib!$A$4:$A$2000,$A11,IN_Contrib!$B$4:$B$2000,$B$2,IN_Contrib!$C$4:$C$2000,"January") -> 0 | L11: =SUMIFS(IN_Contrib!$Z$4:$Z$2000,IN_Contrib!$A$4:$A$2000,$A11,IN_Contrib!$B$4:$B$2000,$B$2,IN_Contrib!$C$4:$C$2000,"February") -> 0 | M11: =SUMIFS(IN_Contrib!$Z$4:$Z$2000,IN_Contrib!$A$4:$A$2000,$A11,IN_Contrib!$B$4:$B$2000,$B$2,IN_Contrib!$C$4:$C$2000,"March") -> 0 | N11: =SUM(B11:M11) -> 0
A12: BEML | B12: =SUMIFS(IN_Contrib!$Z$4:$Z$2000,IN_Contrib!$A$4:$A$2000,$A12,IN_Contrib!$B$4:$B$2000,$B$2,IN_Contrib!$C$4:$C$2000,"April") -> 0 | C12: =SUMIFS(IN_Contrib!$Z$4:$Z$2000,IN_Contrib!$A$4:$A$2000,$A12,IN_Contrib!$B$4:$B$2000,$B$2,IN_Contrib!$C$4:$C$2000,"May") -> 0 | D12: =SUMIFS(IN_Contrib!$Z$4:$Z$2000,IN_Contrib!$A$4:$A$2000,$A12,IN_Contrib!$B$4:$B$2000,$B$2,IN_Contrib!$C$4:$C$2000,"June") -> 0 | E12: =SUMIFS(IN_Contrib!$Z$4:$Z$2000,IN_Contrib!$A$4:$A$2000,$A12,IN_Contrib!$B$4:$B$2000,$B$2,IN_Contrib!$C$4:$C$2000,"July") -> 0 | F12: =SUMIFS(IN_Contrib!$Z$4:$Z$2000,IN_Contrib!$A$4:$A$2000,$A12,IN_Contrib!$B$4:$B$2000,$B$2,IN_Contrib!$C$4:$C$2000,"August") -> 0 | G12: =SUMIFS(IN_Contrib!$Z$4:$Z$2000,IN_Contrib!$A$4:$A$2000,$A12,IN_Contrib!$B$4:$B$2000,$B$2,IN_Contrib!$C$4:$C$2000,"September") -> 0 | H12: =SUMIFS(IN_Contrib!$Z$4:$Z$2000,IN_Contrib!$A$4:$A$2000,$A12,IN_Contrib!$B$4:$B$2000,$B$2,IN_Contrib!$C$4:$C$2000,"October") -> 0 | I12: =SUMIFS(IN_Contrib!$Z$4:$Z$2000,IN_Contrib!$A$4:$A$2000,$A12,IN_Contrib!$B$4:$B$2000,$B$2,IN_Contrib!$C$4:$C$2000,"November") -> 0 | J12: =SUMIFS(IN_Contrib!$Z$4:$Z$2000,IN_Contrib!$A$4:$A$2000,$A12,IN_Contrib!$B$4:$B$2000,$B$2,IN_Contrib!$C$4:$C$2000,"December") -> 0 | K12: =SUMIFS(IN_Contrib!$Z$4:$Z$2000,IN_Contrib!$A$4:$A$2000,$A12,IN_Contrib!$B$4:$B$2000,$B$2,IN_Contrib!$C$4:$C$2000,"January") -> 0 | L12: =SUMIFS(IN_Contrib!$Z$4:$Z$2000,IN_Contrib!$A$4:$A$2000,$A12,IN_Contrib!$B$4:$B$2000,$B$2,IN_Contrib!$C$4:$C$2000,"February") -> 0 | M12: =SUMIFS(IN_Contrib!$Z$4:$Z$2000,IN_Contrib!$A$4:$A$2000,$A12,IN_Contrib!$B$4:$B$2000,$B$2,IN_Contrib!$C$4:$C$2000,"March") -> 0 | N12: =SUM(B12:M12) -> 0
A13: Uchimura India | B13: =SUMIFS(IN_Contrib!$Z$4:$Z$2000,IN_Contrib!$A$4:$A$2000,$A13,IN_Contrib!$B$4:$B$2000,$B$2,IN_Contrib!$C$4:$C$2000,"April") -> 0 | C13: =SUMIFS(IN_Contrib!$Z$4:$Z$2000,IN_Contrib!$A$4:$A$2000,$A13,IN_Contrib!$B$4:$B$2000,$B$2,IN_Contrib!$C$4:$C$2000,"May") -> 0 | D13: =SUMIFS(IN_Contrib!$Z$4:$Z$2000,IN_Contrib!$A$4:$A$2000,$A13,IN_Contrib!$B$4:$B$2000,$B$2,IN_Contrib!$C$4:$C$2000,"June") -> 0 | E13: =SUMIFS(IN_Contrib!$Z$4:$Z$2000,IN_Contrib!$A$4:$A$2000,$A13,IN_Contrib!$B$4:$B$2000,$B$2,IN_Contrib!$C$4:$C$2000,"July") -> 0 | F13: =SUMIFS(IN_Contrib!$Z$4:$Z$2000,IN_Contrib!$A$4:$A$2000,$A13,IN_Contrib!$B$4:$B$2000,$B$2,IN_Contrib!$C$4:$C$2000,"August") -> 0 | G13: =SUMIFS(IN_Contrib!$Z$4:$Z$2000,IN_Contrib!$A$4:$A$2000,$A13,IN_Contrib!$B$4:$B$2000,$B$2,IN_Contrib!$C$4:$C$2000,"September") -> 0 | H13: =SUMIFS(IN_Contrib!$Z$4:$Z$2000,IN_Contrib!$A$4:$A$2000,$A13,IN_Contrib!$B$4:$B$2000,$B$2,IN_Contrib!$C$4:$C$2000,"October") -> 0 | I13: =SUMIFS(IN_Contrib!$Z$4:$Z$2000,IN_Contrib!$A$4:$A$2000,$A13,IN_Contrib!$B$4:$B$2000,$B$2,IN_Contrib!$C$4:$C$2000,"November") -> 0 | J13: =SUMIFS(IN_Contrib!$Z$4:$Z$2000,IN_Contrib!$A$4:$A$2000,$A13,IN_Contrib!$B$4:$B$2000,$B$2,IN_Contrib!$C$4:$C$2000,"December") -> 0 | K13: =SUMIFS(IN_Contrib!$Z$4:$Z$2000,IN_Contrib!$A$4:$A$2000,$A13,IN_Contrib!$B$4:$B$2000,$B$2,IN_Contrib!$C$4:$C$2000,"January") -> 0 | L13: =SUMIFS(IN_Contrib!$Z$4:$Z$2000,IN_Contrib!$A$4:$A$2000,$A13,IN_Contrib!$B$4:$B$2000,$B$2,IN_Contrib!$C$4:$C$2000,"February") -> 0 | M13: =SUMIFS(IN_Contrib!$Z$4:$Z$2000,IN_Contrib!$A$4:$A$2000,$A13,IN_Contrib!$B$4:$B$2000,$B$2,IN_Contrib!$C$4:$C$2000,"March") -> 0 | N13: =SUM(B13:M13) -> 0
A14: Wilson | B14: =SUMIFS(IN_Contrib!$Z$4:$Z$2000,IN_Contrib!$A$4:$A$2000,$A14,IN_Contrib!$B$4:$B$2000,$B$2,IN_Contrib!$C$4:$C$2000,"April") -> 0 | C14: =SUMIFS(IN_Contrib!$Z$4:$Z$2000,IN_Contrib!$A$4:$A$2000,$A14,IN_Contrib!$B$4:$B$2000,$B$2,IN_Contrib!$C$4:$C$2000,"May") -> 0 | D14: =SUMIFS(IN_Contrib!$Z$4:$Z$2000,IN_Contrib!$A$4:$A$2000,$A14,IN_Contrib!$B$4:$B$2000,$B$2,IN_Contrib!$C$4:$C$2000,"June") -> 0 | E14: =SUMIFS(IN_Contrib!$Z$4:$Z$2000,IN_Contrib!$A$4:$A$2000,$A14,IN_Contrib!$B$4:$B$2000,$B$2,IN_Contrib!$C$4:$C$2000,"July") -> 0 | F14: =SUMIFS(IN_Contrib!$Z$4:$Z$2000,IN_Contrib!$A$4:$A$2000,$A14,IN_Contrib!$B$4:$B$2000,$B$2,IN_Contrib!$C$4:$C$2000,"August") -> 0 | G14: =SUMIFS(IN_Contrib!$Z$4:$Z$2000,IN_Contrib!$A$4:$A$2000,$A14,IN_Contrib!$B$4:$B$2000,$B$2,IN_Contrib!$C$4:$C$2000,"September") -> 0 | H14: =SUMIFS(IN_Contrib!$Z$4:$Z$2000,IN_Contrib!$A$4:$A$2000,$A14,IN_Contrib!$B$4:$B$2000,$B$2,IN_Contrib!$C$4:$C$2000,"October") -> 0 | I14: =SUMIFS(IN_Contrib!$Z$4:$Z$2000,IN_Contrib!$A$4:$A$2000,$A14,IN_Contrib!$B$4:$B$2000,$B$2,IN_Contrib!$C$4:$C$2000,"November") -> 0 | J14: =SUMIFS(IN_Contrib!$Z$4:$Z$2000,IN_Contrib!$A$4:$A$2000,$A14,IN_Contrib!$B$4:$B$2000,$B$2,IN_Contrib!$C$4:$C$2000,"December") -> 0 | K14: =SUMIFS(IN_Contrib!$Z$4:$Z$2000,IN_Contrib!$A$4:$A$2000,$A14,IN_Contrib!$B$4:$B$2000,$B$2,IN_Contrib!$C$4:$C$2000,"January") -> 0 | L14: =SUMIFS(IN_Contrib!$Z$4:$Z$2000,IN_Contrib!$A$4:$A$2000,$A14,IN_Contrib!$B$4:$B$2000,$B$2,IN_Contrib!$C$4:$C$2000,"February") -> 0 | M14: =SUMIFS(IN_Contrib!$Z$4:$Z$2000,IN_Contrib!$A$4:$A$2000,$A14,IN_Contrib!$B$4:$B$2000,$B$2,IN_Contrib!$C$4:$C$2000,"March") -> 0 | N14: =SUM(B14:M14) -> 0
A15: Hensley | B15: =SUMIFS(IN_Contrib!$Z$4:$Z$2000,IN_Contrib!$A$4:$A$2000,$A15,IN_Contrib!$B$4:$B$2000,$B$2,IN_Contrib!$C$4:$C$2000,"April") -> 0 | C15: =SUMIFS(IN_Contrib!$Z$4:$Z$2000,IN_Contrib!$A$4:$A$2000,$A15,IN_Contrib!$B$4:$B$2000,$B$2,IN_Contrib!$C$4:$C$2000,"May") -> 0.43 | D15: =SUMIFS(IN_Contrib!$Z$4:$Z$2000,IN_Contrib!$A$4:$A$2000,$A15,IN_Contrib!$B$4:$B$2000,$B$2,IN_Contrib!$C$4:$C$2000,"June") -> 0 | E15: =SUMIFS(IN_Contrib!$Z$4:$Z$2000,IN_Contrib!$A$4:$A$2000,$A15,IN_Contrib!$B$4:$B$2000,$B$2,IN_Contrib!$C$4:$C$2000,"July") -> 0 | F15: =SUMIFS(IN_Contrib!$Z$4:$Z$2000,IN_Contrib!$A$4:$A$2000,$A15,IN_Contrib!$B$4:$B$2000,$B$2,IN_Contrib!$C$4:$C$2000,"August") -> 0 | G15: =SUMIFS(IN_Contrib!$Z$4:$Z$2000,IN_Contrib!$A$4:$A$2000,$A15,IN_Contrib!$B$4:$B$2000,$B$2,IN_Contrib!$C$4:$C$2000,"September") -> 0 | H15: =SUMIFS(IN_Contrib!$Z$4:$Z$2000,IN_Contrib!$A$4:$A$2000,$A15,IN_Contrib!$B$4:$B$2000,$B$2,IN_Contrib!$C$4:$C$2000,"October") -> 0 | I15: =SUMIFS(IN_Contrib!$Z$4:$Z$2000,IN_Contrib!$A$4:$A$2000,$A15,IN_Contrib!$B$4:$B$2000,$B$2,IN_Contrib!$C$4:$C$2000,"November") -> 0 | J15: =SUMIFS(IN_Contrib!$Z$4:$Z$2000,IN_Contrib!$A$4:$A$2000,$A15,IN_Contrib!$B$4:$B$2000,$B$2,IN_Contrib!$C$4:$C$2000,"December") -> 0 | K15: =SUMIFS(IN_Contrib!$Z$4:$Z$2000,IN_Contrib!$A$4:$A$2000,$A15,IN_Contrib!$B$4:$B$2000,$B$2,IN_Contrib!$C$4:$C$2000,"January") -> 0 | L15: =SUMIFS(IN_Contrib!$Z$4:$Z$2000,IN_Contrib!$A$4:$A$2000,$A15,IN_Contrib!$B$4:$B$2000,$B$2,IN_Contrib!$C$4:$C$2000,"February") -> 0 | M15: =SUMIFS(IN_Contrib!$Z$4:$Z$2000,IN_Contrib!$A$4:$A$2000,$A15,IN_Contrib!$B$4:$B$2000,$B$2,IN_Contrib!$C$4:$C$2000,"March") -> 0 | N15: =SUM(B15:M15) -> 0.43
A16: TATA Metaliks | B16: =SUMIFS(IN_Contrib!$Z$4:$Z$2000,IN_Contrib!$A$4:$A$2000,$A16,IN_Contrib!$B$4:$B$2000,$B$2,IN_Contrib!$C$4:$C$2000,"April") -> 0 | C16: =SUMIFS(IN_Contrib!$Z$4:$Z$2000,IN_Contrib!$A$4:$A$2000,$A16,IN_Contrib!$B$4:$B$2000,$B$2,IN_Contrib!$C$4:$C$2000,"May") -> 0 | D16: =SUMIFS(IN_Contrib!$Z$4:$Z$2000,IN_Contrib!$A$4:$A$2000,$A16,IN_Contrib!$B$4:$B$2000,$B$2,IN_Contrib!$C$4:$C$2000,"June") -> 0 | E16: =SUMIFS(IN_Contrib!$Z$4:$Z$2000,IN_Contrib!$A$4:$A$2000,$A16,IN_Contrib!$B$4:$B$2000,$B$2,IN_Contrib!$C$4:$C$2000,"July") -> 0 | F16: =SUMIFS(IN_Contrib!$Z$4:$Z$2000,IN_Contrib!$A$4:$A$2000,$A16,IN_Contrib!$B$4:$B$2000,$B$2,IN_Contrib!$C$4:$C$2000,"August") -> 0 | G16: =SUMIFS(IN_Contrib!$Z$4:$Z$2000,IN_Contrib!$A$4:$A$2000,$A16,IN_Contrib!$B$4:$B$2000,$B$2,IN_Contrib!$C$4:$C$2000,"September") -> 0 | H16: =SUMIFS(IN_Contrib!$Z$4:$Z$2000,IN_Contrib!$A$4:$A$2000,$A16,IN_Contrib!$B$4:$B$2000,$B$2,IN_Contrib!$C$4:$C$2000,"October") -> 0 | I16: =SUMIFS(IN_Contrib!$Z$4:$Z$2000,IN_Contrib!$A$4:$A$2000,$A16,IN_Contrib!$B$4:$B$2000,$B$2,IN_Contrib!$C$4:$C$2000,"November") -> 0 | J16: =SUMIFS(IN_Contrib!$Z$4:$Z$2000,IN_Contrib!$A$4:$A$2000,$A16,IN_Contrib!$B$4:$B$2000,$B$2,IN_Contrib!$C$4:$C$2000,"December") -> 0 | K16: =SUMIFS(IN_Contrib!$Z$4:$Z$2000,IN_Contrib!$A$4:$A$2000,$A16,IN_Contrib!$B$4:$B$2000,$B$2,IN_Contrib!$C$4:$C$2000,"January") -> 0 | L16: =SUMIFS(IN_Contrib!$Z$4:$Z$2000,IN_Contrib!$A$4:$A$2000,$A16,IN_Contrib!$B$4:$B$2000,$B$2,IN_Contrib!$C$4:$C$2000,"February") -> 0 | M16: =SUMIFS(IN_Contrib!$Z$4:$Z$2000,IN_Contrib!$A$4:$A$2000,$A16,IN_Contrib!$B$4:$B$2000,$B$2,IN_Contrib!$C$4:$C$2000,"March") -> 0 | N16: =SUM(B16:M16) -> 0
B17: =SUMIFS(IN_Contrib!$Z$4:$Z$2000,IN_Contrib!$A$4:$A$2000,$A17,IN_Contrib!$B$4:$B$2000,$B$2,IN_Contrib!$C$4:$C$2000,"April") -> 0 | C17: =SUMIFS(IN_Contrib!$Z$4:$Z$2000,IN_Contrib!$A$4:$A$2000,$A17,IN_Contrib!$B$4:$B$2000,$B$2,IN_Contrib!$C$4:$C$2000,"May") -> 0 | D17: =SUMIFS(IN_Contrib!$Z$4:$Z$2000,IN_Contrib!$A$4:$A$2000,$A17,IN_Contrib!$B$4:$B$2000,$B$2,IN_Contrib!$C$4:$C$2000,"June") -> 0 | E17: =SUMIFS(IN_Contrib!$Z$4:$Z$2000,IN_Contrib!$A$4:$A$2000,$A17,IN_Contrib!$B$4:$B$2000,$B$2,IN_Contrib!$C$4:$C$2000,"July") -> 0 | F17: =SUMIFS(IN_Contrib!$Z$4:$Z$2000,IN_Contrib!$A$4:$A$2000,$A17,IN_Contrib!$B$4:$B$2000,$B$2,IN_Contrib!$C$4:$C$2000,"August") -> 0 | G17: =SUMIFS(IN_Contrib!$Z$4:$Z$2000,IN_Contrib!$A$4:$A$2000,$A17,IN_Contrib!$B$4:$B$2000,$B$2,IN_Contrib!$C$4:$C$2000,"September") -> 0 | H17: =SUMIFS(IN_Contrib!$Z$4:$Z$2000,IN_Contrib!$A$4:$A$2000,$A17,IN_Contrib!$B$4:$B$2000,$B$2,IN_Contrib!$C$4:$C$2000,"October") -> 0 | I17: =SUMIFS(IN_Contrib!$Z$4:$Z$2000,IN_Contrib!$A$4:$A$2000,$A17,IN_Contrib!$B$4:$B$2000,$B$2,IN_Contrib!$C$4:$C$2000,"November") -> 0 | J17: =SUMIFS(IN_Contrib!$Z$4:$Z$2000,IN_Contrib!$A$4:$A$2000,$A17,IN_Contrib!$B$4:$B$2000,$B$2,IN_Contrib!$C$4:$C$2000,"December") -> 0 | K17: =SUMIFS(IN_Contrib!$Z$4:$Z$2000,IN_Contrib!$A$4:$A$2000,$A17,IN_Contrib!$B$4:$B$2000,$B$2,IN_Contrib!$C$4:$C$2000,"January") -> 0 | L17: =SUMIFS(IN_Contrib!$Z$4:$Z$2000,IN_Contrib!$A$4:$A$2000,$A17,IN_Contrib!$B$4:$B$2000,$B$2,IN_Contrib!$C$4:$C$2000,"February") -> 0 | M17: =SUMIFS(IN_Contrib!$Z$4:$Z$2000,IN_Contrib!$A$4:$A$2000,$A17,IN_Contrib!$B$4:$B$2000,$B$2,IN_Contrib!$C$4:$C$2000,"March") -> 0 | N17: =SUM(B17:M17) -> 0
A18: Aaditya Consultancy | B18: =SUMIFS(IN_Contrib!$Z$4:$Z$2000,IN_Contrib!$A$4:$A$2000,$A18,IN_Contrib!$B$4:$B$2000,$B$2,IN_Contrib!$C$4:$C$2000,"April") -> 0 | C18: =SUMIFS(IN_Contrib!$Z$4:$Z$2000,IN_Contrib!$A$4:$A$2000,$A18,IN_Contrib!$B$4:$B$2000,$B$2,IN_Contrib!$C$4:$C$2000,"May") -> 0 | D18: =SUMIFS(IN_Contrib!$Z$4:$Z$2000,IN_Contrib!$A$4:$A$2000,$A18,IN_Contrib!$B$4:$B$2000,$B$2,IN_Contrib!$C$4:$C$2000,"June") -> 0 | E18: =SUMIFS(IN_Contrib!$Z$4:$Z$2000,IN_Contrib!$A$4:$A$2000,$A18,IN_Contrib!$B$4:$B$2000,$B$2,IN_Contrib!$C$4:$C$2000,"July") -> 0 | F18: =SUMIFS(IN_Contrib!$Z$4:$Z$2000,IN_Contrib!$A$4:$A$2000,$A18,IN_Contrib!$B$4:$B$2000,$B$2,IN_Contrib!$C$4:$C$2000,"August") -> 0 | G18: =SUMIFS(IN_Contrib!$Z$4:$Z$2000,IN_Contrib!$A$4:$A$2000,$A18,IN_Contrib!$B$4:$B$2000,$B$2,IN_Contrib!$C$4:$C$2000,"September") -> 0 | H18: =SUMIFS(IN_Contrib!$Z$4:$Z$2000,IN_Contrib!$A$4:$A$2000,$A18,IN_Contrib!$B$4:$B$2000,$B$2,IN_Contrib!$C$4:$C$2000,"October") -> 0 | I18: =SUMIFS(IN_Contrib!$Z$4:$Z$2000,IN_Contrib!$A$4:$A$2000,$A18,IN_Contrib!$B$4:$B$2000,$B$2,IN_Contrib!$C$4:$C$2000,"November") -> 0 | J18: =SUMIFS(IN_Contrib!$Z$4:$Z$2000,IN_Contrib!$A$4:$A$2000,$A18,IN_Contrib!$B$4:$B$2000,$B$2,IN_Contrib!$C$4:$C$2000,"December") -> 0 | K18: =SUMIFS(IN_Contrib!$Z$4:$Z$2000,IN_Contrib!$A$4:$A$2000,$A18,IN_Contrib!$B$4:$B$2000,$B$2,IN_Contrib!$C$4:$C$2000,"January") -> 0 | L18: =SUMIFS(IN_Contrib!$Z$4:$Z$2000,IN_Contrib!$A$4:$A$2000,$A18,IN_Contrib!$B$4:$B$2000,$B$2,IN_Contrib!$C$4:$C$2000,"February") -> 0 | M18: =SUMIFS(IN_Contrib!$Z$4:$Z$2000,IN_Contrib!$A$4:$A$2000,$A18,IN_Contrib!$B$4:$B$2000,$B$2,IN_Contrib!$C$4:$C$2000,"March") -> 0 | N18: =SUM(B18:M18) -> 0
A19: Total | B19: =SUM(B5:B18) -> 20.96 | C19: =SUM(C5:C18) -> 47.26 | D19: =SUM(D5:D18) -> 55.89 | E19: =SUM(E5:E18) -> 57.05 | F19: =SUM(F5:F18) -> 47.98 | G19: =SUM(G5:G18) -> 72.02 | H19: =SUM(H5:H18) -> 0 | I19: =SUM(I5:I18) -> 0 | ... N19: =SUM(N5:N18) -> 301.16
A21: Monthly totals (all customers) | B21: Apr | C21: May | D21: Jun | E21: Jul | F21: Aug | G21: Sep | H21: Oct | I21: Nov | J21: Dec | K21: Jan | L21: Feb | M21: Mar | N21: Total
A22: Pouring MT | B22: =SUMIFS(IN_Contrib!$G$4:$G$2000,IN_Contrib!$B$4:$B$2000,$B$2,IN_Contrib!$C$4:$C$2000,"April") -> 39.086 | C22: =SUMIFS(IN_Contrib!$G$4:$G$2000,IN_Contrib!$B$4:$B$2000,$B$2,IN_Contrib!$C$4:$C$2000,"May") -> 91.311 | D22: =SUMIFS(IN_Contrib!$G$4:$G$2000,IN_Contrib!$B$4:$B$2000,$B$2,IN_Contrib!$C$4:$C$2000,"June") -> 92.135 | E22: =SUMIFS(IN_Contrib!$G$4:$G$2000,IN_Contrib!$B$4:$B$2000,$B$2,IN_Contrib!$C$4:$C$2000,"July") -> 106.77 | F22: =SUMIFS(IN_Contrib!$G$4:$G$2000,IN_Contrib!$B$4:$B$2000,$B$2,IN_Contrib!$C$4:$C$2000,"August") -> 85.14 | G22: =SUMIFS(IN_Contrib!$G$4:$G$2000,IN_Contrib!$B$4:$B$2000,$B$2,IN_Contrib!$C$4:$C$2000,"September") -> 113.84 | H22: =SUMIFS(IN_Contrib!$G$4:$G$2000,IN_Contrib!$B$4:$B$2000,$B$2,IN_Contrib!$C$4:$C$2000,"October") -> 0 | I22: =SUMIFS(IN_Contrib!$G$4:$G$2000,IN_Contrib!$B$4:$B$2000,$B$2,IN_Contrib!$C$4:$C$2000,"November") -> 0 | J22: =SUMIFS(IN_Contrib!$G$4:$G$2000,IN_Contrib!$B$4:$B$2000,$B$2,IN_Contrib!$C$4:$C$2000,"December") -> 0 | K22: =SUMIFS(IN_Contrib!$G$4:$G$2000,IN_Contrib!$B$4:$B$2000,$B$2,IN_Contrib!$C$4:$C$2000,"January") -> 0 | L22: =SUMIFS(IN_Contrib!$G$4:$G$2000,IN_Contrib!$B$4:$B$2000,$B$2,IN_Contrib!$C$4:$C$2000,"February") -> 0 | M22: =SUMIFS(IN_Contrib!$G$4:$G$2000,IN_Contrib!$B$4:$B$2000,$B$2,IN_Contrib!$C$4:$C$2000,"March") -> 0 | N22: =SUM(B22:M22) -> 528.282
A23: Rejection MT (Nos x wt) | B23: =SUMIFS(IN_Contrib!$AD$4:$AD$2000,IN_Contrib!$B$4:$B$2000,$B$2,IN_Contrib!$C$4:$C$2000,"April") -> 5.478 | C23: =SUMIFS(IN_Contrib!$AD$4:$AD$2000,IN_Contrib!$B$4:$B$2000,$B$2,IN_Contrib!$C$4:$C$2000,"May") -> 4.942 | D23: =SUMIFS(IN_Contrib!$AD$4:$AD$2000,IN_Contrib!$B$4:$B$2000,$B$2,IN_Contrib!$C$4:$C$2000,"June") -> 1.0485 | E23: =SUMIFS(IN_Contrib!$AD$4:$AD$2000,IN_Contrib!$B$4:$B$2000,$B$2,IN_Contrib!$C$4:$C$2000,"July") -> 6.4248 | F23: =SUMIFS(IN_Contrib!$AD$4:$AD$2000,IN_Contrib!$B$4:$B$2000,$B$2,IN_Contrib!$C$4:$C$2000,"August") -> 7.782 | G23: =SUMIFS(IN_Contrib!$AD$4:$AD$2000,IN_Contrib!$B$4:$B$2000,$B$2,IN_Contrib!$C$4:$C$2000,"September") -> 8.51899 | H23: =SUMIFS(IN_Contrib!$AD$4:$AD$2000,IN_Contrib!$B$4:$B$2000,$B$2,IN_Contrib!$C$4:$C$2000,"October") -> 0 | I23: =SUMIFS(IN_Contrib!$AD$4:$AD$2000,IN_Contrib!$B$4:$B$2000,$B$2,IN_Contrib!$C$4:$C$2000,"November") -> 0 | J23: =SUMIFS(IN_Contrib!$AD$4:$AD$2000,IN_Contrib!$B$4:$B$2000,$B$2,IN_Contrib!$C$4:$C$2000,"December") -> 0 | K23: =SUMIFS(IN_Contrib!$AD$4:$AD$2000,IN_Contrib!$B$4:$B$2000,$B$2,IN_Contrib!$C$4:$C$2000,"January") -> 0 | L23: =SUMIFS(IN_Contrib!$AD$4:$AD$2000,IN_Contrib!$B$4:$B$2000,$B$2,IN_Contrib!$C$4:$C$2000,"February") -> 0 | M23: =SUMIFS(IN_Contrib!$AD$4:$AD$2000,IN_Contrib!$B$4:$B$2000,$B$2,IN_Contrib!$C$4:$C$2000,"March") -> 0 | N23: =SUM(B23:M23) -> 34.19429
A24: Destruct test MT | B24: =SUMIFS(IN_Contrib!$AE$4:$AE$2000,IN_Contrib!$B$4:$B$2000,$B$2,IN_Contrib!$C$4:$C$2000,"April") -> 0.186 | C24: =SUMIFS(IN_Contrib!$AE$4:$AE$2000,IN_Contrib!$B$4:$B$2000,$B$2,IN_Contrib!$C$4:$C$2000,"May") -> 1.908 | D24: =SUMIFS(IN_Contrib!$AE$4:$AE$2000,IN_Contrib!$B$4:$B$2000,$B$2,IN_Contrib!$C$4:$C$2000,"June") -> 6.0725 | E24: =SUMIFS(IN_Contrib!$AE$4:$AE$2000,IN_Contrib!$B$4:$B$2000,$B$2,IN_Contrib!$C$4:$C$2000,"July") -> 3.35465 | F24: =SUMIFS(IN_Contrib!$AE$4:$AE$2000,IN_Contrib!$B$4:$B$2000,$B$2,IN_Contrib!$C$4:$C$2000,"August") -> 1.3625 | G24: =SUMIFS(IN_Contrib!$AE$4:$AE$2000,IN_Contrib!$B$4:$B$2000,$B$2,IN_Contrib!$C$4:$C$2000,"September") -> 0.41528 | H24: =SUMIFS(IN_Contrib!$AE$4:$AE$2000,IN_Contrib!$B$4:$B$2000,$B$2,IN_Contrib!$C$4:$C$2000,"October") -> 0 | I24: =SUMIFS(IN_Contrib!$AE$4:$AE$2000,IN_Contrib!$B$4:$B$2000,$B$2,IN_Contrib!$C$4:$C$2000,"November") -> 0 | J24: =SUMIFS(IN_Contrib!$AE$4:$AE$2000,IN_Contrib!$B$4:$B$2000,$B$2,IN_Contrib!$C$4:$C$2000,"December") -> 0 | K24: =SUMIFS(IN_Contrib!$AE$4:$AE$2000,IN_Contrib!$B$4:$B$2000,$B$2,IN_Contrib!$C$4:$C$2000,"January") -> 0 | L24: =SUMIFS(IN_Contrib!$AE$4:$AE$2000,IN_Contrib!$B$4:$B$2000,$B$2,IN_Contrib!$C$4:$C$2000,"February") -> 0 | M24: =SUMIFS(IN_Contrib!$AE$4:$AE$2000,IN_Contrib!$B$4:$B$2000,$B$2,IN_Contrib!$C$4:$C$2000,"March") -> 0 | N24: =SUM(B24:M24) -> 13.29893
A25: Contribution Rs L | B25: =SUMIFS(IN_Contrib!$Z$4:$Z$2000,IN_Contrib!$B$4:$B$2000,$B$2,IN_Contrib!$C$4:$C$2000,"April") -> 20.96 | C25: =SUMIFS(IN_Contrib!$Z$4:$Z$2000,IN_Contrib!$B$4:$B$2000,$B$2,IN_Contrib!$C$4:$C$2000,"May") -> 47.26 | D25: =SUMIFS(IN_Contrib!$Z$4:$Z$2000,IN_Contrib!$B$4:$B$2000,$B$2,IN_Contrib!$C$4:$C$2000,"June") -> 55.89 | E25: =SUMIFS(IN_Contrib!$Z$4:$Z$2000,IN_Contrib!$B$4:$B$2000,$B$2,IN_Contrib!$C$4:$C$2000,"July") -> 57.05 | F25: =SUMIFS(IN_Contrib!$Z$4:$Z$2000,IN_Contrib!$B$4:$B$2000,$B$2,IN_Contrib!$C$4:$C$2000,"August") -> 47.98 | G25: =SUMIFS(IN_Contrib!$Z$4:$Z$2000,IN_Contrib!$B$4:$B$2000,$B$2,IN_Contrib!$C$4:$C$2000,"September") -> 72.02 | H25: =SUMIFS(IN_Contrib!$Z$4:$Z$2000,IN_Contrib!$B$4:$B$2000,$B$2,IN_Contrib!$C$4:$C$2000,"October") -> 0 | I25: =SUMIFS(IN_Contrib!$Z$4:$Z$2000,IN_Contrib!$B$4:$B$2000,$B$2,IN_Contrib!$C$4:$C$2000,"November") -> 0 | J25: =SUMIFS(IN_Contrib!$Z$4:$Z$2000,IN_Contrib!$B$4:$B$2000,$B$2,IN_Contrib!$C$4:$C$2000,"December") -> 0 | K25: =SUMIFS(IN_Contrib!$Z$4:$Z$2000,IN_Contrib!$B$4:$B$2000,$B$2,IN_Contrib!$C$4:$C$2000,"January") -> 0 | L25: =SUMIFS(IN_Contrib!$Z$4:$Z$2000,IN_Contrib!$B$4:$B$2000,$B$2,IN_Contrib!$C$4:$C$2000,"February") -> 0 | M25: =SUMIFS(IN_Contrib!$Z$4:$Z$2000,IN_Contrib!$B$4:$B$2000,$B$2,IN_Contrib!$C$4:$C$2000,"March") -> 0 | N25: =SUM(B25:M25) -> 301.16
A26: Rejection loss Rs L | B26: =SUMIFS(IN_Contrib!$AA$4:$AA$2000,IN_Contrib!$B$4:$B$2000,$B$2,IN_Contrib!$C$4:$C$2000,"April") -> 2.34 | C26: =SUMIFS(IN_Contrib!$AA$4:$AA$2000,IN_Contrib!$B$4:$B$2000,$B$2,IN_Contrib!$C$4:$C$2000,"May") -> 2.2 | D26: =SUMIFS(IN_Contrib!$AA$4:$AA$2000,IN_Contrib!$B$4:$B$2000,$B$2,IN_Contrib!$C$4:$C$2000,"June") -> 0.49 | E26: =SUMIFS(IN_Contrib!$AA$4:$AA$2000,IN_Contrib!$B$4:$B$2000,$B$2,IN_Contrib!$C$4:$C$2000,"July") -> 3.15 | F26: =SUMIFS(IN_Contrib!$AA$4:$AA$2000,IN_Contrib!$B$4:$B$2000,$B$2,IN_Contrib!$C$4:$C$2000,"August") -> 3.42 | G26: =SUMIFS(IN_Contrib!$AA$4:$AA$2000,IN_Contrib!$B$4:$B$2000,$B$2,IN_Contrib!$C$4:$C$2000,"September") -> 4.04 | H26: =SUMIFS(IN_Contrib!$AA$4:$AA$2000,IN_Contrib!$B$4:$B$2000,$B$2,IN_Contrib!$C$4:$C$2000,"October") -> 0 | I26: =SUMIFS(IN_Contrib!$AA$4:$AA$2000,IN_Contrib!$B$4:$B$2000,$B$2,IN_Contrib!$C$4:$C$2000,"November") -> 0 | J26: =SUMIFS(IN_Contrib!$AA$4:$AA$2000,IN_Contrib!$B$4:$B$2000,$B$2,IN_Contrib!$C$4:$C$2000,"December") -> 0 | K26: =SUMIFS(IN_Contrib!$AA$4:$AA$2000,IN_Contrib!$B$4:$B$2000,$B$2,IN_Contrib!$C$4:$C$2000,"January") -> 0 | L26: =SUMIFS(IN_Contrib!$AA$4:$AA$2000,IN_Contrib!$B$4:$B$2000,$B$2,IN_Contrib!$C$4:$C$2000,"February") -> 0 | M26: =SUMIFS(IN_Contrib!$AA$4:$AA$2000,IN_Contrib!$B$4:$B$2000,$B$2,IN_Contrib!$C$4:$C$2000,"March") -> 0 | N26: =SUM(B26:M26) -> 15.64
A27: Destruct test loss Rs L | B27: =SUMIFS(IN_Contrib!$AB$4:$AB$2000,IN_Contrib!$B$4:$B$2000,$B$2,IN_Contrib!$C$4:$C$2000,"April") -> 0.11 | C27: =SUMIFS(IN_Contrib!$AB$4:$AB$2000,IN_Contrib!$B$4:$B$2000,$B$2,IN_Contrib!$C$4:$C$2000,"May") -> 1.16 | D27: =SUMIFS(IN_Contrib!$AB$4:$AB$2000,IN_Contrib!$B$4:$B$2000,$B$2,IN_Contrib!$C$4:$C$2000,"June") -> 3.64 | E27: =SUMIFS(IN_Contrib!$AB$4:$AB$2000,IN_Contrib!$B$4:$B$2000,$B$2,IN_Contrib!$C$4:$C$2000,"July") -> 2.05 | F27: =SUMIFS(IN_Contrib!$AB$4:$AB$2000,IN_Contrib!$B$4:$B$2000,$B$2,IN_Contrib!$C$4:$C$2000,"August") -> 0.83 | G27: =SUMIFS(IN_Contrib!$AB$4:$AB$2000,IN_Contrib!$B$4:$B$2000,$B$2,IN_Contrib!$C$4:$C$2000,"September") -> 0.28 | H27: =SUMIFS(IN_Contrib!$AB$4:$AB$2000,IN_Contrib!$B$4:$B$2000,$B$2,IN_Contrib!$C$4:$C$2000,"October") -> 0 | I27: =SUMIFS(IN_Contrib!$AB$4:$AB$2000,IN_Contrib!$B$4:$B$2000,$B$2,IN_Contrib!$C$4:$C$2000,"November") -> 0 | J27: =SUMIFS(IN_Contrib!$AB$4:$AB$2000,IN_Contrib!$B$4:$B$2000,$B$2,IN_Contrib!$C$4:$C$2000,"December") -> 0 | K27: =SUMIFS(IN_Contrib!$AB$4:$AB$2000,IN_Contrib!$B$4:$B$2000,$B$2,IN_Contrib!$C$4:$C$2000,"January") -> 0 | L27: =SUMIFS(IN_Contrib!$AB$4:$AB$2000,IN_Contrib!$B$4:$B$2000,$B$2,IN_Contrib!$C$4:$C$2000,"February") -> 0 | M27: =SUMIFS(IN_Contrib!$AB$4:$AB$2000,IN_Contrib!$B$4:$B$2000,$B$2,IN_Contrib!$C$4:$C$2000,"March") -> 0 | N27: =SUM(B27:M27) -> 8.07
A28: Loss of contribution Rs L | B28: =SUMIFS(IN_Contrib!$AC$4:$AC$2000,IN_Contrib!$B$4:$B$2000,$B$2,IN_Contrib!$C$4:$C$2000,"April") -> 3.57 | C28: =SUMIFS(IN_Contrib!$AC$4:$AC$2000,IN_Contrib!$B$4:$B$2000,$B$2,IN_Contrib!$C$4:$C$2000,"May") -> 3.89 | D28: =SUMIFS(IN_Contrib!$AC$4:$AC$2000,IN_Contrib!$B$4:$B$2000,$B$2,IN_Contrib!$C$4:$C$2000,"June") -> 5.1 | E28: =SUMIFS(IN_Contrib!$AC$4:$AC$2000,IN_Contrib!$B$4:$B$2000,$B$2,IN_Contrib!$C$4:$C$2000,"July") -> 6.16 | F28: =SUMIFS(IN_Contrib!$AC$4:$AC$2000,IN_Contrib!$B$4:$B$2000,$B$2,IN_Contrib!$C$4:$C$2000,"August") -> 6.32 | G28: =SUMIFS(IN_Contrib!$AC$4:$AC$2000,IN_Contrib!$B$4:$B$2000,$B$2,IN_Contrib!$C$4:$C$2000,"September") -> 6.14 | H28: =SUMIFS(IN_Contrib!$AC$4:$AC$2000,IN_Contrib!$B$4:$B$2000,$B$2,IN_Contrib!$C$4:$C$2000,"October") -> 0 | I28: =SUMIFS(IN_Contrib!$AC$4:$AC$2000,IN_Contrib!$B$4:$B$2000,$B$2,IN_Contrib!$C$4:$C$2000,"November") -> 0 | J28: =SUMIFS(IN_Contrib!$AC$4:$AC$2000,IN_Contrib!$B$4:$B$2000,$B$2,IN_Contrib!$C$4:$C$2000,"December") -> 0 | K28: =SUMIFS(IN_Contrib!$AC$4:$AC$2000,IN_Contrib!$B$4:$B$2000,$B$2,IN_Contrib!$C$4:$C$2000,"January") -> 0 | L28: =SUMIFS(IN_Contrib!$AC$4:$AC$2000,IN_Contrib!$B$4:$B$2000,$B$2,IN_Contrib!$C$4:$C$2000,"February") -> 0 | M28: =SUMIFS(IN_Contrib!$AC$4:$AC$2000,IN_Contrib!$B$4:$B$2000,$B$2,IN_Contrib!$C$4:$C$2000,"March") -> 0 | N28: =SUM(B28:M28) -> 31.18
A30: Weighted avg contribution Rs/kg = Contribution Rs L x 100 / Pouring MT | B30: =IF(B22=0,0,B25*100/B22) -> 53.625339 | C30: =IF(C22=0,0,C25*100/C22) -> 51.757182 | D30: =IF(D22=0,0,D25*100/D22) -> 60.660987 | E30: =IF(E22=0,0,E25*100/E22) -> 53.432612 | F30: =IF(F22=0,0,F25*100/F22) -> 56.35424 | G30: =IF(G22=0,0,G25*100/G22) -> 63.26423 | H30: =IF(H22=0,0,H25*100/H22) -> 0 | I30: =IF(I22=0,0,I25*100/I22) -> 0 | ... N30: =IF(N22=0,0,N25*100/N22) -> 57.007432
A31: Ledger contribution per MIS (Rs L) | B31: =MIS!B22 -> 13.06 | C31: =MIS!C22 -> 35.85 | D31: =MIS!D22 -> 51.28 | E31: =MIS!F22 -> 58.26 | F31: =MIS!G22 -> 50.51 | G31: =MIS!H22 -> 66.84 | H31: =MIS!J22 -> 0 | I31: =MIS!K22 -> 0 | J31: =MIS!L22 -> 0 | K31: =MIS!N22 -> 0 | L31: =MIS!O22 -> 0 | M31: =MIS!P22 -> 0 | N31: =SUM(B31:M31) -> 275.8
A32: Difference: MIS ledger contribution - product-wise contribution | B32: =B31-B25 -> -7.9 | C32: =C31-C25 -> -11.41 | D32: =D31-D25 -> -4.61 | E32: =E31-E25 -> 1.21 | F32: =F31-F25 -> 2.53 | G32: =G31-G25 -> -5.18 | H32: =H31-H25 -> 0 | I32: =I31-I25 -> 0 | ... M32: =M31-M25 -> 0 | N32: =SUM(B32:M32) -> -25.36

Sheet CHECK
A1: TIE-OUT: model MIS vs published Sept'26 MIS (Apr-Sep'26)
A3: Line | B3: Basis | C3: Apr'26 | D3: May'26 | E3: Jun'26 | F3: Jul'26 | G3: Aug'26 | H3: Sep'26 | I3: Max |var|
A4: Sales Domestic (incl GST) | B4: Published | C4: 150.43 | D4: 183.09 | E4: 252.08 | F4: 326.82 | G4: 271.68 | H4: 257.64
B5: Model | C5: =MIS!B7 -> 150.43 | D5: =MIS!C7 -> 183.09 | E5: =MIS!D7 -> 252.08 | F5: =MIS!F7 -> 326.82 | G5: =MIS!G7 -> 271.68 | H5: =MIS!H7 -> 257.64
B6: Variance | C6: =ROUND(C5-C4,2) -> 0 | D6: =ROUND(D5-D4,2) -> 0 | E6: =ROUND(E5-E4,2) -> 0 | F6: =ROUND(F5-F4,2) -> 0 | G6: =ROUND(G5-G4,2) -> 0 | H6: =ROUND(H5-H4,2) -> 0 | I6: =MAX(MAX(C6:H6),-MIN(C6:H6)) -> 0
A7: Less GST | B7: Published | C7: 22.95 | D7: 27.93 | E7: 38.45 | F7: 49.85 | G7: 41.44 | H7: 39.3
B8: Model | C8: =MIS!B8 -> 22.95 | D8: =MIS!C8 -> 27.93 | E8: =MIS!D8 -> 38.45 | F8: =MIS!F8 -> 49.85 | G8: =MIS!G8 -> 41.44 | H8: =MIS!H8 -> 39.3
B9: Variance | C9: =ROUND(C8-C7,2) -> 0 | D9: =ROUND(D8-D7,2) -> 0 | E9: =ROUND(E8-E7,2) -> 0 | F9: =ROUND(F8-F7,2) -> 0 | G9: =ROUND(G8-G7,2) -> 0 | H9: =ROUND(H8-H7,2) -> 0 | I9: =MAX(MAX(C9:H9),-MIN(C9:H9)) -> 0
A10: Sales Domestic (ex GST) | B10: Published | C10: 127.48 | D10: 155.16 | E10: 213.63 | F10: 276.97 | G10: 230.24 | H10: 218.34
B11: Model | C11: =MIS!B9 -> 127.48 | D11: =MIS!C9 -> 155.16 | E11: =MIS!D9 -> 213.63 | F11: =MIS!F9 -> 276.97 | G11: =MIS!G9 -> 230.24 | H11: =MIS!H9 -> 218.34
B12: Variance | C12: =ROUND(C11-C10,2) -> 0 | D12: =ROUND(D11-D10,2) -> 0 | E12: =ROUND(E11-E10,2) -> 0 | F12: =ROUND(F11-F10,2) -> 0 | G12: =ROUND(G11-G10,2) -> 0 | H12: =ROUND(H11-H10,2) -> 0 | I12: =MAX(MAX(C12:H12),-MIN(C12:H12)) -> 0
A13: Less: Sales Return | B13: Published | C13: 0 | D13: 4.86 | E13: 7.15 | F13: 1.35 | G13: 1 | H13: 0.56
B14: Model | C14: =MIS!B10 -> 0 | D14: =MIS!C10 -> 4.86 | E14: =MIS!D10 -> 7.15 | F14: =MIS!F10 -> 1.35 | G14: =MIS!G10 -> 1 | H14: =MIS!H10 -> 0.56
B15: Variance | C15: =ROUND(C14-C13,2) -> 0 | D15: =ROUND(D14-D13,2) -> 0 | E15: =ROUND(E14-E13,2) -> 0 | F15: =ROUND(F14-F13,2) -> 0 | G15: =ROUND(G14-G13,2) -> 0 | H15: =ROUND(H14-H13,2) -> 0 | I15: =MAX(MAX(C15:H15),-MIN(C15:H15)) -> 0
A16: Net Sales | B16: Published | C16: 127.48 | D16: 150.3 | E16: 206.48 | F16: 275.62 | G16: 229.24 | H16: 217.78
B17: Model | C17: =MIS!B11 -> 127.48 | D17: =MIS!C11 -> 150.3 | E17: =MIS!D11 -> 206.48 | F17: =MIS!F11 -> 275.62 | G17: =MIS!G11 -> 229.24 | H17: =MIS!H11 -> 217.78
B18: Variance | C18: =ROUND(C17-C16,2) -> 0 | D18: =ROUND(D17-D16,2) -> 0 | E18: =ROUND(E17-E16,2) -> 0 | F18: =ROUND(F17-F16,2) -> 0 | G18: =ROUND(G17-G16,2) -> 0 | H18: =ROUND(H17-H16,2) -> 0 | I18: =MAX(MAX(C18:H18),-MIN(C18:H18)) -> 0
A19: Other Business Income/Sales | B19: Published | C19: 0 | D19: 1.5 | E19: 0 | F19: 0 | G19: 2.5 | H19: 4.8
B20: Model | C20: =MIS!B12 -> 0 | D20: =MIS!C12 -> 1.5 | E20: =MIS!D12 -> 0 | F20: =MIS!F12 -> 0 | G20: =MIS!G12 -> 2.5 | H20: =MIS!H12 -> 4.8
B21: Variance | C21: =ROUND(C20-C19,2) -> 0 | D21: =ROUND(D20-D19,2) -> 0 | E21: =ROUND(E20-E19,2) -> 0 | F21: =ROUND(F20-F19,2) -> 0 | G21: =ROUND(G20-G19,2) -> 0 | H21: =ROUND(H20-H19,2) -> 0 | I21: =MAX(MAX(C21:H21),-MIN(C21:H21)) -> 0
A22: Stock of Return Goods (Valued at Sales Price) | B22: Published | C22: -15.08 | D22: -3.56 | E22: -4.02 | F22: -3.79 | G22: 1 | H22: 0.56
B23: Model | C23: =MIS!B13 -> -15.08 | D23: =MIS!C13 -> -3.56 | E23: =MIS!D13 -> -4.02 | F23: =MIS!F13 -> -3.79 | G23: =MIS!G13 -> 1 | H23: =MIS!H13 -> 0.56
B24: Variance | C24: =ROUND(C23-C22,2) -> 0 | D24: =ROUND(D23-D22,2) -> 0 | E24: =ROUND(E23-E22,2) -> 0 | F24: =ROUND(F23-F22,2) -> 0 | G24: =ROUND(G23-G22,2) -> 0 | H24: =ROUND(H23-H22,2) -> 0 | I24: =MAX(MAX(C24:H24),-MIN(C24:H24)) -> 0
A25: Net turnover for contribution | B25: Published | C25: 112.4 | D25: 148.24 | E25: 202.46 | F25: 271.83 | G25: 232.74 | H25: 223.14
B26: Model | C26: =MIS!B14 -> 112.4 | D26: =MIS!C14 -> 148.24 | E26: =MIS!D14 -> 202.46 | F26: =MIS!F14 -> 271.83 | G26: =MIS!G14 -> 232.74 | H26: =MIS!H14 -> 223.14
B27: Variance | C27: =ROUND(C26-C25,2) -> 0 | D27: =ROUND(D26-D25,2) -> 0 | E27: =ROUND(E26-E25,2) -> 0 | F27: =ROUND(F26-F25,2) -> 0 | G27: =ROUND(G26-G25,2) -> 0 | H27: =ROUND(H26-H25,2) -> 0 | I27: =MAX(MAX(C27:H27),-MIN(C27:H27)) -> 0
A28: Material Consumed-Direct & Indirect | B28: Published | C28: 47.91 | D28: 159.27 | E28: 153.67 | F28: 160.21 | G28: 109.64 | H28: 174.02
B29: Model | C29: =MIS!B16 -> 47.91 | D29: =MIS!C16 -> 159.27 | E29: =MIS!D16 -> 153.67 | F29: =MIS!F16 -> 160.21 | G29: =MIS!G16 -> 109.64 | H29: =MIS!H16 -> 174.02
B30: Variance | C30: =ROUND(C29-C28,2) -> 0 | D30: =ROUND(D29-D28,2) -> 0 | E30: =ROUND(E29-E28,2) -> 0 | F30: =ROUND(F29-F28,2) -> 0 | G30: =ROUND(G29-G28,2) -> 0 | H30: =ROUND(H29-H28,2) -> 0 | I30: =MAX(MAX(C30:H30),-MIN(C30:H30)) -> 0
A31: (Increase)/Decrease in Stock | B31: Published | C31: 31.72 | D31: -71.63 | E31: -32.47 | F31: 22.62 | G31: 43.89 | H31: -48.76
B32: Model | C32: =MIS!B17 -> 31.72 | D32: =MIS!C17 -> -71.63 | E32: =MIS!D17 -> -32.47 | F32: =MIS!F17 -> 22.62 | G32: =MIS!G17 -> 43.89 | H32: =MIS!H17 -> -48.76
B33: Variance | C33: =ROUND(C32-C31,2) -> 0 | D33: =ROUND(D32-D31,2) -> 0 | E33: =ROUND(E32-E31,2) -> 0 | F33: =ROUND(F32-F31,2) -> 0 | G33: =ROUND(G32-G31,2) -> 0 | H33: =ROUND(H32-H31,2) -> 0 | I33: =MAX(MAX(C33:H33),-MIN(C33:H33)) -> 0
A34: - Power & Fuel (Variable part) | B34: Published | C34: 10.61 | D34: 15.14 | E34: 17.79 | F34: 18.01 | G34: 17.14 | H34: 18.37
B35: Model | C35: =MIS!B19 -> 10.61 | D35: =MIS!C19 -> 15.14 | E35: =MIS!D19 -> 17.79 | F35: =MIS!F19 -> 18.01 | G35: =MIS!G19 -> 17.14 | H35: =MIS!H19 -> 18.37
B36: Variance | C36: =ROUND(C35-C34,2) -> 0 | D36: =ROUND(D35-D34,2) -> 0 | E36: =ROUND(E35-E34,2) -> 0 | F36: =ROUND(F35-F34,2) -> 0 | G36: =ROUND(G35-G34,2) -> 0 | H36: =ROUND(H35-H34,2) -> 0 | I36: =MAX(MAX(C36:H36),-MIN(C36:H36)) -> 0
A37: - Job-work Charges | B37: Published | C37: 9.1 | D37: 9.61 | E37: 12.19 | F37: 12.73 | G37: 11.56 | H37: 12.67
B38: Model | C38: =MIS!B20 -> 9.1 | D38: =MIS!C20 -> 9.61 | E38: =MIS!D20 -> 12.19 | F38: =MIS!F20 -> 12.73 | G38: =MIS!G20 -> 11.56 | H38: =MIS!H20 -> 12.67
B39: Variance | C39: =ROUND(C38-C37,2) -> 0 | D39: =ROUND(D38-D37,2) -> 0 | E39: =ROUND(E38-E37,2) -> 0 | F39: =ROUND(F38-F37,2) -> 0 | G39: =ROUND(G38-G37,2) -> 0 | H39: =ROUND(H38-H37,2) -> 0 | I39: =MAX(MAX(C39:H39),-MIN(C39:H39)) -> 0
A40: Total Net Variable Costs | B40: Published | C40: 99.34 | D40: 112.39 | E40: 151.18 | F40: 213.57 | G40: 182.23 | H40: 156.3
B41: Model | C41: =MIS!B21 -> 99.34 | D41: =MIS!C21 -> 112.39 | E41: =MIS!D21 -> 151.18 | F41: =MIS!F21 -> 213.57 | G41: =MIS!G21 -> 182.23 | H41: =MIS!H21 -> 156.3
B42: Variance | C42: =ROUND(C41-C40,2) -> 0 | D42: =ROUND(D41-D40,2) -> 0 | E42: =ROUND(E41-E40,2) -> 0 | F42: =ROUND(F41-F40,2) -> 0 | G42: =ROUND(G41-G40,2) -> 0 | H42: =ROUND(H41-H40,2) -> 0 | I42: =MAX(MAX(C42:H42),-MIN(C42:H42)) -> 0
A43: Contributions | B43: Published | C43: 13.06 | D43: 35.85 | E43: 51.28 | F43: 58.26 | G43: 50.51 | H43: 66.84
B44: Model | C44: =MIS!B22 -> 13.06 | D44: =MIS!C22 -> 35.85 | E44: =MIS!D22 -> 51.28 | F44: =MIS!F22 -> 58.26 | G44: =MIS!G22 -> 50.51 | H44: =MIS!H22 -> 66.84
B45: Variance | C45: =ROUND(C44-C43,2) -> 0 | D45: =ROUND(D44-D43,2) -> 0 | E45: =ROUND(E44-E43,2) -> 0 | F45: =ROUND(F44-F43,2) -> 0 | G45: =ROUND(G44-G43,2) -> 0 | H45: =ROUND(H44-H43,2) -> 0 | I45: =MAX(MAX(C45:H45),-MIN(C45:H45)) -> 0
A46: Administrative Expenses | B46: Published | C46: 3.21 | D46: 4.13 | E46: 4.5 | F46: 7.52 | G46: 6.07 | H46: 7.13
B47: Model | C47: =MIS!B25 -> 3.21 | D47: =MIS!C25 -> 4.13 | E47: =MIS!D25 -> 4.5 | F47: =MIS!F25 -> 7.52 | G47: =MIS!G25 -> 6.07 | H47: =MIS!H25 -> 7.13
B48: Variance | C48: =ROUND(C47-C46,2) -> 0 | D48: =ROUND(D47-D46,2) -> 0 | E48: =ROUND(E47-E46,2) -> 0 | F48: =ROUND(F47-F46,2) -> 0 | G48: =ROUND(G47-G46,2) -> 0 | H48: =ROUND(H47-H46,2) -> 0 | I48: =MAX(MAX(C48:H48),-MIN(C48:H48)) -> 0
A49: Material Consumed - Repair & maintt. | B49: Published | C49: 1.38 | D49: 2.28 | E49: 2.31 | F49: 3.41 | G49: 2.28 | H49: 1.97
B50: Model | C50: =MIS!B26 -> 1.38 | D50: =MIS!C26 -> 2.28 | E50: =MIS!D26 -> 2.31 | F50: =MIS!F26 -> 3.41 | G50: =MIS!G26 -> 2.28 | H50: =MIS!H26 -> 1.97
B51: Variance | C51: =ROUND(C50-C49,2) -> 0 | D51: =ROUND(D50-D49,2) -> 0 | E51: =ROUND(E50-E49,2) -> 0 | F51: =ROUND(F50-F49,2) -> 0 | G51: =ROUND(G50-G49,2) -> 0 | H51: =ROUND(H50-H49,2) -> 0 | I51: =MAX(MAX(C51:H51),-MIN(C51:H51)) -> 0
A52: Other Manufacturing Overhead (Fixed) | B52: Published | C52: 4.62 | D52: 5.7 | E52: 5.93 | F52: 5.44 | G52: 4.71 | H52: 6.92
B53: Model | C53: =MIS!B27 -> 4.62 | D53: =MIS!C27 -> 5.7 | E53: =MIS!D27 -> 5.93 | F53: =MIS!F27 -> 5.44 | G53: =MIS!G27 -> 4.71 | H53: =MIS!H27 -> 6.92
B54: Variance | C54: =ROUND(C53-C52,2) -> 0 | D54: =ROUND(D53-D52,2) -> 0 | E54: =ROUND(E53-E52,2) -> 0 | F54: =ROUND(F53-F52,2) -> 0 | G54: =ROUND(G53-G52,2) -> 0 | H54: =ROUND(H53-H52,2) -> 0 | I54: =MAX(MAX(C54:H54),-MIN(C54:H54)) -> 0
A55: Salary & Wages | B55: Published | C55: 15.91 | D55: 12.37 | E55: 14.85 | F55: 16.85 | G55: 15.87 | H55: 16.61
B56: Model | C56: =MIS!B28 -> 15.91 | D56: =MIS!C28 -> 12.37 | E56: =MIS!D28 -> 14.85 | F56: =MIS!F28 -> 16.85 | G56: =MIS!G28 -> 15.87 | H56: =MIS!H28 -> 16.61
B57: Variance | C57: =ROUND(C56-C55,2) -> 0 | D57: =ROUND(D56-D55,2) -> 0 | E57: =ROUND(E56-E55,2) -> 0 | F57: =ROUND(F56-F55,2) -> 0 | G57: =ROUND(G56-G55,2) -> 0 | H57: =ROUND(H56-H55,2) -> 0 | I57: =MAX(MAX(C57:H57),-MIN(C57:H57)) -> 0
A58: - Power & Fuel (Fixed Part - Max Demand Charges) | B58: Published | C58: 5.58 | D58: 5.88 | E58: 5.56 | F58: 5.53 | G58: 7.21 | H58: 7.25
B59: Model | C59: =MIS!B29 -> 5.58 | D59: =MIS!C29 -> 5.88 | E59: =MIS!D29 -> 5.56 | F59: =MIS!F29 -> 5.53 | G59: =MIS!G29 -> 7.21 | H59: =MIS!H29 -> 7.25
B60: Variance | C60: =ROUND(C59-C58,2) -> 0 | D60: =ROUND(D59-D58,2) -> 0 | E60: =ROUND(E59-E58,2) -> 0 | F60: =ROUND(F59-F58,2) -> 0 | G60: =ROUND(G59-G58,2) -> 0 | H60: =ROUND(H59-H58,2) -> 0 | I60: =MAX(MAX(C60:H60),-MIN(C60:H60)) -> 0
A61: Selling Expenses | B61: Published | C61: 0 | D61: 0 | E61: 0 | F61: 0 | G61: 0 | H61: 3.22
B62: Model | C62: =MIS!B30 -> 0 | D62: =MIS!C30 -> 0 | E62: =MIS!D30 -> 0 | F62: =MIS!F30 -> 0 | G62: =MIS!G30 -> 0 | H62: =MIS!H30 -> 3.22
B63: Variance | C63: =ROUND(C62-C61,2) -> 0 | D63: =ROUND(D62-D61,2) -> 0 | E63: =ROUND(E62-E61,2) -> 0 | F63: =ROUND(F62-F61,2) -> 0 | G63: =ROUND(G62-G61,2) -> 0 | H63: =ROUND(H62-H61,2) -> 0 | I63: =MAX(MAX(C63:H63),-MIN(C63:H63)) -> 0
A64: Total Fixed Costs | B64: Published | C64: 30.7 | D64: 30.36 | E64: 33.15 | F64: 38.75 | G64: 36.14 | H64: 43.1
B65: Model | C65: =MIS!B31 -> 30.7 | D65: =MIS!C31 -> 30.36 | E65: =MIS!D31 -> 33.15 | F65: =MIS!F31 -> 38.75 | G65: =MIS!G31 -> 36.14 | H65: =MIS!H31 -> 43.1
B66: Variance | C66: =ROUND(C65-C64,2) -> 0 | D66: =ROUND(D65-D64,2) -> 0 | E66: =ROUND(E65-E64,2) -> 0 | F66: =ROUND(F65-F64,2) -> 0 | G66: =ROUND(G65-G64,2) -> 0 | H66: =ROUND(H65-H64,2) -> 0 | I66: =MAX(MAX(C66:H66),-MIN(C66:H66)) -> 0
A67: NET PROFIT FROM OPERATIONS | B67: Published | C67: -17.64 | D67: 5.49 | E67: 18.13 | F67: 19.51 | G67: 14.37 | H67: 23.74
B68: Model | C68: =MIS!B32 -> -17.64 | D68: =MIS!C32 -> 5.49 | E68: =MIS!D32 -> 18.13 | F68: =MIS!F32 -> 19.51 | G68: =MIS!G32 -> 14.37 | H68: =MIS!H32 -> 23.74
B69: Variance | C69: =ROUND(C68-C67,2) -> 0 | D69: =ROUND(D68-D67,2) -> 0 | E69: =ROUND(E68-E67,2) -> 0 | F69: =ROUND(F68-F67,2) -> 0 | G69: =ROUND(G68-G67,2) -> 0 | H69: =ROUND(H68-H67,2) -> 0 | I69: =MAX(MAX(C69:H69),-MIN(C69:H69)) -> 0
A70: Net Income from Storage Facility Service Charges | B70: Published | C70: 6.89 | D70: 6.89 | E70: 6.89 | F70: 6.95 | G70: 7.91 | H70: 7.39
B71: Model | C71: =MIS!B36 -> 6.89 | D71: =MIS!C36 -> 6.89 | E71: =MIS!D36 -> 6.89 | F71: =MIS!F36 -> 6.95 | G71: =MIS!G36 -> 7.91 | H71: =MIS!H36 -> 7.39
B72: Variance | C72: =ROUND(C71-C70,2) -> 0 | D72: =ROUND(D71-D70,2) -> 0 | E72: =ROUND(E71-E70,2) -> 0 | F72: =ROUND(F71-F70,2) -> 0 | G72: =ROUND(G71-G70,2) -> 0 | H72: =ROUND(H71-H70,2) -> 0 | I72: =MAX(MAX(C72:H72),-MIN(C72:H72)) -> 0
A73: EBITDA | B73: Published | C73: -10.75 | D73: 12.38 | E73: 25.02 | F73: 26.46 | G73: 22.28 | H73: 31.13
B74: Model | C74: =MIS!B37 -> -10.75 | D74: =MIS!C37 -> 12.38 | E74: =MIS!D37 -> 25.02 | F74: =MIS!F37 -> 26.46 | G74: =MIS!G37 -> 22.28 | H74: =MIS!H37 -> 31.13
B75: Variance | C75: =ROUND(C74-C73,2) -> 0 | D75: =ROUND(D74-D73,2) -> 0 | E75: =ROUND(E74-E73,2) -> 0 | F75: =ROUND(F74-F73,2) -> 0 | G75: =ROUND(G74-G73,2) -> 0 | H75: =ROUND(H74-H73,2) -> 0 | I75: =MAX(MAX(C75:H75),-MIN(C75:H75)) -> 0
A76: PBT 2026-27 | B76: Published | C76: -10.75 | D76: 12.38 | E76: 25.02 | F76: 26.46 | G76: 22.28 | H76: 31.13
B77: Model | C77: =MIS!B40 -> -10.75 | D77: =MIS!C40 -> 12.38 | E77: =MIS!D40 -> 25.02 | F77: =MIS!F40 -> 26.46 | G77: =MIS!G40 -> 22.28 | H77: =MIS!H40 -> 31.13
B78: Variance | C78: =ROUND(C77-C76,2) -> 0 | D78: =ROUND(D77-D76,2) -> 0 | E78: =ROUND(E77-E76,2) -> 0 | F78: =ROUND(F77-F76,2) -> 0 | G78: =ROUND(G77-G76,2) -> 0 | H78: =ROUND(H77-H76,2) -> 0 | I78: =MAX(MAX(C78:H78),-MIN(C78:H78)) -> 0
A80: Max absolute variance (all lines) | C80: =MAX(I4:I78) -> 0
A81: Status (tolerance 0.02 = rounding) | C81: =IF(C80<=0.02,"TIES TO PUBLISHED MIS","REVIEW VARIANCES") -> TIES TO PUBLISHED MIS

Sheet PY_COMPARE
A1: COMPARISON WITH PREVIOUS YEARS (as per published MIS; 2026-27 linked live)
A3: 2026-27 (live from MIS)
A4: PARTICULARS | B4: APR | C4: MAY | D4: JUN | E4: 1st Qtr | F4: JUL | G4: AUG | H4: SEP | I4: 2nd Qtr | J4: 3rd Qtr | K4: 4th Qtr | L4: Total | M4: Avg/Month
A5: Production (MT) | B5: =MIS!B45 -> 33.56 | C5: =MIS!C45 -> 84.62 | D5: =MIS!D45 -> 83 | E5: =MIS!E45 -> 201.18 | F5: =MIS!F45 -> 84.62 | G5: =MIS!G45 -> 77.44 | H5: =MIS!H45 -> 105.48 | I5: =MIS!I45 -> 267.54 | J5: =MIS!M45 -> 0 | K5: =MIS!Q45 -> 0 | L5: =MIS!R45 -> 468.72 | M5: =L5/12 -> 39.06
A6: Despatch (MT) | B6: =MIS!B46 -> 50.44 | C6: =MIS!C46 -> 36.67 | D6: =MIS!D46 -> 106.07 | E6: =MIS!E46 -> 193.18 | F6: =MIS!F46 -> 36.67 | G6: =MIS!G46 -> 94.58 | H6: =MIS!H46 -> 89.34 | I6: =MIS!I46 -> 220.59 | J6: =MIS!M46 -> 0 | K6: =MIS!Q46 -> 0 | L6: =MIS!R46 -> 413.77 | M6: =L6/12 -> 34.480833
A7: In-house Rejections (MT) | B7: =MIS!B47 -> 5.73 | C7: =MIS!C47 -> 6.9 | D7: =MIS!D47 -> 9.39 | E7: =MIS!E47 -> 22.02 | F7: =MIS!F47 -> 6.9 | G7: =MIS!G47 -> 9.16 | H7: =MIS!H47 -> 9.04 | I7: =MIS!I47 -> 25.1 | J7: =MIS!M47 -> 0 | K7: =MIS!Q47 -> 0 | L7: =MIS!R47 -> 47.12 | M7: =L7/12 -> 3.9266667
A8: Sales net of Return (ex GST, O/Income) | B8: =MIS!B49 -> 127.48 | C8: =MIS!C49 -> 150.3 | D8: =MIS!D49 -> 206.48 | E8: =MIS!E49 -> 484.26 | F8: =MIS!F49 -> 275.62 | G8: =MIS!G49 -> 229.24 | H8: =MIS!H49 -> 217.78 | I8: =MIS!I49 -> 722.64 | J8: =MIS!M49 -> 0 | K8: =MIS!Q49 -> 0 | L8: =MIS!R49 -> 1206.9 | M8: =L8/12 -> 100.575
A9: Collections (incl GST) | B9: =MIS!B50 -> 149.75 | C9: =MIS!C50 -> 126.8 | D9: =MIS!D50 -> 238.95 | E9: =MIS!E50 -> 515.5 | F9: =MIS!F50 -> 269.64 | G9: =MIS!G50 -> 302.91 | H9: =MIS!H50 -> 284.24 | I9: =MIS!I50 -> 856.79 | J9: =MIS!M50 -> 0 | K9: =MIS!Q50 -> 0 | L9: =MIS!R50 -> 1372.29 | M9: =L9/12 -> 114.3575
A10: PBT | B10: =MIS!B51 -> -10.75 | C10: =MIS!C51 -> 12.38 | D10: =MIS!D51 -> 25.02 | E10: =MIS!E51 -> 26.65 | F10: =MIS!F51 -> 26.46 | G10: =MIS!G51 -> 22.28 | H10: =MIS!H51 -> 31.13 | I10: =MIS!I51 -> 79.87 | J10: =MIS!M51 -> 0 | K10: =MIS!Q51 -> 0 | L10: =MIS!R51 -> 106.52 | M10: =L10/12 -> 8.8766667
A11: Net Profit from Operations | B11: =MIS!B52 -> -17.64 | C11: =MIS!C52 -> 5.49 | D11: =MIS!D52 -> 18.13 | E11: =MIS!E52 -> 5.98 | F11: =MIS!F52 -> 19.51 | G11: =MIS!G52 -> 14.37 | H11: =MIS!H52 -> 23.74 | I11: =MIS!I52 -> 57.62 | J11: =MIS!M52 -> 0 | K11: =MIS!Q52 -> 0 | L11: =MIS!R52 -> 63.6 | M11: =L11/12 -> 5.3
A12: Income from Storage Facility | B12: =MIS!B53 -> 6.89 | C12: =MIS!C53 -> 6.89 | D12: =MIS!D53 -> 6.89 | E12: =MIS!E53 -> 20.67 | F12: =MIS!F53 -> 6.95 | G12: =MIS!G53 -> 7.91 | H12: =MIS!H53 -> 7.39 | I12: =MIS!I53 -> 22.25 | J12: =MIS!M53 -> 0 | K12: =MIS!Q53 -> 0 | L12: =MIS!R53 -> 42.92 | M12: =L12/12 -> 3.5766667
A14: 2025-26
A15: PARTICULARS | B15: APR | C15: MAY | D15: JUN | E15: 1st Qtr | F15: JUL | G15: AUG | H15: SEP | I15: 2nd Qtr | J15: 3rd Qtr | K15: 4th Qtr | L15: Total | M15: Avg/Month
A16: Production (MT) | B16: 136.43 | C16: 136.51 | D16: 117.91 | E16: 390.85 | F16: 66.14 | G16: 118.32 | H16: 90.49 | I16: 274.95 | J16: 289.12 | K16: 112.1 | L16: 1067.02 | M16: =L16/12 -> 88.918333
A17: Despatch (MT) | B17: 112.94 | C17: 163.13 | D17: 109.15 | E17: 385.22 | F17: 116.85 | G17: 98.79 | H17: 82 | I17: 297.64 | J17: 342.03 | K17: 110.35 | L17: 1135.24 | M17: =L17/12 -> 94.603333
A18: In-house Rejections (MT) | B18: 6.36 | C18: 6.68 | D18: 5.56 | E18: 18.6 | F18: 9.79 | G18: 7.89 | H18: 5.15 | I18: 22.83 | J18: 22.25 | K18: 8.36 | L18: 72.04 | M18: =L18/12 -> 6.0033333
A19: Sales net of Return (ex GST, O/Income) | B19: 236.73 | C19: 364.16 | D19: 238.11 | E19: 839 | F19: 248.19 | G19: 217.83 | H19: 170.98 | I19: 637 | J19: 784.51 | K19: 228.87 | L19: 2489.38 | M19: =L19/12 -> 207.44833
A20: Collections (incl GST) | B20: 355.44 | C20: 307.29 | D20: 280.64 | E20: 943.37 | F20: 282.36 | G20: 259.57 | H20: 227.97 | I20: 769.9 | J20: 899.18 | K20: 358.13 | L20: 2970.58 | M20: =L20/12 -> 247.54833
A21: PBT | B21: 19.43 | C21: 53.85 | D21: 20.71 | E21: 93.99 | F21: 18.58 | G21: 17.01 | H21: 11.21 | I21: 46.8 | J21: 61.01 | K21: -19.37 | L21: 182.43 | M21: =L21/12 -> 15.2025
A22: Net Profit from Operations | B22: 12.87 | C22: 47.27 | D22: 14.13 | E22: 74.27 | F22: 12 | G22: 11.84 | H22: 3.13 | I22: 26.97 | J22: 40.34 | K22: -40.04 | L22: 101.54 | M22: =L22/12 -> 8.4616667
A23: Income from Storage Facility | B23: 6.56 | C23: 6.58 | D23: 6.58 | E23: 19.72 | F23: 6.58 | G23: 5.17 | H23: 8.08 | I23: 19.83 | J23: 20.67 | K23: 20.67 | L23: 80.89 | M23: =L23/12 -> 6.7408333
A25: 2024-25
A26: PARTICULARS | B26: APR | C26: MAY | D26: JUN | E26: 1st Qtr | F26: JUL | G26: AUG | H26: SEP | I26: 2nd Qtr | J26: 3rd Qtr | K26: 4th Qtr | L26: Total | M26: Avg/Month
A27: Production (MT) | B27: 40.62 | C27: 73.14 | D27: 69.12 | E27: 182.88 | F27: 85.86 | G27: 90.06 | H27: 55.05 | I27: 230.97 | J27: 243.02 | K27: 302.73 | L27: 959.6 | M27: =L27/12 -> 79.966667
A28: Despatch (MT) | B28: 56.02 | C28: 49.56 | D28: 81.16 | E28: 186.74 | F28: 74.52 | G28: 82.03 | H28: 75.21 | I28: 231.76 | J28: 199.55 | K28: 347.91 | L28: 965.96 | M28: =L28/12 -> 80.496667
A29: In-house Rejections (MT) | B29: 3.28 | C29: 4.06 | D29: 7.4 | E29: 14.74 | F29: 3.8 | G29: 3.49 | H29: 3.76 | I29: 11.05 | J29: 9 | K29: 17.1 | L29: 51.89 | M29: =L29/12 -> 4.3241667
A30: Sales net of Return (ex GST, O/Income) | B30: 122.88 | C30: 92.55 | D30: 171.82 | E30: 387.25 | F30: 150.66 | G30: 173.4 | H30: 152.25 | I30: 476.31 | J30: 439.37 | K30: 650.58 | L30: 1953.51 | M30: =L30/12 -> 162.7925
A31: Collections (incl GST) | B31: 116.42 | C31: 153.1 | D31: 165.47 | E31: 434.99 | F31: 228.5 | G31: 143.24 | H31: 166.46 | I31: 538.2 | J31: 465.28 | K31: 684.39 | L31: 2122.86 | M31: =L31/12 -> 176.905
A32: PBT | B32: 6.45 | C32: 2.65 | D32: 2.51 | E32: 11.61 | F32: 0.65 | G32: 5.73 | H32: -3.39 | I32: 2.99 | J32: 30.82 | K32: 82.5 | L32: 127.93 | M32: =L32/12 -> 10.660833
A33: Net Profit from Operations | B33: 0.37 | C33: -3.43 | D33: -2.85 | E33: -5.91 | F33: -6.23 | G33: -0.41 | H33: -8.49 | I33: -15.13 | J33: 18.16 | K33: 57.1 | L33: 54.23 | M33: =L33/12 -> 4.5191667
A34: Income from Storage Facility | B34: 6.08 | C34: 6.08 | D34: 5.36 | E34: 17.52 | F34: 6.88 | G34: 6.14 | H34: 5.1 | I34: 18.12 | J34: 12.66 | K34: 25.4 | L34: 73.7 | M34: =L34/12 -> 6.1416667
A36: 2023-24
A37: PARTICULARS | B37: APR | C37: MAY | D37: JUN | E37: 1st Qtr | F37: JUL | G37: AUG | H37: SEP | I37: 2nd Qtr | J37: 3rd Qtr | K37: 4th Qtr | L37: Total | M37: Avg/Month
A38: Production (MT) | B38: 75.11 | C38: 12.03 | D38: 52.1 | E38: 139.24 | F38: 112.13 | G38: 107.08 | H38: 84.64 | I38: 303.85 | J38: 271.9 | K38: 235.11 | L38: 950.1 | M38: =L38/12 -> 79.175
A39: Despatch (MT) | B39: 68.03 | C39: 58.52 | D39: 14.31 | E39: 140.86 | F39: 99.37 | G39: 97.33 | H39: 100.89 | I39: 297.59 | J39: 254.19 | K39: 274.18 | L39: 966.82 | M39: =L39/12 -> 80.568333
A40: In-house Rejections (MT) | B40: 5.05 | C40: 2.1 | D40: 2.01 | E40: 9.16 | F40: 5.98 | G40: 7.44 | H40: 4.76 | I40: 18.18 | J40: 11.97 | K40: 22.79 | L40: 62.1 | M40: =L40/12 -> 5.175
A41: Sales net of Return (ex GST, O/Income) | B41: 190.22 | C41: 154.24 | D41: 25.11 | E41: 369.57 | F41: 220.08 | G41: 204.74 | H41: 209.19 | I41: 634.01 | J41: 485.64 | K41: 576.92 | L41: 2066.14 | M41: =L41/12 -> 172.17833
A42: Collections (incl GST) | B42: 289.76 | C42: 152.09 | D42: 90.74 | E42: 532.59 | F42: 92.89 | G42: 341 | H42: 244.59 | I42: 678.48 | J42: 541.48 | K42: 693.78 | L42: 2446.33 | M42: =L42/12 -> 203.86083
A43: PBT | B43: 11.56 | C43: 4.13 | D43: -24.14 | E43: -8.45 | F43: 21.87 | G43: 37.93 | H43: 39.33 | I43: 99.13 | J43: 35.37 | K43: 31.81 | L43: 157.86 | M43: =L43/12 -> 13.155
A44: Net Profit from Operations | B44: 6.7 | C44: -1.29 | D44: -25.7 | E44: -20.29 | F44: 17.77 | G44: 33.9 | H44: 35.23 | I44: 86.9 | J44: 26.78 | K44: 25.98 | L44: 119.37 | M44: =L44/12 -> 9.9475
A45: Income from Storage Facility | B45: 4.86 | C45: 5.42 | D45: 1.56 | E45: 11.84 | F45: 4.91 | G45: 4.91 | H45: 4.91 | I45: 14.73 | J45: 13.88 | K45: 18.31 | L45: 58.76 | M45: =L45/12 -> 4.8966667
